Workbook
Name _Hlk161219787: 'Nota 3'!$B$34
Name _Hlk161831706: 'Nota 3'!$B$58
Name _Hlk161832494: 'Nota 5 Txt'!$B$224
Name _Hlk161986056: 'Dictamen 1'!$B$23
Name _Hlk161986056: 'Dictamen 2'!#REF!
Name _Hlk161987517: 'Nota 3'!$B$33
Name _Hlk161988619: 'Nota 3'!$B$57
Name _TOC_250001: Datos!#REF!
Name _TOC_250001: CF!$B$10
Name OLE_LINK1: Datos!#REF!
Name OLE_LINK1: BG!$B$12

Sheet Datos
B2: Datos del documento
B4: Nombre Linea 1: | C4: Fideicomiso Irrevocable 4341
B5: Nombre Linea 2: | C5: Fideicomiso FORTMCK 19-12 Lomas Verdes
B6: Fecha del Balance: | C6: Al 31 de diciembre de 2024 y 2023
B7: Fecha del Estado de resultdos: | C7: Por los ejercicios terminados al 31 de diciembre de 2024 y 2023
B8: Año actual: | C8: 2024
B9: Año anterior: | C9: 2023
B10: Fecha del dictamen: | C10: 30 de abril de 2025
B11: =+CONCATENATE("Resultado de ",C9-1) -> Resultado de 2022 | C11: -292
C12: Fideicomiso por el año que terminó el 31 de diciembre de 2023
C13: estados financieros el 28 de abril de 2023
C14: Al 31 de diciembre de 2024 y 2023
C15: Los saldos por pagar al 31 de diciembre de 2024 y 2023
C16: El 27 de diciembre de 2022
C17: 1o de enero de 2024
C18: Al 31 de diciembre de 2024 y 2023
C19: El Fideicomiso al 31 de diciembre de 2024
C20: 1o de enero de 2023

Sheet Catálogo
A1: Cuenta | B1: Scta | C1: SSCta | D1: Descripción | F1: Rubro | G1: Nota
A2: 103 | B2: 0 | C2: 0 | D2: BANCOS | E2: 1030BANCOS | F2: #N/A
A3: 103 | B3: 1 | C3: 0 | D3: MONEDA NACIONAL | E3: 1031MONEDA NACIONAL | F3: #N/A
A4: 103 | B4: 1 | C4: 2 | D4: BBVA CTA 0116008208 | E4: 1031BBVA CTA 0116008208 | F4: Efectivo y equivalentes de efectivo | G4: Depósitos en cuenta de cheques
A5: 103 | B5: 1 | C5: 5 | D5: INVEX CTA 05661 COBRANZA | E5: 1031INVEX CTA 05661 COBRANZA | F5: Efectivo y equivalentes de efectivo | G5: Depósitos en cuenta de cheques
A6: 103 | B6: 1 | C6: 6 | D6: INVEX CTA 05662 RESERVA | E6: 1031INVEX CTA 05662 RESERVA | F6: Efectivo y equivalentes de efectivo | G6: Depósitos en cuenta de cheques
A7: 104 | B7: 0 | C7: 0 | D7: INVERSIONES SISTEMA FINANCIERO | E7: 1040INVERSIONES SISTEMA FINANCIERO | F7: #N/A
A8: 104 | B8: 1 | C8: 0 | D8: MONEDA NACIONAL | E8: 1041MONEDA NACIONAL | F8: #N/A
A9: 104 | B9: 1 | C9: 1 | D9: ACTINVER 8344681 CUENTA GENERAL | E9: 1041ACTINVER 8344681 CUENTA GENERAL | F9: Efectivo y equivalentes de efectivo | G9: =+'N4 Efectivo'!$E$11 -> Inversiones en valores realizables
A10: 104 | B10: 1 | C10: 2 | D10: ACTINVER 8344681 COMPLEMENTARIA | E10: 1041ACTINVER 8344681 COMPLEMENTARIA | F10: Efectivo y equivalentes de efectivo | G10: =+'N4 Efectivo'!$E$11 -> Inversiones en valores realizables
A11: 104 | B11: 1 | C11: 3 | D11: ACTINVER 5371322 CUENTA GENERAL | E11: 1041ACTINVER 5371322 CUENTA GENERAL | F11: Efectivo y equivalentes de efectivo | G11: =+'N4 Efectivo'!$E$11 -> Inversiones en valores realizables
A12: 104 | B12: 1 | C12: 4 | D12: ACTINVER CTA 5371322 COMPLEMENTARIA | E12: 1041ACTINVER CTA 5371322 COMPLEMENTARIA | F12: Efectivo y equivalentes de efectivo | G12: =+'N4 Efectivo'!$E$11 -> Inversiones en valores realizables
A13: 104 | B13: 1 | C13: 5 | D13: INVEX CTA 0705 COBRA INVER | E13: 1041INVEX CTA 0705 COBRA INVER | F13: Efectivo y equivalentes de efectivo | G13: =+'N4 Efectivo'!$E$11 -> Inversiones en valores realizables
A14: 104 | B14: 1 | C14: 6 | D14: INVEX CTA 0705 COBRA INVER COMPLEMENTARI | E14: 1041INVEX CTA 0705 COBRA INVER COMPLEMENTARI | F14: Efectivo y equivalentes de efectivo | G14: =+'N4 Efectivo'!$E$11 -> Inversiones en valores realizables
A15: 104 | B15: 1 | C15: 7 | D15: INVEX CTA 0732 RESERVA INVER | E15: 1041INVEX CTA 0732 RESERVA INVER | F15: Efectivo y equivalentes de efectivo | G15: =+'N4 Efectivo'!$E$11 -> Inversiones en valores realizables
A16: 104 | B16: 1 | C16: 8 | D16: INVEX CTA 0732 RESERVA INVER COMPLEMENTA | E16: 1041INVEX CTA 0732 RESERVA INVER COMPLEMENTA | F16: Efectivo y equivalentes de efectivo | G16: =+'N4 Efectivo'!$E$11 -> Inversiones en valores realizables
A17: 108 | B17: 0 | C17: 0 | D17: CLIENTES | E17: 1080CLIENTES | F17: #N/A
A18: 108 | B18: 1 | C18: 0 | D18: CLIENTES M.N. | E18: 1081CLIENTES M.N. | F18: #N/A
A19: 109 | B19: 0 | C19: 0 | D19: DEUDORES DIVERSOS | E19: 1090DEUDORES DIVERSOS | F19: #N/A
A20: 109 | B20: 1 | C20: 0 | D20: DEUDORES DIVERSOS M.N. | E20: 1091DEUDORES DIVERSOS M.N. | F20: Deudores diversos y otras cuentas por cobrar
A21: 113 | B21: 0 | C21: 0 | D21: ANTICIPO DE IMPUESTOS | E21: 1130ANTICIPO DE IMPUESTOS | F21: #N/A
A22: 113 | B22: 1 | C22: 0 | D22: ISR | E22: 1131ISR | F22: #N/A
A23: 113 | B23: 1 | C23: 1 | D23: ISR PAGO PROVISIONALES | E23: 1131ISR PAGO PROVISIONALES | F23: Impuestos por recuperar | G23: ISR Retenido
A24: 113 | B24: 1 | C24: 2 | D24: ISR RETENCIONES BANCOS | E24: 1131ISR RETENCIONES BANCOS | F24: Impuestos por recuperar | G24: ISR Retenido
A25: 114 | B25: 0 | C25: 0 | D25: IMPUESTOS A FAVOR | E25: 1140IMPUESTOS A FAVOR | F25: #N/A
A26: 114 | B26: 1 | C26: 0 | D26: IVA SALDO A FAVOR | E26: 1141IVA SALDO A FAVOR | F26: #N/A
A27: 114 | B27: 1 | C27: 1 | D27: IVA SALDO A FAVOR AL 16% | E27: 1141IVA SALDO A FAVOR AL 16% | F27: Inventarios inmobiliarios y costos pagados por anticipado | G27: Impuesto al Valor Agregado
A28: 115 | B28: 0 | C28: 0 | D28: IMPUESTOS A FAVOR NO CAUSADO | E28: 1150IMPUESTOS A FAVOR NO CAUSADO | F28: #N/A
A29: 115 | B29: 1 | C29: 0 | D29: IVA ACREDITABLE NO PAGADO | E29: 1151IVA ACREDITABLE NO PAGADO | F29: #N/A
A30: 115 | B30: 1 | C30: 1 | D30: IVA ACREDITABLE NO PAGADO AL 16% | E30: 1151IVA ACREDITABLE NO PAGADO AL 16% | F30: Deudores diversos y otras cuentas por cobrar
E31: 1180PAGOS ANTICIPADOS
E32: 1182PROVEEDORES
E33: 1182BANCO ACTINVER | F33: Inventarios inmobiliarios y costos pagados por anticipado | G33: =+'N5 Inventarios Inm(Tablas)'!$B$16 -> Otros pagos anticipados (v)
A34: 120 | B34: 0 | C34: 0 | D34: ANTICIPOS CONSTRUCCION | E34: 1200ANTICIPOS CONSTRUCCION | F34: #N/A
A35: 120 | B35: 1 | C35: 0 | D35: ANTICIPOS CONSTRUCCION M.N. | E35: 1201ANTICIPOS CONSTRUCCION M.N. | F35: Inventarios inmobiliarios y costos pagados por anticipado | G35: =+'N5 Inventarios Inm(Tablas)'!$B$16 -> Otros pagos anticipados (v)
A36: 121 | B36: 0 | C36: 0 | D36: TERRENOS | E36: 1210TERRENOS | F36: #N/A
A37: 121 | B37: 1 | C37: 0 | D37: INVERSIÓN | E37: 1211INVERSIÓN | F37: #N/A
A38: 121 | B38: 1 | C38: 1 | D38: TERRENO LOTE 18 0980616001000000 | E38: 1211TERRENO LOTE 18 0980616001000000 | F38: Inventarios inmobiliarios y costos pagados por anticipado | G38: =+'N5 Inventarios Inm(Tablas)'!$B$5 -> Terrenos (i)
A39: 121 | B39: 1 | C39: 2 | D39: TERRENO L-19 No, CAT. 0980616002000000 | E39: 1211TERRENO L-19 No, CAT. 0980616002000000 | F39: Inventarios inmobiliarios y costos pagados por anticipado | G39: =+'N5 Inventarios Inm(Tablas)'!$B$5 -> Terrenos (i)
A40: 121 | B40: 1 | C40: 3 | D40: TERRENO L-20 CLAVE No. 0980616003000000 | E40: 1211TERRENO L-20 CLAVE No. 0980616003000000 | F40: Inventarios inmobiliarios y costos pagados por anticipado | G40: =+'N5 Inventarios Inm(Tablas)'!$B$5 -> Terrenos (i)
A41: 121 | B41: 1 | C41: 4 | D41: TERRENO MADIN CLAVE No: 1000676303000000 | E41: 1211TERRENO MADIN CLAVE No: 1000676303000000 | F41: Inventarios inmobiliarios y costos pagados por anticipado | G41: =+'N5 Inventarios Inm(Tablas)'!$B$5 -> Terrenos (i)
A42: 123 | B42: 0 | C42: 0 | D42: CONSTRUCCIONES EN PROCESO | E42: 1230CONSTRUCCIONES EN PROCESO | F42: #N/A
A43: 123 | B43: 4 | C43: 0 | D43: SUBCONTRATO (HARD-COST) | E43: 1234SUBCONTRATO (HARD-COST) | F43: #N/A
A44: 123 | B44: 4 | C44: 1 | D44: PRELIMINARES EDIFICACIÓN | E44: 1234PRELIMINARES EDIFICACIÓN | F44: Inventarios inmobiliarios y costos pagados por anticipado | G44: =+'N5 Inventarios Inm(Tablas)'!$B$9 -> Construcción en proceso (ii)
A45: 123 | B45: 4 | C45: 25 | D45: PAVIMENTACIÓN | E45: 1234PAVIMENTACIÓN | F45: Inventarios inmobiliarios y costos pagados por anticipado | G45: =+'N5 Inventarios Inm(Tablas)'!$B$9 -> Construcción en proceso (ii)
A46: 123 | B46: 4 | C46: 26 | D46: INSTALACIÓN ELÉCTRICA | E46: 1234INSTALACIÓN ELÉCTRICA | F46: Inventarios inmobiliarios y costos pagados por anticipado | G46: =+'N5 Inventarios Inm(Tablas)'!$B$9 -> Construcción en proceso (ii)
A47: 123 | B47: 6 | C47: 0 | D47: ADMINISTRATIVOS | E47: 1236ADMINISTRATIVOS | F47: #N/A
A48: 123 | B48: 6 | C48: 2 | D48: HONORARIOS PERSONAS MORALES | E48: 1236HONORARIOS PERSONAS MORALES | F48: Inventarios inmobiliarios y costos pagados por anticipado | G48: =+'N5 Inventarios Inm(Tablas)'!$B$11 -> Gastos administrativos y de comercialización (iv)
A49: 123 | B49: 6 | C49: 6 | D49: HONORARIOS PERSONAS FISICAS | E49: 1236HONORARIOS PERSONAS FISICAS | F49: Inventarios inmobiliarios y costos pagados por anticipado | G49: =+'N5 Inventarios Inm(Tablas)'!$B$11 -> Gastos administrativos y de comercialización (iv)
A50: 123 | B50: 6 | C50: 14 | D50: PREDIAL Y AGUA | E50: 1236PREDIAL Y AGUA | F50: Inventarios inmobiliarios y costos pagados por anticipado | G50: =+'N5 Inventarios Inm(Tablas)'!$B$11 -> Gastos administrativos y de comercialización (iv)
A51: 123 | B51: 7 | C51: 0 | D51: PRE Y POST OPERATIVOS (SOFT-COST) | E51: 1237PRE Y POST OPERATIVOS (SOFT-COST) | F51: #N/A
A52: 123 | B52: 7 | C52: 1 | D52: TERRENO | E52: 1237TERRENO | F52: Inventarios inmobiliarios y costos pagados por anticipado | G52: =+'N5 Inventarios Inm(Tablas)'!$B$10 -> Gastos legales, financieros y por trámites (iii)
A53: 123 | B53: 7 | C53: 2 | D53: COMPRA DE TERRENO | E53: 1237COMPRA DE TERRENO | F53: Inventarios inmobiliarios y costos pagados por anticipado | G53: =+'N5 Inventarios Inm(Tablas)'!$B$10 -> Gastos legales, financieros y por trámites (iii)
A54: 123 | B54: 7 | C54: 3 | D54: ESTUDIOS | E54: 1237ESTUDIOS | F54: Inventarios inmobiliarios y costos pagados por anticipado | G54: =+'N5 Inventarios Inm(Tablas)'!$B$10 -> Gastos legales, financieros y por trámites (iii)
A55: 123 | B55: 7 | C55: 4 | D55: TRAMITES MUNICIPALES | E55: 1237TRAMITES MUNICIPALES | F55: Inventarios inmobiliarios y costos pagados por anticipado | G55: =+'N5 Inventarios Inm(Tablas)'!$B$10 -> Gastos legales, financieros y por trámites (iii)
A56: 123 | B56: 7 | C56: 5 | D56: TRAMITES ESTATALES | E56: 1237TRAMITES ESTATALES | F56: Inventarios inmobiliarios y costos pagados por anticipado | G56: =+'N5 Inventarios Inm(Tablas)'!$B$10 -> Gastos legales, financieros y por trámites (iii)
A57: 123 | B57: 7 | C57: 6 | D57: TRAMITES FEDERALES | E57: 1237TRAMITES FEDERALES | F57: Inventarios inmobiliarios y costos pagados por anticipado | G57: =+'N5 Inventarios Inm(Tablas)'!$B$10 -> Gastos legales, financieros y por trámites (iii)
A58: 123 | B58: 7 | C58: 7 | D58: ANTEPPROYECTO | E58: 1237ANTEPPROYECTO | F58: Inventarios inmobiliarios y costos pagados por anticipado | G58: =+'N5 Inventarios Inm(Tablas)'!$B$10 -> Gastos legales, financieros y por trámites (iii)
A59: 123 | B59: 7 | C59: 8 | D59: PROYECTO EJECUTIVO | E59: 1237PROYECTO EJECUTIVO | F59: Inventarios inmobiliarios y costos pagados por anticipado | G59: =+'N5 Inventarios Inm(Tablas)'!$B$10 -> Gastos legales, financieros y por trámites (iii)
A60: 123 | B60: 7 | C60: 9 | D60: INGENIERIAS | E60: 1237INGENIERIAS | F60: Inventarios inmobiliarios y costos pagados por anticipado | G60: =+'N5 Inventarios Inm(Tablas)'!$B$10 -> Gastos legales, financieros y por trámites (iii)
A61: 123 | B61: 7 | C61: 10 | D61: SERVICIOS | E61: 1237SERVICIOS | F61: Inventarios inmobiliarios y costos pagados por anticipado | G61: =+'N5 Inventarios Inm(Tablas)'!$B$10 -> Gastos legales, financieros y por trámites (iii)
A62: 123 | B62: 7 | C62: 11 | D62: FINANCIEROS | E62: 1237FINANCIEROS | F62: Inventarios inmobiliarios y costos pagados por anticipado | G62: =+'N5 Inventarios Inm(Tablas)'!$B$10 -> Gastos legales, financieros y por trámites (iii)
A63: 123 | B63: 7 | C63: 12 | D63: ADMINISTRATIVOS DE OBRA | E63: 1237ADMINISTRATIVOS DE OBRA | F63: Inventarios inmobiliarios y costos pagados por anticipado | G63: =+'N5 Inventarios Inm(Tablas)'!$B$10 -> Gastos legales, financieros y por trámites (iii)
... A65: 123 | B65: 7 | C65: 18 | D65: COMERCIALIZACION PREOPERATIVOS | E65: 1237COMERCIALIZACION PREOPERATIVOS | F65: Inventarios inmobiliarios y costos pagados por anticipado | G65: =+'N5 Inventarios Inm(Tablas)'!$B$10 -> Gastos legales, financieros y por trámites (iii)
A67: 123 | B67: 9 | C67: 0 | D67: COMERCIALIZACION/FACTURACION | E67: 1239COMERCIALIZACION/FACTURACION | F67: #N/A
A68: 123 | B68: 9 | C68: 1 | D68: COMERCIALIZACION | E68: 1239COMERCIALIZACION. | F68: Inventarios inmobiliarios y costos pagados por anticipado | G68: =+'N5 Inventarios Inm(Tablas)'!$B$11 -> Gastos administrativos y de comercialización (iv)
E69: 1239 COMERCIALIZACION. | F69: #N/A
E70: 1239COMERCIALIZACION | F70: Inventarios inmobiliarios y costos pagados por anticipado | G70: =+'N5 Inventarios Inm(Tablas)'!$B$11 -> Gastos administrativos y de comercialización (iv)
A71: 121 | B71: 1 | C71: 1 | D71: TERRENO L-18 0980616001000000 | E71: 1211TERRENO L-18 0980616001000000 | F71: Inventarios inmobiliarios y costos pagados por anticipado | G71: =+'N5 Inventarios Inm(Tablas)'!$B$5 -> Terrenos (i)
A72: 123 | B72: 4 | C72: 24 | D72: PRELIMINARES URBANIZACIÓN | E72: 1234PRELIMINARES URBANIZACIÓN | F72: Inventarios inmobiliarios y costos pagados por anticipado | G72: =+'N5 Inventarios Inm(Tablas)'!$B$9 -> Construcción en proceso (ii)
A73: 123 | B73: 7 | C73: 24 | D73: GASTOS NO DEDUCIBLES | E73: 1237GASTOS NO DEDUCIBLES | F73: Inventarios inmobiliarios y costos pagados por anticipado | G73: =+'N5 Inventarios Inm(Tablas)'!$B$9 -> Construcción en proceso (ii)
A74: 123 | B74: 7 | C74: 123 | D74: GASTOS ADMINISTRATIVOS OBRA | E74: 1237GASTOS ADMINISTRATIVOS OBRA | F74: Inventarios inmobiliarios y costos pagados por anticipado | G74: =+'N5 Inventarios Inm(Tablas)'!$B$9 -> Construcción en proceso (ii)
A75: 125 | B75: 0 | C75: 0 | D75: EQUIPO DE COMPUTO | E75: 1250EQUIPO DE COMPUTO | F75: #N/A
A76: 125 | B76: 1 | C76: 0 | D76: INVERSION EQUIPO DE COMPUTO | E76: 1251INVERSION EQUIPO DE COMPUTO | F76: #N/A
A77: 125 | B77: 1 | C77: 1 | D77: INVERSIÓN EQP COMPUTO | E77: 1251INVERSIÓN EQP COMPUTO | F77: Mobiliario y equipo, neto
A78: 125 | B78: 1 | C78: 2 | D78: DEPRECIACIÓN EQP COMPUTO | E78: 1251DEPRECIACIÓN EQP COMPUTO | F78: Mobiliario y equipo, neto
A79: 124 | B79: 0 | C79: 0 | D79: MOBILIARIO Y EQUIPO DE OFICINA | E79: 1240MOBILIARIO Y EQUIPO DE OFICINA
A80: 124 | B80: 1 | C80: 0 | D80: INVERSIÓN | E80: 1241INVERSIÓN
A81: 124 | B81: 1 | C81: 1 | D81: MOBILIARIO Y EQP DE OFICINA | E81: 1241MOBILIARIO Y EQP DE OFICINA | F81: Mobiliario y equipo, neto
A82: 124 | B82: 2 | C82: 0 | D82: DEPRECIACION MOB Y EQUIPO DE OFICINA | E82: 1242DEPRECIACION MOB Y EQUIPO DE OFICINA | F82: Mobiliario y equipo, neto
A83: 126 | B83: 0 | C83: 0 | D83: EQUIPO DE VIDEO VIGILANCIA | E83: 1260EQUIPO DE VIDEO VIGILANCIA
A84: 126 | B84: 1 | C84: 0 | D84: INVERSION | E84: 1261INVERSION
A85: 126 | B85: 1 | C85: 1 | D85: CIRCUITO CERRADO DE TV | E85: 1261CIRCUITO CERRADO DE TV | F85: Mobiliario y equipo, neto
A86: 126 | B86: 2 | C86: 0 | D86: DEPRECIACION EQP DE VIDEO VIGILANCIA | E86: 1262DEPRECIACION EQP DE VIDEO VIGILANCIA | F86: Mobiliario y equipo, neto
A87: 173 | B87: 0 | C87: 0 | D87: DEPOSITOS EN GARANTIA | E87: 1730DEPOSITOS EN GARANTIA | F87: #N/A
A88: 173 | B88: 1 | C88: 0 | D88: DEPOSITOS EN GARANTIA M.N. | E88: 1731DEPOSITOS EN GARANTIA M.N. | F88: Inventarios inmobiliarios y costos pagados por anticipado | G88: =+'N5 Inventarios Inm(Tablas)'!$B$16 -> Otros pagos anticipados (v)
A89: 201 | B89: 0 | C89: 0 | D89: PROVEEDORES | E89: 2010PROVEEDORES | F89: #N/A
A90: 201 | B90: 1 | C90: 0 | D90: PROVEEDORES M.N. | E90: 2011PROVEEDORES M.N. | F90: Proveedores y acreedores diversos
A91: 201 | B91: 2 | C91: 0 | D91: PROVEEDORES M.E. | E91: 2012PROVEEDORES M.E. | F91: Proveedores y acreedores diversos
A92: 201 | B92: 200 | C92: 0 | D92: PROVEEDORES COMPLEMENTARIA | E92: 201200PROVEEDORES COMPLEMENTARIA | F92: Proveedores y acreedores diversos
A93: 202 | B93: 0 | C93: 0 | D93: ACREEDORES DIVERSOS | E93: 2020ACREEDORES DIVERSOS | F93: #N/A
A94: 202 | B94: 1 | C94: 0 | D94: ACREEDORES M.N. | E94: 2021ACREEDORES M.N. | F94: Proveedores y acreedores diversos
A95: 218 | B95: 0 | C95: 0 | D95: IMPUESTOS POR PAGAR | E95: 2180IMPUESTOS POR PAGAR | F95: #N/A
A96: 218 | B96: 1 | C96: 0 | D96: ISR | E96: 2181ISR | F96: #N/A
A97: 218 | B97: 1 | C97: 3 | D97: ISR RETENCIONES SERVICIOS PROFESIONALES | E97: 2181ISR RETENCIONES SERVICIOS PROFESIONALES | F97: Impuestos por pagar
A98: 218 | B98: 1 | C98: 8 | D98: ISR RETENCIONES EFECTIVAMENTE PAGADO | E98: 2181ISR RETENCIONES EFECTIVAMENTE PAGADO | F98: Impuestos por pagar
A99: 218 | B99: 2 | C99: 0 | D99: IVA | E99: 2182IVA | F99: #N/A
A100: 218 | B100: 2 | C100: 1 | D100: IVA POR PAGAR 16% | E100: 2182IVA POR PAGAR 16% | F100: Impuestos por pagar
A101: 218 | B101: 2 | C101: 2 | D101: IVA RETENIDO SERVICIOS PROFESIONALES | E101: 2182IVA RETENIDO SERVICIOS PROFESIONALES | F101: Impuestos por pagar
A102: 218 | B102: 2 | C102: 3 | D102: IVA RETENIDO EFECTIVAMENTE PAGADO | E102: 2182IVA RETENIDO EFECTIVAMENTE PAGADO | F102: Impuestos por pagar
...

Sheet BalanzaActual
A1: FIDEICOMISO FORTMCK19-12 LOMAS VERDES | S1: FIDEICOMISO FORTMCK19-12 LOMAS VERDES | AH1: Rubro | AI1: Nota
A2: R.F.C.: FFL191202GZ1 Dirección: Av. Santa Fe 505 Int. 802 Piso 8 Col. Cruz Manca CP05349 | S2: R.F.C.: FFL191202GZ1 Dirección: Av. Santa Fe 505 Int. 802 Piso 8 Col. Cruz Manca CP05349 | AG2: =+CONCATENATE(S2,T2,V2) -> R.F.C.: FFL191202GZ1 Dirección: Av. Santa Fe 505 Int. 802 Piso 8 Col. Cruz Manca CP05349 | AH2: =+VLOOKUP(AG2,Catálogo!E:F,2,0) -> #N/A | AI2: =+VLOOKUP(AG2,Catálogo!E:G,3,0) -> #N/A
A3: Periodo de : Enero 2024 a Diciembre 2024 | S3: Periodo de : Enero 2024 a Septiembre 2024 | AG3: =+CONCATENATE(S3,T3,V3) -> Periodo de : Enero 2024 a Septiembre 2024 | AH3: =+VLOOKUP(AG3,Catálogo!E:F,2,0) -> #N/A | AI3: =+VLOOKUP(AG3,Catálogo!E:G,3,0) -> #N/A
A4: Balanza de Comprobación | S4: Balanza de Comprobación | AG4: =+CONCATENATE(S4,T4,V4) -> Balanza de Comprobación | AH4: =+VLOOKUP(AG4,Catálogo!E:F,2,0) -> #N/A | AI4: =+VLOOKUP(AG4,Catálogo!E:G,3,0) -> #N/A
A5: Balanza compartida por el contador: | D5: Andrés Martínez | S5: Balanza compartida por el contador: | V5: Andrés Martínez | AG5: =+CONCATENATE(S5,T5,V5) -> Balanza compartida por el contador:Andrés Martínez | AH5: =+VLOOKUP(AG5,Catálogo!E:F,2,0) -> #N/A | AI5: =+VLOOKUP(AG5,Catálogo!E:G,3,0) -> #N/A
A6: Correo: | B6: amartinez@fortemcapital.com.mx | S6: Correo: | T6: amartinez@fortemcapital.com.mx | AG6: =+CONCATENATE(S6,T6,V6) -> Correo:amartinez@fortemcapital.com.mx | AH6: =+VLOOKUP(AG6,Catálogo!E:F,2,0) -> #N/A | AI6: =+VLOOKUP(AG6,Catálogo!E:G,3,0) -> #N/A
A7: Fecha de envio: 07/03/25 | O7: =+SUM(O11:O152) -> 0 | S7: Fecha de envio: 16/10/2024 | AG7: =+CONCATENATE(S7,T7,V7) -> Fecha de envio: 16/10/2024 | AH7: =+VLOOKUP(AG7,Catálogo!E:F,2,0) -> #N/A | AI7: =+VLOOKUP(AG7,Catálogo!E:G,3,0) -> #N/A
A8: Fecha de descarga: 07/03/25 | S8: Fecha de descarga: 16/10/2024 | AG8: =+CONCATENATE(S8,T8,V8) -> Fecha de descarga: 16/10/2024 | AH8: =+VLOOKUP(AG8,Catálogo!E:F,2,0) -> #N/A | AI8: =+VLOOKUP(AG8,Catálogo!E:G,3,0) -> #N/A
AG9: =+CONCATENATE(S9,T9,V9) | AH9: =+VLOOKUP(AG9,Catálogo!E:F,2,0) -> #N/A | AI9: =+VLOOKUP(AG9,Catálogo!E:G,3,0) -> #N/A
A10: Cuenta | B10: Scta | C10: SSCta | D10: Descripción | E10: Saldo Inicial | F10: Cargos | G10: Abonos | H10: Saldo Actual | K10: Quitar duplicados y cuentas de mayor | N10: Determinar saldos ajustados listos para trabajar | S10: Cuenta | T10: Scta | U10: SSCta | V10: Descripción | W10: Saldo Inicial | X10: Cargos | Y10: Abonos | Z10: Saldo Actual | AG10: =+CONCATENATE(S10,T10,V10) -> CuentaSctaDescripción | AH10: =+VLOOKUP(AG10,Catálogo!E:F,2,0) -> #N/A | AI10: =+VLOOKUP(AG10,Catálogo!E:G,3,0) -> #N/A
A11: 103 | B11: 0 | C11: 0 | D11: BANCOS | E11: 360054.31 | F11: 61942189 | G11: -61837756 | H11: 464487.14 | J11: =+ROUND(H11/1000,0) -> 464 | K11: =+IFERROR(LEFT(AH11,3),0) -> 0 | L11: =+IFERROR(ABS(K11),"ok") -> 0 | M11: =+IF(L11="ok",J11,0) -> 0 | O11: =+M11+N11 -> 0 | S11: 103 | T11: 0 | U11: 0 | V11: BANCOS | W11: 360054.31 | X11: 61942189 | Y11: -61837756 | Z11: =+O11 -> 0 | AG11: =+CONCATENATE(S11,T11,V11) -> 1030BANCOS | AH11: =+VLOOKUP(AG11,Catálogo!E:F,2,0) -> #N/A | AI11: =+VLOOKUP(AG11,Catálogo!E:G,3,0) -> 0
A12: 103 | B12: 1 | C12: 0 | D12: MONEDA NACIONAL | E12: 360054.31 | F12: 61942189 | G12: -61837756 | H12: 464487.14 | J12: =+ROUND(H12/1000,0) -> 464 | K12: =+IFERROR(LEFT(AH12,3),0) -> 0 | L12: =+IFERROR(ABS(K12),"ok") -> 0 | M12: =+IF(L12="ok",J12,0) -> 0 | O12: =+M12+N12 -> 0 | S12: 103 | T12: 1 | U12: 0 | V12: MONEDA NACIONAL | W12: 360054.31 | X12: 61942189 | Y12: -61837756 | Z12: =+O12 -> 0 | AG12: =+CONCATENATE(S12,T12,V12) -> 1031MONEDA NACIONAL | AH12: =+VLOOKUP(AG12,Catálogo!E:F,2,0) -> #N/A | AI12: =+VLOOKUP(AG12,Catálogo!E:G,3,0) -> 0
A13: 103 | B13: 1 | C13: 2 | D13: BBVA CTA 0116008208 | E13: 2749.92 | F13: 26742159 | G13: -26711748 | H13: 33160.16 | J13: =+ROUND(H13/1000,0) -> 33 | K13: =+IFERROR(LEFT(AH13,3),0) -> Efe | L13: =+IFERROR(ABS(K13),"ok") -> ok | M13: =+IF(L13="ok",J13,0) -> 33 | O13: =+M13+N13 -> 33 | S13: 103 | T13: 1 | U13: 2 | V13: BBVA CTA 0116008208 | W13: 2749.92 | X13: 26742159 | Y13: -26711748 | Z13: =+O13 -> 33 | AG13: =+CONCATENATE(S13,T13,V13) -> 1031BBVA CTA 0116008208 | AH13: =+VLOOKUP(AG13,Catálogo!E:F,2,0) -> Efectivo y equivalentes de efectivo | AI13: =+VLOOKUP(AG13,Catálogo!E:G,3,0) -> Depósitos en cuenta de cheques
A14: 103 | B14: 1 | C14: 3 | D14: BBVA CTA 0122389452 | E14: 7291.8 | F14: 0 | G14: -965.12 | H14: 6326.68 | J14: =+ROUND(H14/1000,0) -> 6 | K14: =+IFERROR(LEFT(AH14,3),0) -> Efe | L14: =+IFERROR(ABS(K14),"ok") -> ok | M14: =+IF(L14="ok",J14,0) -> 6 | O14: =+M14+N14 -> 6 | S14: 103 | T14: 1 | U14: 3 | V14: BBVA CTA 0122389452 | W14: 7291.8 | X14: 0 | Y14: -965.12 | Z14: =+O14 -> 6 | AG14: =+CONCATENATE(S14,T14,V14) -> 1031BBVA CTA 0122389452 | AH14: =+VLOOKUP(AG14,Catálogo!E:F,2,0) -> Efectivo y equivalentes de efectivo | AI14: =+VLOOKUP(AG14,Catálogo!E:G,3,0) -> Depósitos en cuenta de cheques
A15: 103 | B15: 1 | C15: 5 | D15: INVEX CTA 05661 COBRANZA | E15: 350012.59 | F15: 35200030 | G15: -35125042 | H15: 425000.3 | J15: =+ROUND(H15/1000,0) -> 425 | K15: =+IFERROR(LEFT(AH15,3),0) -> Efe | L15: =+IFERROR(ABS(K15),"ok") -> ok | M15: =+IF(L15="ok",J15,0) -> 425 | O15: =+M15+N15 -> 425 | S15: 103 | T15: 1 | U15: 5 | V15: INVEX CTA 05661 COBRANZA | W15: 350012.59 | X15: 35200030 | Y15: -35125042 | Z15: =+O15 -> 425 | AG15: =+CONCATENATE(S15,T15,V15) -> 1031INVEX CTA 05661 COBRANZA | AH15: =+VLOOKUP(AG15,Catálogo!E:F,2,0) -> Efectivo y equivalentes de efectivo | AI15: =+VLOOKUP(AG15,Catálogo!E:G,3,0) -> Depósitos en cuenta de cheques
A16: 104 | B16: 0 | C16: 0 | D16: INVERSIONES SISTEMA FINANCIERO | E16: 50825584 | F16: 6.607306e+08 | G16: -6.6930136e+08 | H16: 42254825 | J16: =+ROUND(H16/1000,0) -> 42255 | K16: =+IFERROR(LEFT(AH16,3),0) -> 0 | L16: =+IFERROR(ABS(K16),"ok") -> 0 | M16: =+IF(L16="ok",J16,0) -> 0 | O16: =+M16+N16 -> 0 | S16: 104 | T16: 0 | U16: 0 | V16: INVERSIONES SISTEMA FINANCIERO | W16: 50825584 | X16: 6.607306e+08 | Y16: -6.6930136e+08 | Z16: =+O16 -> 0 | AG16: =+CONCATENATE(S16,T16,V16) -> 1040INVERSIONES SISTEMA FINANCIERO | AH16: =+VLOOKUP(AG16,Catálogo!E:F,2,0) -> #N/A | AI16: =+VLOOKUP(AG16,Catálogo!E:G,3,0) -> 0
A17: 104 | B17: 1 | C17: 0 | D17: MONEDA NACIONAL | E17: 50825584 | F17: 6.607306e+08 | G17: -6.6930136e+08 | H17: 42254825 | J17: =+ROUND(H17/1000,0) -> 42255 | K17: =+IFERROR(LEFT(AH17,3),0) -> 0 | L17: =+IFERROR(ABS(K17),"ok") -> 0 | M17: =+IF(L17="ok",J17,0) -> 0 | O17: =+M17+N17 -> 0 | S17: 104 | T17: 1 | U17: 0 | V17: MONEDA NACIONAL | W17: 50825584 | X17: 6.607306e+08 | Y17: -6.6930136e+08 | Z17: =+O17 -> 0 | AG17: =+CONCATENATE(S17,T17,V17) -> 1041MONEDA NACIONAL | AH17: =+VLOOKUP(AG17,Catálogo!E:F,2,0) -> #N/A | AI17: =+VLOOKUP(AG17,Catálogo!E:G,3,0) -> 0
A18: 104 | B18: 1 | C18: 1 | D18: ACTINVER 8344681 CUENTA GENERAL | E18: 37.97 | F18: 2.1565824e+08 | G18: -2.1565827e+08 | H18: 4.82 | J18: =+ROUND(H18/1000,0) -> 0 | K18: =+IFERROR(LEFT(AH18,3),0) -> Efe | L18: =+IFERROR(ABS(K18),"ok") -> ok | M18: =+IF(L18="ok",J18,0) -> 0 | O18: =+M18+N18 -> 0 | S18: 104 | T18: 1 | U18: 1 | V18: ACTINVER 8344681 CUENTA GENERAL | W18: 37.97 | X18: 2.1565824e+08 | Y18: -2.1565827e+08 | Z18: =+O18 -> 0 | AG18: =+CONCATENATE(S18,T18,V18) -> 1041ACTINVER 8344681 CUENTA GENERAL | AH18: =+VLOOKUP(AG18,Catálogo!E:F,2,0) -> Efectivo y equivalentes de efectivo | AI18: =+VLOOKUP(AG18,Catálogo!E:G,3,0) -> Inversiones en valores realizables
A19: 104 | B19: 1 | C19: 2 | D19: ACTINVER 8344681 COMPLEMENTARIA | E19: 14209863 | F19: 9296193 | G19: -14209863 | H19: 9296193 | J19: =+ROUND(H19/1000,0) -> 9296 | K19: =+IFERROR(LEFT(AH19,3),0) -> Efe | L19: =+IFERROR(ABS(K19),"ok") -> ok | M19: =+IF(L19="ok",J19,0) -> 9296 | O19: =+M19+N19 -> 9296 | S19: 104 | T19: 1 | U19: 2 | V19: ACTINVER 8344681 COMPLEMENTARIA | W19: 14209863 | X19: 9296193 | Y19: -14209863 | Z19: =+O19 -> 9296 | AG19: =+CONCATENATE(S19,T19,V19) -> 1041ACTINVER 8344681 COMPLEMENTARIA | AH19: =+VLOOKUP(AG19,Catálogo!E:F,2,0) -> Efectivo y equivalentes de efectivo | AI19: =+VLOOKUP(AG19,Catálogo!E:G,3,0) -> Inversiones en valores realizables
A20: 104 | B20: 1 | C20: 3 | D20: ACTINVER 5371322 CUENTA GENERAL | E20: 63.87 | F20: 3.5478633e+08 | G20: -3.5478633e+08 | H20: 63.24 | J20: =+ROUND(H20/1000,0) -> 0 | K20: =+IFERROR(LEFT(AH20,3),0) -> Efe | L20: =+IFERROR(ABS(K20),"ok") -> ok | M20: =+IF(L20="ok",J20,0) -> 0 | O20: =+M20+N20 -> 0 | S20: 104 | T20: 1 | U20: 3 | V20: ACTINVER 5371322 CUENTA GENERAL | W20: 63.87 | X20: 3.5478633e+08 | Y20: -3.5478633e+08 | Z20: =+O20 -> 0 | AG20: =+CONCATENATE(S20,T20,V20) -> 1041ACTINVER 5371322 CUENTA GENERAL | AH20: =+VLOOKUP(AG20,Catálogo!E:F,2,0) -> Efectivo y equivalentes de efectivo | AI20: =+VLOOKUP(AG20,Catálogo!E:G,3,0) -> Inversiones en valores realizables
A21: 104 | B21: 1 | C21: 4 | D21: ACTINVER CTA 5371322 COMPLEMENTARIA | E21: 19570563 | F21: 12794513 | G21: -19570563 | H21: 12794513 | J21: =+ROUND(H21/1000,0) -> 12795 | K21: =+IFERROR(LEFT(AH21,3),0) -> Efe | L21: =+IFERROR(ABS(K21),"ok") -> ok | M21: =+IF(L21="ok",J21,0) -> 12795 | O21: =+M21+N21 -> 12795 | S21: 104 | T21: 1 | U21: 4 | V21: ACTINVER CTA 5371322 COMPLEMENTARIA | W21: 19570563 | X21: 12794513 | Y21: -19570563 | Z21: =+O21 -> 12795 | AG21: =+CONCATENATE(S21,T21,V21) -> 1041ACTINVER CTA 5371322 COMPLEMENTARIA | AH21: =+VLOOKUP(AG21,Catálogo!E:F,2,0) -> Efectivo y equivalentes de efectivo | AI21: =+VLOOKUP(AG21,Catálogo!E:G,3,0) -> Inversiones en valores realizables
A22: 104 | B22: 1 | C22: 5 | D22: INVEX CTA 0705 COBRAZA INVER | E22: 0 | F22: 44864604 | G22: -44864604 | H22: 0 | J22: =+ROUND(H22/1000,0) -> 0 | K22: =+IFERROR(LEFT(AH22,3),0) -> Efe | L22: =+IFERROR(ABS(K22),"ok") -> ok | M22: =+IF(L22="ok",J22,0) -> 0 | O22: =+M22+N22 -> 0 | S22: 104 | T22: 1 | U22: 5 | V22: INVEX CTA 0705 COBRAZA INVER | W22: 0 | X22: 44864604 | Y22: -44864604 | Z22: =+O22 -> 0 | AG22: =+CONCATENATE(S22,T22,V22) -> 1041INVEX CTA 0705 COBRAZA INVER | AH22: =+VLOOKUP(AG22,Catálogo!E:F,2,0) -> Efectivo y equivalentes de efectivo | AI22: =+VLOOKUP(AG22,Catálogo!E:G,3,0) -> Inversiones en valores realizables
... A26: 109 | B26: 0 | C26: 0 | D26: DEUDORES DIVERSOS | E26: 28247873 | F26: 2399820.4 | G26: -11816669 | H26: 18831025 | J26: =+ROUND(H26/1000,0) -> 18831 | K26: =+IFERROR(LEFT(AH26,3),0) -> 0 | L26: =+IFERROR(ABS(K26),"ok") -> 0 | M26: =+IF(L26="ok",J26,0) -> 0 | O26: =+M26+N26 -> 0 | S26: 109 | T26: 0 | U26: 0 | V26: DEUDORES DIVERSOS | W26: 28247873 | X26: 2399820.4 | Y26: -11816669 | Z26: =+O26 -> 0 | AG26: =+CONCATENATE(S26,T26,V26) -> 1090DEUDORES DIVERSOS | AH26: =+VLOOKUP(AG26,Catálogo!E:F,2,0) -> #N/A | AI26: =+VLOOKUP(AG26,Catálogo!E:G,3,0) -> 0
A27: 109 | B27: 1 | C27: 0 | D27: DEUDORES DIVERSOS M.N. | E27: 28247873 | F27: 2399820.4 | G27: -11816669 | H27: 18831025 | J27: =+ROUND(H27/1000,0) -> 18831 | K27: =+IFERROR(LEFT(AH27,3),0) -> Deu | L27: =+IFERROR(ABS(K27),"ok") -> ok | M27: =+IF(L27="ok",J27,0) -> 18831 | N27: 1 | O27: =+M27+N27 -> 18832 | S27: 109 | T27: 1 | U27: 0 | V27: DEUDORES DIVERSOS M.N. | W27: 28247873 | X27: 2399820.4 | Y27: -11816669 | Z27: =+O27 -> 18832 | AG27: =+CONCATENATE(S27,T27,V27) -> 1091DEUDORES DIVERSOS M.N. | AH27: =+VLOOKUP(AG27,Catálogo!E:F,2,0) -> Deudores diversos y otras cuentas por cobrar
A28: 113 | B28: 0 | C28: 0 | D28: ANTICIPO DE IMPUESTOS | E28: 271215.91 | F28: 19646.59 | G28: 0 | H28: 290862.5 | J28: =+ROUND(H28/1000,0) -> 291 | K28: =+IFERROR(LEFT(AH28,3),0) -> 0 | L28: =+IFERROR(ABS(K28),"ok") -> 0 | M28: =+IF(L28="ok",J28,0) -> 0 | O28: =+M28+N28 -> 0 | S28: 113 | T28: 0 | U28: 0 | V28: ANTICIPO DE IMPUESTOS | W28: 271215.91 | X28: 19646.59 | Y28: 0 | Z28: =+O28 -> 0 | AG28: =+CONCATENATE(S28,T28,V28) -> 1130ANTICIPO DE IMPUESTOS | AH28: =+VLOOKUP(AG28,Catálogo!E:F,2,0) -> #N/A | AI28: =+VLOOKUP(AG28,Catálogo!E:G,3,0) -> 0
A29: 113 | B29: 1 | C29: 0 | D29: ISR | E29: 271215.91 | F29: 19646.59 | G29: 0 | H29: 290862.5 | J29: =+ROUND(H29/1000,0) -> 291 | K29: =+IFERROR(LEFT(AH29,3),0) -> 0 | L29: =+IFERROR(ABS(K29),"ok") -> 0 | M29: =+IF(L29="ok",J29,0) -> 0 | O29: =+M29+N29 -> 0 | S29: 113 | T29: 1 | U29: 0 | V29: ISR | W29: 271215.91 | X29: 19646.59 | Y29: 0 | Z29: =+O29 -> 0 | AG29: =+CONCATENATE(S29,T29,V29) -> 1131ISR | AH29: =+VLOOKUP(AG29,Catálogo!E:F,2,0) -> #N/A | AI29: =+VLOOKUP(AG29,Catálogo!E:G,3,0) -> 0
A30: 113 | B30: 1 | C30: 1 | D30: ISR PAGO PROVISIONALES | E30: 12.15 | F30: 0 | G30: 0 | H30: 12.15 | J30: =+ROUND(H30/1000,0) -> 0 | K30: =+IFERROR(LEFT(AH30,3),0) -> Imp | L30: =+IFERROR(ABS(K30),"ok") -> ok | M30: =+IF(L30="ok",J30,0) -> 0 | O30: =+M30+N30 -> 0 | S30: 113 | T30: 1 | U30: 1 | V30: ISR PAGO PROVISIONALES | W30: 12.15 | X30: 0 | Y30: 0 | Z30: =+O30 -> 0 | AG30: =+CONCATENATE(S30,T30,V30) -> 1131ISR PAGO PROVISIONALES | AH30: =+VLOOKUP(AG30,Catálogo!E:F,2,0) -> Impuestos por recuperar | AI30: =+VLOOKUP(AG30,Catálogo!E:G,3,0) -> ISR Retenido
A31: 113 | B31: 1 | C31: 2 | D31: ISR RETENCIONES BANCOS | E31: 271203.76 | F31: 19646.59 | G31: 0 | H31: 290850.35 | J31: =+ROUND(H31/1000,0) -> 291 | K31: =+IFERROR(LEFT(AH31,3),0) -> Imp | L31: =+IFERROR(ABS(K31),"ok") -> ok | M31: =+IF(L31="ok",J31,0) -> 291 | O31: =+M31+N31 -> 291 | S31: 113 | T31: 1 | U31: 2 | V31: ISR RETENCIONES BANCOS | W31: 271203.76 | X31: 19646.59 | Y31: 0 | Z31: =+O31 -> 291 | AG31: =+CONCATENATE(S31,T31,V31) -> 1131ISR RETENCIONES BANCOS | AH31: =+VLOOKUP(AG31,Catálogo!E:F,2,0) -> Impuestos por recuperar | AI31: =+VLOOKUP(AG31,Catálogo!E:G,3,0) -> ISR Retenido
A32: 114 | B32: 0 | C32: 0 | D32: IMPUESTOS A FAVOR | E32: 70226019 | F32: 2414987.7 | G32: -176335.02 | H32: 72464672 | J32: =+ROUND(H32/1000,0) -> 72465 | K32: =+IFERROR(LEFT(AH32,3),0) -> 0 | L32: =+IFERROR(ABS(K32),"ok") -> 0 | M32: =+IF(L32="ok",J32,0) -> 0 | O32: =+M32+N32 -> 0 | S32: 114 | T32: 0 | U32: 0 | V32: IMPUESTOS A FAVOR | W32: 70226019 | X32: 2414987.7 | Y32: -176335.02 | Z32: =+O32 -> 0 | AG32: =+CONCATENATE(S32,T32,V32) -> 1140IMPUESTOS A FAVOR | AH32: =+VLOOKUP(AG32,Catálogo!E:F,2,0) -> #N/A | AI32: =+VLOOKUP(AG32,Catálogo!E:G,3,0) -> 0
A33: 114 | B33: 1 | C33: 0 | D33: IVA SALDO A FAVOR | E33: 70226019 | F33: 2414987.7 | G33: -176335.02 | H33: 72464672 | J33: =+ROUND(H33/1000,0) -> 72465 | K33: =+IFERROR(LEFT(AH33,3),0) -> 0 | L33: =+IFERROR(ABS(K33),"ok") -> 0 | M33: =+IF(L33="ok",J33,0) -> 0 | O33: =+M33+N33 -> 0 | S33: 114 | T33: 1 | U33: 0 | V33: IVA SALDO A FAVOR | W33: 70226019 | X33: 2414987.7 | Y33: -176335.02 | Z33: =+O33 -> 0 | AG33: =+CONCATENATE(S33,T33,V33) -> 1141IVA SALDO A FAVOR | AH33: =+VLOOKUP(AG33,Catálogo!E:F,2,0) -> #N/A | AI33: =+VLOOKUP(AG33,Catálogo!E:G,3,0) -> 0
A34: 114 | B34: 1 | C34: 1 | D34: IVA SALDO A FAVOR AL 16% | E34: 70226019 | F34: 2414987.7 | G34: -176335.02 | H34: 72464672 | J34: =+ROUND(H34/1000,0) -> 72465 | K34: =+IFERROR(LEFT(AH34,3),0) -> Inv | L34: =+IFERROR(ABS(K34),"ok") -> ok | M34: =+IF(L34="ok",J34,0) -> 72465 | O34: =+M34+N34 -> 72465 | S34: 114 | T34: 1 | U34: 1 | V34: IVA SALDO A FAVOR AL 16% | W34: 70226019 | X34: 2414987.7 | Y34: -176335.02 | Z34: =+O34 -> 72465 | AG34: =+CONCATENATE(S34,T34,V34) -> 1141IVA SALDO A FAVOR AL 16% | AH34: =+VLOOKUP(AG34,Catálogo!E:F,2,0) -> Inventarios inmobiliarios y costos pagados por anticipado | AI34: =+VLOOKUP(AG34,Catálogo!E:G,3,0) -> Impuesto al Valor Agregado
A35: 115 | B35: 0 | C35: 0 | D35: IMPUESTOS A FAVOR NO CAUSADO | E35: 6602611.3 | F35: 2054143.3 | G35: -2447241.6 | H35: 6209513 | J35: =+ROUND(H35/1000,0) -> 6210 | K35: =+IFERROR(LEFT(AH35,3),0) -> 0 | L35: =+IFERROR(ABS(K35),"ok") -> 0 | M35: =+IF(L35="ok",J35,0) -> 0 | O35: =+M35+N35 -> 0 | S35: 115 | T35: 0 | U35: 0 | V35: IMPUESTOS A FAVOR NO CAUSADO | W35: 6602611.3 | X35: 2054143.3 | Y35: -2447241.6 | Z35: =+O35 -> 0 | AG35: =+CONCATENATE(S35,T35,V35) -> 1150IMPUESTOS A FAVOR NO CAUSADO | AH35: =+VLOOKUP(AG35,Catálogo!E:F,2,0) -> #N/A | AI35: =+VLOOKUP(AG35,Catálogo!E:G,3,0) -> 0
A36: 115 | B36: 1 | C36: 0 | D36: IVA ACREDITABLE NO PAGADO | E36: 6602611.3 | F36: 2054143.3 | G36: -2447241.6 | H36: 6209513 | J36: =+ROUND(H36/1000,0) -> 6210 | K36: =+IFERROR(LEFT(AH36,3),0) -> 0 | L36: =+IFERROR(ABS(K36),"ok") -> 0 | M36: =+IF(L36="ok",J36,0) -> 0 | O36: =+M36+N36 -> 0 | S36: 115 | T36: 1 | U36: 0 | V36: IVA ACREDITABLE NO PAGADO | W36: 6602611.3 | X36: 2054143.3 | Y36: -2447241.6 | Z36: =+O36 -> 0 | AG36: =+CONCATENATE(S36,T36,V36) -> 1151IVA ACREDITABLE NO PAGADO | AH36: =+VLOOKUP(AG36,Catálogo!E:F,2,0) -> #N/A | AI36: =+VLOOKUP(AG36,Catálogo!E:G,3,0) -> 0
A37: 115 | B37: 1 | C37: 1 | D37: IVA ACREDITABLE NO PAGADO AL 16% | E37: 6602611.3 | F37: 2054143.3 | G37: -2447241.6 | H37: 6209513 | J37: =+ROUND(H37/1000,0) -> 6210 | K37: =+IFERROR(LEFT(AH37,3),0) -> Deu | L37: =+IFERROR(ABS(K37),"ok") -> ok | M37: =+IF(L37="ok",J37,0) -> 6210 | O37: =+M37+N37 -> 6210 | S37: 115 | T37: 1 | U37: 1 | V37: IVA ACREDITABLE NO PAGADO AL 16% | W37: 6602611.3 | X37: 2054143.3 | Y37: -2447241.6 | Z37: =+O37 -> 6210 | AG37: =+CONCATENATE(S37,T37,V37) -> 1151IVA ACREDITABLE NO PAGADO AL 16% | AH37: =+VLOOKUP(AG37,Catálogo!E:F,2,0) -> Deudores diversos y otras cuentas por cobrar | AI37: =+VLOOKUP(AG37,Catálogo!E:G,3,0) -> 0
A38: 118 | B38: 0 | C38: 0 | D38: PAGOS ANTICIPADOS | E38: 0 | F38: 250000 | G38: -21232.88 | H38: 228767.12 | J38: =+ROUND(H38/1000,0) -> 229 | K38: =+IFERROR(LEFT(AH38,3),0) -> 0 | L38: =+IFERROR(ABS(K38),"ok") -> 0 | M38: =+IF(L38="ok",J38,0) -> 0 | O38: =+M38+N38 -> 0 | S38: 118 | T38: 0 | U38: 0 | V38: PAGOS ANTICIPADOS | W38: 0 | X38: 250000 | Y38: -21232.88 | Z38: =+O38 -> 0 | AG38: =+CONCATENATE(S38,T38,V38) -> 1180PAGOS ANTICIPADOS | AH38: =+VLOOKUP(AG38,Catálogo!E:F,2,0) -> 0 | AI38: =+VLOOKUP(AG38,Catálogo!E:G,3,0) -> 0
A39: 118 | B39: 2 | C39: 0 | D39: PROVEEDORES | E39: 0 | F39: 250000 | G39: -21232.88 | H39: 228767.12 | J39: =+ROUND(H39/1000,0) -> 229 | K39: =+IFERROR(LEFT(AH39,3),0) -> 0 | L39: =+IFERROR(ABS(K39),"ok") -> 0 | M39: =+IF(L39="ok",J39,0) -> 0 | O39: =+M39+N39 -> 0 | S39: 118 | T39: 2 | U39: 0 | V39: PROVEEDORES | W39: 0 | X39: 250000 | Y39: -21232.88 | Z39: =+O39 -> 0 | AG39: =+CONCATENATE(S39,T39,V39) -> 1182PROVEEDORES | AH39: =+VLOOKUP(AG39,Catálogo!E:F,2,0) -> 0 | AI39: =+VLOOKUP(AG39,Catálogo!E:G,3,0) -> 0
... A75: 123 | B75: 7 | C75: 123 | D75: GASTOS ADMINISTRATIVOS OBRA | E75: 74914.71 | F75: 21232.88 | G75: 0 | H75: 96147.59 | J75: =+ROUND(H75/1000,0) -> 96 | K75: =+IFERROR(LEFT(AH75,3),0) -> Inv | L75: =+IFERROR(ABS(K75),"ok") -> ok | M75: =+IF(L75="ok",J75,0) -> 96 | O75: =+M75+N75 -> 96 | S75: 123 | T75: 7 | U75: 123 | V75: GASTOS ADMINISTRATIVOS OBRA | W75: 74914.71 | X75: 21232.88 | Y75: 0 | Z75: =+O75 -> 96 | AG75: =+CONCATENATE(S75,T75,V75) -> 1237GASTOS ADMINISTRATIVOS OBRA | AH75: =+VLOOKUP(AG75,Catálogo!E:F,2,0) -> Inventarios inmobiliarios y costos pagados por anticipado | AI75: =+VLOOKUP(AG75,Catálogo!E:G,3,0) -> Construcción en proceso (ii)
A76: 123 | B76: 9 | C76: 0 | D76: COMERCIALIZACION. | E76: 20180706 | F76: 0 | G76: -299999.98 | H76: 19880706 | J76: =+ROUND(H76/1000,0) -> 19881 | K76: =+IFERROR(LEFT(AH76,3),0) -> 0 | L76: =+IFERROR(ABS(K76),"ok") -> 0 | M76: =+IF(L76="ok",J76,0) -> 0 | O76: =+M76+N76 -> 0 | S76: 123 | T76: 9 | U76: 0 | V76: COMERCIALIZACION. | W76: 20180706 | X76: 0 | Y76: -299999.98 | Z76: =+O76 -> 0 | AG76: =+CONCATENATE(S76,T76,V76) -> 1239 COMERCIALIZACION. | AH76: =+VLOOKUP(AG76,Catálogo!E:F,2,0) -> #N/A
A77: 123 | B77: 9 | C77: 1 | D77: COMERCIALIZACION | E77: 20180706 | F77: 0 | G77: -299999.98 | H77: 19880706 | J77: =+ROUND(H77/1000,0) -> 19881 | K77: =+IFERROR(LEFT(AH77,3),0) -> Inv | L77: =+IFERROR(ABS(K77),"ok") -> ok | M77: =+IF(L77="ok",J77,0) -> 19881 | O77: =+M77+N77 -> 19881 | S77: 123 | T77: 9 | U77: 1 | V77: COMERCIALIZACION | W77: 20180706 | X77: 0 | Y77: -299999.98 | Z77: =+O77 -> 19881 | AG77: =+CONCATENATE(S77,T77,V77) -> 1239COMERCIALIZACION | AH77: =+VLOOKUP(AG77,Catálogo!E:F,2,0) -> Inventarios inmobiliarios y costos pagados por anticipado | AI77: =+VLOOKUP(AG77,Catálogo!E:G,3,0) -> Gastos administrativos y de comercialización (iv)
A78: 124 | B78: 0 | C78: 0 | D78: MOBILIARIO Y EQUIPO DE OFICINA | E78: 47000.28 | F78: 0 | G78: -405.18 | H78: 46595.1 | J78: =+ROUND(H78/1000,0) -> 47 | K78: =+IFERROR(LEFT(AH78,3),0) -> 0 | L78: =+IFERROR(ABS(K78),"ok") -> 0 | M78: =+IF(L78="ok",J78,0) -> 0 | O78: =+M78+N78 -> 0 | S78: 124 | T78: 0 | U78: 0 | V78: MOBILIARIO Y EQUIPO DE OFICINA | W78: 47000.28 | X78: 0 | Y78: -405.18 | Z78: =+O78 -> 0 | AG78: =+CONCATENATE(S78,T78,V78) -> 1240MOBILIARIO Y EQUIPO DE OFICINA | AH78: =+VLOOKUP(AG78,Catálogo!E:F,2,0) -> 0 | AI78: =+VLOOKUP(AG78,Catálogo!E:G,3,0) -> 0
A79: 124 | B79: 1 | C79: 0 | D79: INVERSIÓN | E79: 48621 | F79: 0 | G79: 0 | H79: 48621 | J79: =+ROUND(H79/1000,0) -> 49 | K79: =+IFERROR(LEFT(AH79,3),0) -> 0 | L79: =+IFERROR(ABS(K79),"ok") -> 0 | M79: =+IF(L79="ok",J79,0) -> 0 | O79: =+M79+N79 -> 0 | S79: 124 | T79: 1 | U79: 0 | V79: INVERSIÓN | W79: 48621 | X79: 0 | Y79: 0 | Z79: =+O79 -> 0 | AG79: =+CONCATENATE(S79,T79,V79) -> 1241INVERSIÓN | AH79: =+VLOOKUP(AG79,Catálogo!E:F,2,0) -> 0 | AI79: =+VLOOKUP(AG79,Catálogo!E:G,3,0) -> 0
A80: 124 | B80: 1 | C80: 1 | D80: MOBILIARIO Y EQP DE OFICINA | E80: 48621 | F80: 0 | G80: 0 | H80: 48621 | J80: =+ROUND(H80/1000,0) -> 49 | K80: =+IFERROR(LEFT(AH80,3),0) -> Mob | L80: =+IFERROR(ABS(K80),"ok") -> ok | M80: =+IF(L80="ok",J80,0) -> 49 | O80: =+M80+N80 -> 49 | S80: 124 | T80: 1 | U80: 1 | V80: MOBILIARIO Y EQP DE OFICINA | W80: 48621 | X80: 0 | Y80: 0 | Z80: =+O80 -> 49 | AG80: =+CONCATENATE(S80,T80,V80) -> 1241MOBILIARIO Y EQP DE OFICINA | AH80: =+VLOOKUP(AG80,Catálogo!E:F,2,0) -> Mobiliario y equipo, neto | AI80: =+VLOOKUP(AG80,Catálogo!E:G,3,0) -> 0
A81: 124 | B81: 2 | C81: 0 | D81: DEPRECIACION MOB Y EQUIPO DE OFICINA | E81: -1620.72 | F81: 0 | G81: -405.18 | H81: -2025.9 | J81: =+ROUND(H81/1000,0) -> -2 | K81: =+IFERROR(LEFT(AH81,3),0) -> Mob | L81: =+IFERROR(ABS(K81),"ok") -> ok | M81: =+IF(L81="ok",J81,0) -> -2 | O81: =+M81+N81 -> -2 | S81: 124 | T81: 2 | U81: 0 | V81: DEPRECIACION MOB Y EQUIPO DE OFICINA | W81: -1620.72 | X81: 0 | Y81: -405.18 | Z81: =+O81 -> -2 | AG81: =+CONCATENATE(S81,T81,V81) -> 1242DEPRECIACION MOB Y EQUIPO DE OFICINA | AH81: =+VLOOKUP(AG81,Catálogo!E:F,2,0) -> Mobiliario y equipo, neto | AI81: =+VLOOKUP(AG81,Catálogo!E:G,3,0) -> 0
A82: 125 | B82: 0 | C82: 0 | D82: EQUIPO DE COMPUTO | E82: 184012.19 | F82: 46664 | G82: -7815.01 | H82: 222861.18 | J82: =+ROUND(H82/1000,0) -> 223 | K82: =+IFERROR(LEFT(AH82,3),0) -> 0 | L82: =+IFERROR(ABS(K82),"ok") -> 0 | M82: =+IF(L82="ok",J82,0) -> 0 | O82: =+M82+N82 -> 0 | S82: 125 | T82: 0 | U82: 0 | V82: EQUIPO DE COMPUTO | W82: 184012.19 | X82: 46664 | Y82: -7815.01 | Z82: =+O82 -> 0 | AG82: =+CONCATENATE(S82,T82,V82) -> 1250EQUIPO DE COMPUTO | AH82: =+VLOOKUP(AG82,Catálogo!E:F,2,0) -> #N/A | AI82: =+VLOOKUP(AG82,Catálogo!E:G,3,0) -> 0
A83: 125 | B83: 1 | C83: 0 | D83: INVERSION EQUIPO DE COMPUTO | E83: 184012.19 | F83: 46664 | G83: -7815.01 | H83: 222861.18 | J83: =+ROUND(H83/1000,0) -> 223 | K83: =+IFERROR(LEFT(AH83,3),0) -> 0 | L83: =+IFERROR(ABS(K83),"ok") -> 0 | M83: =+IF(L83="ok",J83,0) -> 0 | O83: =+M83+N83 -> 0 | S83: 125 | T83: 1 | U83: 0 | V83: INVERSION EQUIPO DE COMPUTO | W83: 184012.19 | X83: 46664 | Y83: -7815.01 | Z83: =+O83 -> 0 | AG83: =+CONCATENATE(S83,T83,V83) -> 1251INVERSION EQUIPO DE COMPUTO | AH83: =+VLOOKUP(AG83,Catálogo!E:F,2,0) -> #N/A | AI83: =+VLOOKUP(AG83,Catálogo!E:G,3,0) -> 0
A84: 125 | B84: 1 | C84: 1 | D84: INVERSIÓN EQP COMPUTO | E84: 379800.4 | F84: 46664 | G84: 0 | H84: 426464.4 | J84: =+ROUND(H84/1000,0) -> 426 | K84: =+IFERROR(LEFT(AH84,3),0) -> Mob | L84: =+IFERROR(ABS(K84),"ok") -> ok | M84: =+IF(L84="ok",J84,0) -> 426 | O84: =+M84+N84 -> 426 | S84: 125 | T84: 1 | U84: 1 | V84: INVERSIÓN EQP COMPUTO | W84: 379800.4 | X84: 46664 | Y84: 0 | Z84: =+O84 -> 426 | AG84: =+CONCATENATE(S84,T84,V84) -> 1251INVERSIÓN EQP COMPUTO | AH84: =+VLOOKUP(AG84,Catálogo!E:F,2,0) -> Mobiliario y equipo, neto | AI84: =+VLOOKUP(AG84,Catálogo!E:G,3,0) -> 0
A85: 125 | B85: 1 | C85: 2 | D85: DEPRECIACIÓN EQP COMPUTO | E85: -195788.21 | F85: 0 | G85: -7815.01 | H85: -203603.22 | J85: =+ROUND(H85/1000,0) -> -204 | K85: =+IFERROR(LEFT(AH85,3),0) -> Mob | L85: =+IFERROR(ABS(K85),"ok") -> ok | M85: =+IF(L85="ok",J85,0) -> -204 | O85: =+M85+N85 -> -204 | S85: 125 | T85: 1 | U85: 2 | V85: DEPRECIACIÓN EQP COMPUTO | W85: -195788.21 | X85: 0 | Y85: -7815.01 | Z85: =+O85 -> -204 | AG85: =+CONCATENATE(S85,T85,V85) -> 1251DEPRECIACIÓN EQP COMPUTO | AH85: =+VLOOKUP(AG85,Catálogo!E:F,2,0) -> Mobiliario y equipo, neto | AI85: =+VLOOKUP(AG85,Catálogo!E:G,3,0) -> 0
A86: 126 | B86: 0 | C86: 0 | D86: EQUIPO DE VIDEO VIGILANCIA | E86: 97664.18 | F86: 0 | G86: -2790.4 | H86: 94873.78 | J86: =+ROUND(H86/1000,0) -> 95 | K86: =+IFERROR(LEFT(AH86,3),0) -> 0 | L86: =+IFERROR(ABS(K86),"ok") -> 0 | M86: =+IF(L86="ok",J86,0) -> 0 | O86: =+M86+N86 -> 0 | S86: 126 | T86: 0 | U86: 0 | V86: EQUIPO DE VIDEO VIGILANCIA | W86: 97664.18 | X86: 0 | Y86: -2790.4 | Z86: =+O86 -> 0 | AG86: =+CONCATENATE(S86,T86,V86) -> 1260EQUIPO DE VIDEO VIGILANCIA | AH86: =+VLOOKUP(AG86,Catálogo!E:F,2,0) -> 0 | AI86: =+VLOOKUP(AG86,Catálogo!E:G,3,0) -> 0
A87: 126 | B87: 1 | C87: 0 | D87: INVERSION | E87: 111616.18 | F87: 0 | G87: 0 | H87: 111616.18 | J87: =+ROUND(H87/1000,0) -> 112 | K87: =+IFERROR(LEFT(AH87,3),0) -> 0 | L87: =+IFERROR(ABS(K87),"ok") -> 0 | M87: =+IF(L87="ok",J87,0) -> 0 | O87: =+M87+N87 -> 0 | S87: 126 | T87: 1 | U87: 0 | V87: INVERSION | W87: 111616.18 | X87: 0 | Y87: 0 | Z87: =+O87 -> 0 | AG87: =+CONCATENATE(S87,T87,V87) -> 1261INVERSION | AH87: =+VLOOKUP(AG87,Catálogo!E:F,2,0) -> 0 | AI87: =+VLOOKUP(AG87,Catálogo!E:G,3,0) -> 0
A88: 126 | B88: 1 | C88: 1 | D88: CIRCUITO CERRADO DE TV | E88: 111616.18 | F88: 0 | G88: 0 | H88: 111616.18 | J88: =+ROUND(H88/1000,0) -> 112 | K88: =+IFERROR(LEFT(AH88,3),0) -> Mob | L88: =+IFERROR(ABS(K88),"ok") -> ok | M88: =+IF(L88="ok",J88,0) -> 112 | O88: =+M88+N88 -> 112 | S88: 126 | T88: 1 | U88: 1 | V88: CIRCUITO CERRADO DE TV | W88: 111616.18 | X88: 0 | Y88: 0 | Z88: =+O88 -> 112 | AG88: =+CONCATENATE(S88,T88,V88) -> 1261CIRCUITO CERRADO DE TV | AH88: =+VLOOKUP(AG88,Catálogo!E:F,2,0) -> Mobiliario y equipo, neto | AI88: =+VLOOKUP(AG88,Catálogo!E:G,3,0) -> 0
... A95: 202 | B95: 1 | C95: 0 | D95: ACREEDORES M.N. | E95: -2032152.4 | F95: 50000 | G95: 0 | H95: -1982152.4 | J95: =+ROUND(H95/1000,0) -> -1982 | K95: =+IFERROR(LEFT(AH95,3),0) -> Pro | L95: =+IFERROR(ABS(K95),"ok") -> ok | M95: =+IF(L95="ok",J95,0) -> -1982 | O95: =+M95+N95 -> -1982 | S95: 202 | T95: 1 | U95: 0 | V95: ACREEDORES M.N. | W95: -2032152.4 | X95: 50000 | Y95: 0 | Z95: =+O95 -> -1982 | AG95: =+CONCATENATE(S95,T95,V95) -> 2021ACREEDORES M.N. | AH95: =+VLOOKUP(AG95,Catálogo!E:F,2,0) -> Proveedores y acreedores diversos | AI95: =+VLOOKUP(AG95,Catálogo!E:G,3,0) -> 0
A96: 211 | B96: 0 | C96: 0 | D96: 5% RETENCION SOBRE CONSTRUCCION | E96: -2838818.9 | F96: 0 | G96: -50396.83 | H96: -2889215.7 | J96: =+ROUND(H96/1000,0) -> -2889 | K96: =+IFERROR(LEFT(AH96,3),0) -> 0 | L96: =+IFERROR(ABS(K96),"ok") -> 0 | M96: =+IF(L96="ok",J96,0) -> 0 | O96: =+M96+N96 -> 0 | S96: 211 | T96: 0 | U96: 0 | V96: 5% RETENCION SOBRE CONSTRUCCION | W96: -2838818.9 | X96: 0 | Y96: -50396.83 | Z96: =+O96 -> 0 | AG96: =+CONCATENATE(S96,T96,V96) -> 21105% RETENCION SOBRE CONSTRUCCION | AH96: =+VLOOKUP(AG96,Catálogo!E:F,2,0) -> 0 | AI96: Fideicomiso Irrevocable No. 3518 (Banco Actinver, S.A., Institución de Banca Múltiple, Grupo Financiero Actinver, División Fiduciaria) (el “Fideicomiso Fortem CKD 18”)
A97: 211 | B97: 1 | C97: 0 | D97: 5% RETENCION FONDO DE GARANTIA M.N. | E97: -2838818.9 | F97: 0 | G97: -50396.83 | H97: -2889215.7 | J97: =+ROUND(H97/1000,0) -> -2889 | K97: =+IFERROR(LEFT(AH97,3),0) -> Dep | L97: =+IFERROR(ABS(K97),"ok") -> ok | M97: =+IF(L97="ok",J97,0) -> -2889 | O97: =+M97+N97 -> -2889 | S97: 211 | T97: 1 | U97: 0 | V97: 5% RETENCION FONDO DE GARANTIA M.N. | W97: -2838818.9 | X97: 0 | Y97: -50396.83 | Z97: =+O97 -> -2889 | AG97: =+CONCATENATE(S97,T97,V97) -> 21115% RETENCION FONDO DE GARANTIA M.N. | AH97: =+VLOOKUP(AG97,Catálogo!E:F,2,0) -> Depósitos en garantía recibidos | AI97: =+VLOOKUP(AG97,Catálogo!E:G,3,0) -> Garantías retenidas a proveedores
A98: 218 | B98: 0 | C98: 0 | D98: IMPUESTOS POR PAGAR | E98: -354716.71 | F98: 421727.19 | G98: -527304.9 | H98: -460294.42 | J98: =+ROUND(H98/1000,0) -> -460 | K98: =+IFERROR(LEFT(AH98,3),0) -> 0 | L98: =+IFERROR(ABS(K98),"ok") -> 0 | M98: =+IF(L98="ok",J98,0) -> 0 | O98: =+M98+N98 -> 0 | S98: 218 | T98: 0 | U98: 0 | V98: IMPUESTOS POR PAGAR | W98: -354716.71 | X98: 421727.19 | Y98: -527304.9 | Z98: =+O98 -> 0 | AG98: =+CONCATENATE(S98,T98,V98) -> 2180IMPUESTOS POR PAGAR | AH98: =+VLOOKUP(AG98,Catálogo!E:F,2,0) -> #N/A | AI98: =+VLOOKUP(AG98,Catálogo!E:G,3,0) -> 0
A99: 218 | B99: 1 | C99: 0 | D99: ISR | E99: -160438.41 | F99: 160614.22 | G99: -200441.9 | H99: -200266.09 | J99: =+ROUND(H99/1000,0) -> -200 | K99: =+IFERROR(LEFT(AH99,3),0) -> 0 | L99: =+IFERROR(ABS(K99),"ok") -> 0 | M99: =+IF(L99="ok",J99,0) -> 0 | O99: =+M99+N99 -> 0 | S99: 218 | T99: 1 | U99: 0 | V99: ISR | W99: -160438.41 | X99: 160614.22 | Y99: -200441.9 | Z99: =+O99 -> 0 | AG99: =+CONCATENATE(S99,T99,V99) -> 2181ISR | AH99: =+VLOOKUP(AG99,Catálogo!E:F,2,0) -> #N/A | AI99: =+VLOOKUP(AG99,Catálogo!E:G,3,0) -> 0
A100: 218 | B100: 1 | C100: 3 | D100: ISR RETENCIONES SERVICIOS PROFESIONALES | E100: -121630.39 | F100: 121805.22 | G100: -78636.68 | H100: -78461.85 | J100: =+ROUND(H100/1000,0) -> -78 | K100: =+IFERROR(LEFT(AH100,3),0) -> Imp | L100: =+IFERROR(ABS(K100),"ok") -> ok | M100: =+IF(L100="ok",J100,0) -> -78 | O100: =+M100+N100 -> -78 | S100: 218 | T100: 1 | U100: 3 | V100: ISR RETENCIONES SERVICIOS PROFESIONALES | W100: -121630.39 | X100: 121805.22 | Y100: -78636.68 | Z100: =+O100 -> -78 | AG100: =+CONCATENATE(S100,T100,V100) -> 2181ISR RETENCIONES SERVICIOS PROFESIONALES | AH100: =+VLOOKUP(AG100,Catálogo!E:F,2,0) -> Impuestos por pagar | AI100: =+VLOOKUP(AG100,Catálogo!E:G,3,0) -> 0
A101: 218 | B101: 1 | C101: 8 | D101: ISR RETENCIONES EFECTIVAMENTE PAGADO | E101: -38808.02 | F101: 38809 | G101: -121805.22 | H101: -121804.24 | J101: =+ROUND(H101/1000,0) -> -122 | K101: =+IFERROR(LEFT(AH101,3),0) -> Imp | L101: =+IFERROR(ABS(K101),"ok") -> ok | M101: =+IF(L101="ok",J101,0) -> -122 | O101: =+M101+N101 -> -122 | S101: 218 | T101: 1 | U101: 8 | V101: ISR RETENCIONES EFECTIVAMENTE PAGADO | W101: -38808.02 | X101: 38809 | Y101: -121805.22 | Z101: =+O101 -> -122 | AG101: =+CONCATENATE(S101,T101,V101) -> 2181ISR RETENCIONES EFECTIVAMENTE PAGADO | AH101: =+VLOOKUP(AG101,Catálogo!E:F,2,0) -> Impuestos por pagar | AI101: =+VLOOKUP(AG101,Catálogo!E:G,3,0) -> 0
A102: 218 | B102: 2 | C102: 0 | D102: IVA | E102: -194278.3 | F102: 261112.97 | G102: -326863 | H102: -260028.33 | J102: =+ROUND(H102/1000,0) -> -260 | K102: =+IFERROR(LEFT(AH102,3),0) -> 0 | L102: =+IFERROR(ABS(K102),"ok") -> 0 | M102: =+IF(L102="ok",J102,0) -> 0 | O102: =+M102+N102 -> 0 | S102: 218 | T102: 2 | U102: 0 | V102: IVA | W102: -194278.3 | X102: 261112.97 | Y102: -326863 | Z102: =+O102 -> 0 | AG102: =+CONCATENATE(S102,T102,V102) -> 2182IVA | AH102: =+VLOOKUP(AG102,Catálogo!E:F,2,0) -> #N/A | AI102: =+VLOOKUP(AG102,Catálogo!E:G,3,0) -> 0
A103: 218 | B103: 2 | C103: 2 | D103: IVA RETENIDO SERVICIOS PROFESIONALES | E103: -109502.77 | F103: 176335.97 | G103: -150527.03 | H103: -83693.83 | J103: =+ROUND(H103/1000,0) -> -84 | K103: =+IFERROR(LEFT(AH103,3),0) -> Imp | L103: =+IFERROR(ABS(K103),"ok") -> ok | M103: =+IF(L103="ok",J103,0) -> -84 | O103: =+M103+N103 -> -84 | S103: 218 | T103: 2 | U103: 2 | V103: IVA RETENIDO SERVICIOS PROFESIONALES | W103: -109502.77 | X103: 176335.97 | Y103: -150527.03 | Z103: =+O103 -> -84 | AG103: =+CONCATENATE(S103,T103,V103) -> 2182IVA RETENIDO SERVICIOS PROFESIONALES | AH103: =+VLOOKUP(AG103,Catálogo!E:F,2,0) -> Impuestos por pagar | AI103: =+VLOOKUP(AG103,Catálogo!E:G,3,0) -> 0
A104: 218 | B104: 2 | C104: 3 | D104: IVA RETENIDO EFECTIVAMENTE PAGADO | E104: -84775.53 | F104: 84777 | G104: -176335.97 | H104: -176334.5 | J104: =+ROUND(H104/1000,0) -> -176 | K104: =+IFERROR(LEFT(AH104,3),0) -> Imp | L104: =+IFERROR(ABS(K104),"ok") -> ok | M104: =+IF(L104="ok",J104,0) -> -176 | O104: =+M104+N104 -> -176 | S104: 218 | T104: 2 | U104: 3 | V104: IVA RETENIDO EFECTIVAMENTE PAGADO | W104: -84775.53 | X104: 84777 | Y104: -176335.97 | Z104: =+O104 -> -176 | AG104: =+CONCATENATE(S104,T104,V104) -> 2182IVA RETENIDO EFECTIVAMENTE PAGADO | AH104: =+VLOOKUP(AG104,Catálogo!E:F,2,0) -> Impuestos por pagar | AI104: =+VLOOKUP(AG104,Catálogo!E:G,3,0) -> 0
A105: 223 | B105: 0 | C105: 0 | D105: DOCUMENTOS POR PAGAR L.P. | E105: -4.6090286e+08 | F105: 5035847.2 | G105: 0 | H105: -4.5586701e+08 | J105: =+ROUND(H105/1000,0) -> -455867 | K105: =+IFERROR(LEFT(AH105,3),0) -> 0 | L105: =+IFERROR(ABS(K105),"ok") -> 0 | M105: =+IF(L105="ok",J105,0) -> 0 | O105: =+M105+N105 -> 0 | S105: 223 | T105: 0 | U105: 0 | V105: DOCUMENTOS POR PAGAR L.P. | W105: -4.6090286e+08 | X105: 5035847.2 | Y105: 0 | Z105: =+O105 -> 0 | AG105: =+CONCATENATE(S105,T105,V105) -> 2230DOCUMENTOS POR PAGAR L.P. | AH105: =+VLOOKUP(AG105,Catálogo!E:F,2,0) -> #N/A | AI105: =+VLOOKUP(AG105,Catálogo!E:G,3,0) -> 0
A106: 223 | B106: 1 | C106: 0 | D106: MONEDA NACIONAL | E106: -4.6090286e+08 | F106: 5035847.2 | G106: 0 | H106: -4.5586701e+08 | J106: =+ROUND(H106/1000,0) -> -455867 | K106: =+IFERROR(LEFT(AH106,3),0) -> 0 | L106: =+IFERROR(ABS(K106),"ok") -> 0 | M106: =+IF(L106="ok",J106,0) -> 0 | O106: =+M106+N106 -> 0 | S106: 223 | T106: 1 | U106: 0 | V106: MONEDA NACIONAL | W106: -4.6090286e+08 | X106: 5035847.2 | Y106: 0 | Z106: =+O106 -> 0 | AG106: =+CONCATENATE(S106,T106,V106) -> 2231MONEDA NACIONAL | AH106: =+VLOOKUP(AG106,Catálogo!E:F,2,0) -> #N/A | AI106: =+VLOOKUP(AG106,Catálogo!E:G,3,0) -> 0
A107: 223 | B107: 1 | C107: 1 | D107: FIDEICOMISO IRREVOCABLE NUMERO 3518 | E107: -1.3090286e+08 | F107: 5035847.2 | G107: 0 | H107: -1.2586701e+08 | J107: =+ROUND(H107/1000,0) -> -125867 | K107: =+IFERROR(LEFT(AH107,3),0) -> Otr | L107: =+IFERROR(ABS(K107),"ok") -> ok | M107: =+IF(L107="ok",J107,0) -> -125867 | O107: =+M107+N107 -> -125867 | S107: 223 | T107: 1 | U107: 1 | V107: FIDEICOMISO IRREVOCABLE NUMERO 3518 | W107: -1.3090286e+08 | X107: 5035847.2 | Y107: 0 | Z107: =+O107 -> -125867 | AG107: =+CONCATENATE(S107,T107,V107) -> 2231FIDEICOMISO IRREVOCABLE NUMERO 3518 | AH107: =+VLOOKUP(AG107,Catálogo!E:F,2,0) -> Otras aportaciones del fideicomitente | AI107: =+VLOOKUP(AG107,Catálogo!E:G,3,0) -> Otras aportaciones del fideicomitente
A108: 223 | B108: 1 | C108: 2 | D108: NXX CAPITAL MEZZI, SAPI DE CV SOFOM EN R | E108: -330000000 | F108: 0 | G108: 0 | H108: -330000000 | J108: =+ROUND(H108/1000,0) -> -330000 | K108: =+IFERROR(LEFT(AH108,3),0) -> Pré | L108: =+IFERROR(ABS(K108),"ok") -> ok | M108: =+IF(L108="ok",J108,0) -> -330000 | O108: =+M108+N108 -> -330000 | S108: 223 | T108: 1 | U108: 2 | V108: NXX CAPITAL MEZZI, SAPI DE CV SOFOM EN R | W108: -330000000 | X108: 0 | Y108: 0 | Z108: =+O108 -> -330000 | AG108: =+CONCATENATE(S108,T108,V108) -> 2231NXX CAPITAL MEZZI, SAPI DE CV SOFOM EN R | AH108: =+VLOOKUP(AG108,Catálogo!E:F,2,0) -> Préstamos a largo plazo | AI108: =+VLOOKUP(AG108,Catálogo!E:G,3,0) -> Principal del crédito
... A118: 307 | B118: 0 | C118: 0 | D118: PERDIDAS ACUMULADAS | E118: 705484.7 | F118: 0 | G118: 0 | H118: 705484.7 | J118: =+ROUND(H118/1000,0) -> 705 | K118: =+IFERROR(LEFT(AH118,3),0) -> 0 | L118: =+IFERROR(ABS(K118),"ok") -> 0 | M118: =+IF(L118="ok",J118,0) -> 0 | O118: =+M118+N118 -> 0 | S118: 307 | T118: 0 | U118: 0 | V118: PERDIDAS ACUMULADAS | W118: 705484.7 | X118: 0 | Y118: 0 | Z118: =+O118 -> 0 | AG118: =+CONCATENATE(S118,T118,V118) -> 3070PERDIDAS ACUMULADAS | AH118: =+VLOOKUP(AG118,Catálogo!E:F,2,0) -> #N/A | AI118: =+VLOOKUP(AG118,Catálogo!E:G,3,0) -> 0
A119: 307 | B119: 1 | C119: 0 | D119: EJERCICIO 2019 | E119: 279505.99 | F119: 0 | G119: 0 | H119: 279505.99 | J119: =+ROUND(H119/1000,0) -> 280 | K119: =+IFERROR(LEFT(AH119,3),0) -> Res | L119: =+IFERROR(ABS(K119),"ok") -> ok | M119: =+IF(L119="ok",J119,0) -> 280 | N119: -1 | O119: =+M119+N119 -> 279 | S119: 307 | T119: 1 | U119: 0 | V119: EJERCICIO 2019 | W119: 279505.99 | X119: 0 | Y119: 0 | Z119: =+O119 -> 279 | AG119: =+CONCATENATE(S119,T119,V119) -> 3071EJERCICIO 2019 | AH119: =+VLOOKUP(AG119,Catálogo!E:F,2,0) -> Resultados acumulados | AI119: =+VLOOKUP(AG119,Catálogo!E:G,3,0) -> 0
A120: 307 | B120: 2 | C120: 0 | D120: EJERCICIO 2021 | E120: 133570.67 | F120: 0 | G120: 0 | H120: 133570.67 | J120: =+ROUND(H120/1000,0) -> 134 | K120: =+IFERROR(LEFT(AH120,3),0) -> Res | L120: =+IFERROR(ABS(K120),"ok") -> ok | M120: =+IF(L120="ok",J120,0) -> 134 | O120: =+M120+N120 -> 134 | S120: 307 | T120: 2 | U120: 0 | V120: EJERCICIO 2021 | W120: 133570.67 | X120: 0 | Y120: 0 | Z120: =+O120 -> 134 | AG120: =+CONCATENATE(S120,T120,V120) -> 3072EJERCICIO 2021 | AH120: =+VLOOKUP(AG120,Catálogo!E:F,2,0) -> Resultados acumulados | AI120: =+VLOOKUP(AG120,Catálogo!E:G,3,0) -> 0
A121: 307 | B121: 3 | C121: 0 | D121: EJERCICIO 2022 | E121: 292408.04 | F121: 0 | G121: 0 | H121: 292408.04 | J121: =+ROUND(H121/1000,0) -> 292 | K121: =+IFERROR(LEFT(AH121,3),0) -> Res | L121: =+IFERROR(ABS(K121),"ok") -> ok | M121: =+IF(L121="ok",J121,0) -> 292 | O121: =+M121+N121 -> 292 | S121: 307 | T121: 3 | U121: 0 | V121: EJERCICIO 2022 | W121: 292408.04 | X121: 0 | Y121: 0 | Z121: =+O121 -> 292 | AG121: =+CONCATENATE(S121,T121,V121) -> 3073EJERCICIO 2022 | AH121: =+VLOOKUP(AG121,Catálogo!E:F,2,0) -> Resultados acumulados | AI121: =+VLOOKUP(AG121,Catálogo!E:G,3,0) -> 0
A122: 601 | B122: 0 | C122: 0 | D122: GASTOS DE ADMINISTRACIÓN | E122: 75950.93 | F122: 36416276 | G122: 0 | H122: 36492227 | J122: =+ROUND(H122/1000,0) -> 36492 | K122: =+IFERROR(LEFT(AH122,3),0) -> 0 | L122: =+IFERROR(ABS(K122),"ok") -> 0 | M122: =+IF(L122="ok",J122,0) -> 0 | O122: =+M122+N122 -> 0 | S122: 601 | T122: 0 | U122: 0 | V122: GASTOS DE ADMINISTRACIÓN | W122: 75950.93 | X122: 36416276 | Y122: 0 | Z122: =+O122 -> 0 | AG122: =+CONCATENATE(S122,T122,V122) -> 6010GASTOS DE ADMINISTRACIÓN | AH122: =+VLOOKUP(AG122,Catálogo!E:F,2,0) -> #N/A | AI122: =+VLOOKUP(AG122,Catálogo!E:G,3,0) -> 0
A123: 601 | B123: 2 | C123: 0 | D123: HONORARIOS PERSONAS MORALES | E123: 0 | F123: 31066489 | G123: 0 | H123: 31066489 | J123: =+ROUND(H123/1000,0) -> 31066 | K123: =+IFERROR(LEFT(AH123,3),0) -> Gas | L123: =+IFERROR(ABS(K123),"ok") -> ok | M123: =+IF(L123="ok",J123,0) -> 31066 | O123: =+M123+N123 -> 31066 | S123: 601 | T123: 2 | U123: 0 | V123: HONORARIOS PERSONAS MORALES | W123: 0 | X123: 31066489 | Y123: 0 | Z123: =+O123 -> 31066 | AG123: =+CONCATENATE(S123,T123,V123) -> 6012HONORARIOS PERSONAS MORALES | AH123: =+VLOOKUP(AG123,Catálogo!E:F,2,0) -> Gastos operativos | AI123: =+VLOOKUP(AG123,Catálogo!E:G,3,0) -> 0
A124: 601 | B124: 6 | C124: 0 | D124: HONORARIOS PERSONAS FISICAS | E124: 0 | F124: 2345866.5 | G124: 0 | H124: 2345866.5 | J124: =+ROUND(H124/1000,0) -> 2346 | K124: =+IFERROR(LEFT(AH124,3),0) -> Gas | L124: =+IFERROR(ABS(K124),"ok") -> ok | M124: =+IF(L124="ok",J124,0) -> 2346 | O124: =+M124+N124 -> 2346 | S124: 601 | T124: 6 | U124: 0 | V124: HONORARIOS PERSONAS FISICAS | W124: 0 | X124: 2345866.5 | Y124: 0 | Z124: =+O124 -> 2346 | AG124: =+CONCATENATE(S124,T124,V124) -> 6016HONORARIOS PERSONAS FISICAS | AH124: =+VLOOKUP(AG124,Catálogo!E:F,2,0) -> Gastos operativos | AI124: =+VLOOKUP(AG124,Catálogo!E:G,3,0) -> 0
A125: 601 | B125: 7 | C125: 0 | D125: GASTOS LEGALES Y NOTARIALES | E125: 0 | F125: 2107565.3 | G125: 0 | H125: 2107565.3 | J125: =+ROUND(H125/1000,0) -> 2108 | K125: =+IFERROR(LEFT(AH125,3),0) -> Gas | L125: =+IFERROR(ABS(K125),"ok") -> ok | M125: =+IF(L125="ok",J125,0) -> 2108 | O125: =+M125+N125 -> 2108 | S125: 601 | T125: 7 | U125: 0 | V125: GASTOS LEGALES Y NOTARIALES | W125: 0 | X125: 2107565.3 | Y125: 0 | Z125: =+O125 -> 2108 | AG125: =+CONCATENATE(S125,T125,V125) -> 6017GASTOS LEGALES Y NOTARIALES | AH125: =+VLOOKUP(AG125,Catálogo!E:F,2,0) -> Gastos operativos | AI125: =+VLOOKUP(AG125,Catálogo!E:G,3,0) -> 0
A126: 601 | B126: 17 | C126: 0 | D126: SEGURIDAD | E126: 0 | F126: 885345.03 | G126: 0 | H126: 885345.03 | J126: =+ROUND(H126/1000,0) -> 885 | K126: =+IFERROR(LEFT(AH126,3),0) -> Gas | L126: =+IFERROR(ABS(K126),"ok") -> ok | M126: =+IF(L126="ok",J126,0) -> 885 | O126: =+M126+N126 -> 885 | S126: 601 | T126: 17 | U126: 0 | V126: SEGURIDAD | W126: 0 | X126: 885345.03 | Y126: 0 | Z126: =+O126 -> 885 | AG126: =+CONCATENATE(S126,T126,V126) -> 60117SEGURIDAD | AH126: =+VLOOKUP(AG126,Catálogo!E:F,2,0) -> Gastos operativos | AI126: =+VLOOKUP(AG126,Catálogo!E:G,3,0) -> 0
A127: 601 | B127: 101 | C127: 0 | D127: DEPRECIACION DEL EJERCICIO | E127: 75950.93 | F127: 11010.59 | G127: 0 | H127: 86961.52 | J127: =+ROUND(H127/1000,0) -> 87 | K127: =+IFERROR(LEFT(AH127,3),0) -> 0 | L127: =+IFERROR(ABS(K127),"ok") -> 0 | M127: =+IF(L127="ok",J127,0) -> 0 | O127: =+M127+N127 -> 0 | S127: 601 | T127: 101 | U127: 0 | V127: DEPRECIACION DEL EJERCICIO | W127: 75950.93 | X127: 11010.59 | Y127: 0 | Z127: =+O127 -> 0 | AG127: =+CONCATENATE(S127,T127,V127) -> 601101DEPRECIACION DEL EJERCICIO | AH127: =+VLOOKUP(AG127,Catálogo!E:F,2,0) -> #N/A | AI127: =+VLOOKUP(AG127,Catálogo!E:G,3,0) -> 0
A128: 601 | B128: 101 | C128: 1 | D128: DEPRECIACION MOB Y EQUIPO DE OFICINA | E128: 1620.72 | F128: 405.18 | G128: 0 | H128: 2025.9 | J128: =+ROUND(H128/1000,0) -> 2 | K128: =+IFERROR(LEFT(AH128,3),0) -> Gas | L128: =+IFERROR(ABS(K128),"ok") -> ok | M128: =+IF(L128="ok",J128,0) -> 2 | O128: =+M128+N128 -> 2 | S128: 601 | T128: 101 | U128: 1 | V128: DEPRECIACION MOB Y EQUIPO DE OFICINA | W128: 1620.72 | X128: 405.18 | Y128: 0 | Z128: =+O128 -> 2 | AG128: =+CONCATENATE(S128,T128,V128) -> 601101DEPRECIACION MOB Y EQUIPO DE OFICINA | AH128: =+VLOOKUP(AG128,Catálogo!E:F,2,0) -> Gastos operativos | AI128: =+VLOOKUP(AG128,Catálogo!E:G,3,0) -> 0
A129: 601 | B129: 101 | C129: 2 | D129: DEPRECIACION EQUIPO DE COMPUTO | E129: 60378.21 | F129: 7815.01 | G129: 0 | H129: 68193.22 | J129: =+ROUND(H129/1000,0) -> 68 | K129: =+IFERROR(LEFT(AH129,3),0) -> Gas | L129: =+IFERROR(ABS(K129),"ok") -> ok | M129: =+IF(L129="ok",J129,0) -> 68 | O129: =+M129+N129 -> 68 | S129: 601 | T129: 101 | U129: 2 | V129: DEPRECIACION EQUIPO DE COMPUTO | W129: 60378.21 | X129: 7815.01 | Y129: 0 | Z129: =+O129 -> 68 | AG129: =+CONCATENATE(S129,T129,V129) -> 601101DEPRECIACION EQUIPO DE COMPUTO | AH129: =+VLOOKUP(AG129,Catálogo!E:F,2,0) -> Gastos operativos | AI129: =+VLOOKUP(AG129,Catálogo!E:G,3,0) -> 0
A130: 601 | B130: 101 | C130: 4 | D130: DEPRECIACION EQP DE VIDEO VIGILANCIA | E130: 13952 | F130: 2790.4 | G130: 0 | H130: 16742.4 | J130: =+ROUND(H130/1000,0) -> 17 | K130: =+IFERROR(LEFT(AH130,3),0) -> Gas | L130: =+IFERROR(ABS(K130),"ok") -> ok | M130: =+IF(L130="ok",J130,0) -> 17 | O130: =+M130+N130 -> 17 | S130: 601 | T130: 101 | U130: 4 | V130: DEPRECIACION EQP DE VIDEO VIGILANCIA | W130: 13952 | X130: 2790.4 | Y130: 0 | Z130: =+O130 -> 17 | AG130: =+CONCATENATE(S130,T130,V130) -> 601101DEPRECIACION EQP DE VIDEO VIGILANCIA | AH130: =+VLOOKUP(AG130,Catálogo!E:F,2,0) -> Gastos operativos | AI130: =+VLOOKUP(AG130,Catálogo!E:G,3,0) -> 0
A131: 701 | B131: 0 | C131: 0 | D131: PRODUCTOS FINANCIEROS | E131: -7650515.4 | F131: 0 | G131: -399782.81 | H131: -8050298.2 | J131: =+ROUND(H131/1000,0) -> -8050 | K131: =+IFERROR(LEFT(AH131,3),0) -> 0 | L131: =+IFERROR(ABS(K131),"ok") -> 0 | M131: =+IF(L131="ok",J131,0) -> 0 | O131: =+M131+N131 -> 0 | S131: 701 | T131: 0 | U131: 0 | V131: PRODUCTOS FINANCIEROS | W131: -7650515.4 | X131: 0 | Y131: -399782.81 | Z131: =+O131 -> 0 | AG131: =+CONCATENATE(S131,T131,V131) -> 7010PRODUCTOS FINANCIEROS | AH131: =+VLOOKUP(AG131,Catálogo!E:F,2,0) -> #N/A | AI131: =+VLOOKUP(AG131,Catálogo!E:G,3,0) -> 0
... A141: 752 | B141: 1 | C141: 0 | D141: VARIOS | E141: 0.05 | F141: 0.01 | G141: 0 | H141: 0.06 | J141: =+ROUND(H141/1000,0) -> 0 | K141: =+IFERROR(LEFT(AH141,3),0) -> Otr | L141: =+IFERROR(ABS(K141),"ok") -> ok | M141: =+IF(L141="ok",J141,0) -> 0 | O141: =+M141+N141 -> 0 | S141: 752 | T141: 1 | U141: 0 | V141: VARIOS | W141: 0.05 | X141: 0.01 | Y141: 0 | Z141: =+O141 -> 0 | AG141: =+CONCATENATE(S141,T141,V141) -> 7521VARIOS | AH141: =+VLOOKUP(AG141,Catálogo!E:F,2,0) -> Otros ingresos | AI141: =+VLOOKUP(AG141,Catálogo!E:G,3,0) -> 0
J142: =+ROUND(H142/1000,0) -> 0 | K142: =+IFERROR(LEFT(AH142,3),0) -> 0 | L142: =+IFERROR(ABS(K142),"ok") -> 0 | M142: =+IF(L142="ok",J142,0) -> 0 | O142: =+M142+N142 -> 0 | AG142: =+CONCATENATE(S142,T142,V142) | AH142: =+VLOOKUP(AG142,Catálogo!E:F,2,0) -> #N/A | AI142: =+VLOOKUP(AG142,Catálogo!E:G,3,0) -> #N/A
J143: =+ROUND(H143/1000,0) -> 0 | K143: =+IFERROR(LEFT(AH143,3),0) -> 0 | L143: =+IFERROR(ABS(K143),"ok") -> 0 | M143: =+IF(L143="ok",J143,0) -> 0 | O143: =+M143+N143 -> 0 | AG143: =+CONCATENATE(S143,T143,V143) | AH143: =+VLOOKUP(AG143,Catálogo!E:F,2,0) -> #N/A | AI143: =+VLOOKUP(AG143,Catálogo!E:G,3,0) -> #N/A
J144: =+ROUND(H144/1000,0) -> 0 | K144: =+IFERROR(LEFT(AH144,3),0) -> 0 | L144: =+IFERROR(ABS(K144),"ok") -> 0 | M144: =+IF(L144="ok",J144,0) -> 0 | O144: =+M144+N144 -> 0 | AG144: =+CONCATENATE(S144,T144,V144) | AH144: =+VLOOKUP(AG144,Catálogo!E:F,2,0) -> #N/A | AI144: =+VLOOKUP(AG144,Catálogo!E:G,3,0) -> #N/A
J145: =+ROUND(H145/1000,0) -> 0 | K145: =+IFERROR(LEFT(AH145,3),0) -> 0 | L145: =+IFERROR(ABS(K145),"ok") -> 0 | M145: =+IF(L145="ok",J145,0) -> 0 | O145: =+M145+N145 -> 0 | AG145: =+CONCATENATE(S145,T145,V145) | AH145: =+VLOOKUP(AG145,Catálogo!E:F,2,0) -> #N/A | AI145: =+VLOOKUP(AG145,Catálogo!E:G,3,0) -> #N/A
J146: =+ROUND(H146/1000,0) -> 0 | K146: =+IFERROR(LEFT(AH146,3),0) -> 0 | L146: =+IFERROR(ABS(K146),"ok") -> 0 | M146: =+IF(L146="ok",J146,0) -> 0 | O146: =+M146+N146 -> 0 | AG146: =+CONCATENATE(S146,T146,V146) | AH146: =+VLOOKUP(AG146,Catálogo!E:F,2,0) -> #N/A | AI146: =+VLOOKUP(AG146,Catálogo!E:G,3,0) -> #N/A
J147: =+ROUND(H147/1000,0) -> 0 | K147: =+IFERROR(LEFT(AH147,3),0) -> 0 | L147: =+IFERROR(ABS(K147),"ok") -> 0 | M147: =+IF(L147="ok",J147,0) -> 0 | O147: =+M147+N147 -> 0 | AG147: =+CONCATENATE(S147,T147,V147) | AH147: =+VLOOKUP(AG147,Catálogo!E:F,2,0) -> #N/A | AI147: =+VLOOKUP(AG147,Catálogo!E:G,3,0) -> #N/A
J148: =+ROUND(H148/1000,0) -> 0 | K148: =+IFERROR(LEFT(AH148,3),0) -> 0 | L148: =+IFERROR(ABS(K148),"ok") -> 0 | M148: =+IF(L148="ok",J148,0) -> 0 | O148: =+M148+N148 -> 0 | AG148: =+CONCATENATE(S148,T148,V148) | AH148: =+VLOOKUP(AG148,Catálogo!E:F,2,0) -> #N/A | AI148: =+VLOOKUP(AG148,Catálogo!E:G,3,0) -> #N/A
J149: =+ROUND(H149/1000,0) -> 0 | K149: =+IFERROR(LEFT(AH149,3),0) -> 0 | L149: =+IFERROR(ABS(K149),"ok") -> 0 | M149: =+IF(L149="ok",J149,0) -> 0 | O149: =+M149+N149 -> 0 | AG149: =+CONCATENATE(S149,T149,V149) | AH149: =+VLOOKUP(AG149,Catálogo!E:F,2,0) -> #N/A | AI149: =+VLOOKUP(AG149,Catálogo!E:G,3,0) -> #N/A
J150: =+ROUND(H150/1000,0) -> 0 | K150: =+IFERROR(LEFT(AH150,3),0) -> 0 | L150: =+IFERROR(ABS(K150),"ok") -> 0 | M150: =+IF(L150="ok",J150,0) -> 0 | O150: =+M150+N150 -> 0 | AG150: =+CONCATENATE(S150,T150,V150) | AH150: =+VLOOKUP(AG150,Catálogo!E:F,2,0) -> #N/A | AI150: =+VLOOKUP(AG150,Catálogo!E:G,3,0) -> #N/A
J151: =+ROUND(H151/1000,0) -> 0 | K151: =+IFERROR(LEFT(AH151,3),0) -> 0 | L151: =+IFERROR(ABS(K151),"ok") -> 0 | M151: =+IF(L151="ok",J151,0) -> 0 | O151: =+M151+N151 -> 0 | AG151: =+CONCATENATE(S151,T151,V151) | AH151: =+VLOOKUP(AG151,Catálogo!E:F,2,0) -> #N/A | AI151: =+VLOOKUP(AG151,Catálogo!E:G,3,0) -> #N/A
J152: =+ROUND(H152/1000,0) -> 0 | K152: =+IFERROR(LEFT(AH152,3),0) -> 0 | L152: =+IFERROR(ABS(K152),"ok") -> 0 | M152: =+IF(L152="ok",J152,0) -> 0 | O152: =+M152+N152 -> 0 | AG152: =+CONCATENATE(S152,T152,V152) | AH152: =+VLOOKUP(AG152,Catálogo!E:F,2,0) -> #N/A | AI152: =+VLOOKUP(AG152,Catálogo!E:G,3,0) -> #N/A
J153: =+ROUND(H153/1000,0) -> 0 | K153: =+IFERROR(LEFT(AH153,3),0) -> 0 | L153: =+IFERROR(ABS(K153),"ok") -> 0 | M153: =+IF(L153="ok",J153,0) -> 0 | O153: =+M153+N153 -> 0 | AG153: =+CONCATENATE(S153,T153,V153) | AH153: =+VLOOKUP(AG153,Catálogo!E:F,2,0) -> #N/A | AI153: =+VLOOKUP(AG153,Catálogo!E:G,3,0) -> #N/A
... J251: =+ROUND(H251/1000,0) -> 0 | K251: =+IFERROR(LEFT(AH251,3),0) -> 0 | L251: =+IFERROR(ABS(K251),"ok") -> 0 | M251: =+IF(L251="ok",J251,0) -> 0 | O251: =+M251+N251 -> 0 | AG251: =+CONCATENATE(S251,T251,V251) | AH251: =+VLOOKUP(AG251,Catálogo!E:F,2,0) -> #N/A | AI251: =+VLOOKUP(AG251,Catálogo!E:G,3,0) -> #N/A
K252: =+IFERROR(LEFT(AH252,3),0) -> 0 | L252: =+IFERROR(ABS(K252),"ok") -> 0 | M252: =+IF(L252="ok",J252,0) -> 0 | O252: =+M252+N252 -> 0 | AG252: =+CONCATENATE(S252,T252,V252) | AH252: =+VLOOKUP(AG252,Catálogo!E:F,2,0) -> #N/A | AI252: =+VLOOKUP(AG252,Catálogo!E:G,3,0) -> #N/A
K253: =+IFERROR(LEFT(AH253,3),0) -> 0 | L253: =+IFERROR(ABS(K253),"ok") -> 0 | M253: =+IF(L253="ok",J253,0) -> 0 | O253: =+M253+N253 -> 0 | AG253: =+CONCATENATE(S253,T253,V253) | AH253: =+VLOOKUP(AG253,Catálogo!E:F,2,0) -> #N/A | AI253: =+VLOOKUP(AG253,Catálogo!E:G,3,0) -> #N/A
AG254: =+CONCATENATE(S254,T254,V254) | AH254: =+VLOOKUP(AG254,Catálogo!E:F,2,0) -> #N/A | AI254: =+VLOOKUP(AG254,Catálogo!E:G,3,0) -> #N/A
AG255: =+CONCATENATE(S255,T255,V255) | AH255: =+VLOOKUP(AG255,Catálogo!E:F,2,0) -> #N/A | AI255: =+VLOOKUP(AG255,Catálogo!E:G,3,0) -> #N/A
AG256: =+CONCATENATE(S256,T256,V256) | AH256: =+VLOOKUP(AG256,Catálogo!E:F,2,0) -> #N/A | AI256: =+VLOOKUP(AG256,Catálogo!E:G,3,0) -> #N/A
AG257: =+CONCATENATE(S257,T257,V257) | AH257: =+VLOOKUP(AG257,Catálogo!E:F,2,0) -> #N/A | AI257: =+VLOOKUP(AG257,Catálogo!E:G,3,0) -> #N/A
AG258: =+CONCATENATE(S258,T258,V258) | AH258: =+VLOOKUP(AG258,Catálogo!E:F,2,0) -> #N/A | AI258: =+VLOOKUP(AG258,Catálogo!E:G,3,0) -> #N/A
AG259: =+CONCATENATE(S259,T259,V259) | AH259: =+VLOOKUP(AG259,Catálogo!E:F,2,0) -> #N/A | AI259: =+VLOOKUP(AG259,Catálogo!E:G,3,0) -> #N/A
...

Sheet BalanzaAnterior
O7: =+SUM(O11:O251) -> 1
A10: Cuenta | B10: Scta | C10: SSCta | D10: Descripción | E10: Saldo Inicial | F10: Cargos | G10: Abonos | H10: Saldo Actual | K10: Quitar duplicados y cuentas de mayor | N10: Determinar saldos ajustados listos para trabajar | R10: Cuenta | S10: Scta | T10: SSCta | U10: Descripción | V10: Saldo Inicial | W10: Cargos | X10: Abonos | Y10: Saldo Actual | AE10: Rubro | AF10: Nota
A11: 103 | B11: 0 | C11: 0 | D11: BANCOS | E11: 22923.02 | F11: 3.5605501e+08 | G11: -3.5490394e+08 | H11: 1173988.2 | J11: =+ROUND(H11/1000,0) -> 1174 | K11: =+IFERROR(LEFT(AE11,3),0) -> 0 | L11: =+IFERROR(ABS(K11),"ok") -> 0 | M11: =+IF(L11="ok",J11,0) -> 0 | O11: =+M11+N11 -> 0 | R11: 103 | S11: 0 | T11: 0 | U11: BANCOS | V11: 22923.02 | W11: 3.5605501e+08 | X11: -3.5490394e+08 | Y11: =+O11 -> 0 | AD11: =+CONCATENATE(A11,B11,D11) -> 1030BANCOS | AE11: =+VLOOKUP(AD11,Catálogo!E:F,2,0) -> #N/A | AF11: =+VLOOKUP(AD11,Catálogo!E:G,3,0) -> 0
A12: 103 | B12: 1 | C12: 0 | D12: MONEDA NACIONAL | E12: 22923.02 | F12: 3.5605501e+08 | G12: -3.5490394e+08 | H12: 1173988.2 | J12: =+ROUND(H12/1000,0) -> 1174 | K12: =+IFERROR(LEFT(AE12,3),0) -> 0 | L12: =+IFERROR(ABS(K12),"ok") -> 0 | M12: =+IF(L12="ok",J12,0) -> 0 | O12: =+M12+N12 -> 0 | R12: 103 | S12: 1 | T12: 0 | U12: MONEDA NACIONAL | V12: 22923.02 | W12: 3.5605501e+08 | X12: -3.5490394e+08 | Y12: =+O12 -> 0 | AD12: =+CONCATENATE(A12,B12,D12) -> 1031MONEDA NACIONAL | AE12: =+VLOOKUP(AD12,Catálogo!E:F,2,0) -> #N/A | AF12: =+VLOOKUP(AD12,Catálogo!E:G,3,0) -> 0
A13: 103 | B13: 1 | C13: 2 | D13: BBVA CTA 0116008208 | E13: 22923.02 | F13: 2.4509195e+08 | G13: -2.4424089e+08 | H13: 873988.17 | J13: =+ROUND(H13/1000,0) -> 874 | K13: =+IFERROR(LEFT(AE13,3),0) -> Efe | L13: =+IFERROR(ABS(K13),"ok") -> ok | M13: =+IF(L13="ok",J13,0) -> 874 | O13: =+M13+N13 -> 874 | R13: 103 | S13: 1 | T13: 2 | U13: BBVA CTA 0116008208 | V13: 22923.02 | W13: 2.4509195e+08 | X13: -2.4424089e+08 | Y13: =+O13 -> 874 | AD13: =+CONCATENATE(A13,B13,D13) -> 1031BBVA CTA 0116008208 | AE13: =+VLOOKUP(AD13,Catálogo!E:F,2,0) -> Efectivo y equivalentes de efectivo | AF13: =+VLOOKUP(AD13,Catálogo!E:G,3,0) -> Depósitos en cuenta de cheques
A14: 103 | B14: 1 | C14: 5 | D14: INVEX CTA 05661 COBRANZA | E14: 0 | F14: 98632558 | G14: -98332558 | H14: 300000 | J14: =+ROUND(H14/1000,0) -> 300 | K14: =+IFERROR(LEFT(AE14,3),0) -> Efe | L14: =+IFERROR(ABS(K14),"ok") -> ok | M14: =+IF(L14="ok",J14,0) -> 300 | O14: =+M14+N14 -> 300 | R14: 103 | S14: 1 | T14: 5 | U14: INVEX CTA 05661 COBRANZA | V14: 0 | W14: 98632558 | X14: -98332558 | Y14: =+O14 -> 300 | AD14: =+CONCATENATE(A14,B14,D14) -> 1031INVEX CTA 05661 COBRANZA | AE14: =+VLOOKUP(AD14,Catálogo!E:F,2,0) -> Efectivo y equivalentes de efectivo | AF14: =+VLOOKUP(AD14,Catálogo!E:G,3,0) -> Depósitos en cuenta de cheques
A15: 103 | B15: 1 | C15: 6 | D15: INVEX CTA 05662 RESERVA | E15: 0 | F15: 12330500 | G15: -12330500 | H15: 0 | J15: =+ROUND(H15/1000,0) -> 0 | K15: =+IFERROR(LEFT(AE15,3),0) -> Efe | L15: =+IFERROR(ABS(K15),"ok") -> ok | M15: =+IF(L15="ok",J15,0) -> 0 | O15: =+M15+N15 -> 0 | R15: 103 | S15: 1 | T15: 6 | U15: INVEX CTA 05662 RESERVA | V15: 0 | W15: 12330500 | X15: -12330500 | Y15: =+O15 -> 0 | AD15: =+CONCATENATE(A15,B15,D15) -> 1031INVEX CTA 05662 RESERVA | AE15: =+VLOOKUP(AD15,Catálogo!E:F,2,0) -> Efectivo y equivalentes de efectivo | AF15: =+VLOOKUP(AD15,Catálogo!E:G,3,0) -> Depósitos en cuenta de cheques
A16: 104 | B16: 0 | C16: 0 | D16: INVERSIONES SISTEMA FINANCIERO | E16: 8699.59 | F16: 2.2878173e+09 | G16: -2.2423491e+09 | H16: 45476852 | J16: =+ROUND(H16/1000,0) -> 45477 | K16: =+IFERROR(LEFT(AE16,3),0) -> 0 | L16: =+IFERROR(ABS(K16),"ok") -> 0 | M16: =+IF(L16="ok",J16,0) -> 0 | O16: =+M16+N16 -> 0 | R16: 104 | S16: 0 | T16: 0 | U16: INVERSIONES SISTEMA FINANCIERO | V16: 8699.59 | W16: 2.2878173e+09 | X16: -2.2423491e+09 | Y16: =+O16 -> 0 | AD16: =+CONCATENATE(A16,B16,D16) -> 1040INVERSIONES SISTEMA FINANCIERO | AE16: =+VLOOKUP(AD16,Catálogo!E:F,2,0) -> #N/A | AF16: =+VLOOKUP(AD16,Catálogo!E:G,3,0) -> 0
A17: 104 | B17: 1 | C17: 0 | D17: MONEDA NACIONAL | E17: 8699.59 | F17: 2.2878173e+09 | G17: -2.2423491e+09 | H17: 45476852 | J17: =+ROUND(H17/1000,0) -> 45477 | K17: =+IFERROR(LEFT(AE17,3),0) -> 0 | L17: =+IFERROR(ABS(K17),"ok") -> 0 | M17: =+IF(L17="ok",J17,0) -> 0 | O17: =+M17+N17 -> 0 | R17: 104 | S17: 1 | T17: 0 | U17: MONEDA NACIONAL | V17: 8699.59 | W17: 2.2878173e+09 | X17: -2.2423491e+09 | Y17: =+O17 -> 0 | AD17: =+CONCATENATE(A17,B17,D17) -> 1041MONEDA NACIONAL | AE17: =+VLOOKUP(AD17,Catálogo!E:F,2,0) -> #N/A | AF17: =+VLOOKUP(AD17,Catálogo!E:G,3,0) -> 0
A18: 104 | B18: 1 | C18: 1 | D18: ACTINVER 8344681 CUENTA GENERAL | E18: 3.55 | F18: 1.2228753e+09 | G18: -1.2223359e+09 | H18: 539403.32 | J18: =+ROUND(H18/1000,0) -> 539 | K18: =+IFERROR(LEFT(AE18,3),0) -> Efe | L18: =+IFERROR(ABS(K18),"ok") -> ok | M18: =+IF(L18="ok",J18,0) -> 539 | O18: =+M18+N18 -> 539 | R18: 104 | S18: 1 | T18: 1 | U18: ACTINVER 8344681 CUENTA GENERAL | V18: 3.55 | W18: 1.2228753e+09 | X18: -1.2223359e+09 | Y18: =+O18 -> 539 | AD18: =+CONCATENATE(A18,B18,D18) -> 1041ACTINVER 8344681 CUENTA GENERAL | AE18: =+VLOOKUP(AD18,Catálogo!E:F,2,0) -> Efectivo y equivalentes de efectivo | AF18: =+VLOOKUP(AD18,Catálogo!E:G,3,0) -> Inversiones en valores realizables
A19: 104 | B19: 1 | C19: 2 | D19: ACTINVER 8344681 COMPLEMENTARIA | E19: 8696.04 | F19: 34345824 | G19: -2000694.7 | H19: 32353825 | J19: =+ROUND(H19/1000,0) -> 32354 | K19: =+IFERROR(LEFT(AE19,3),0) -> Efe | L19: =+IFERROR(ABS(K19),"ok") -> ok | M19: =+IF(L19="ok",J19,0) -> 32354 | O19: =+M19+N19 -> 32354 | R19: 104 | S19: 1 | T19: 2 | U19: ACTINVER 8344681 COMPLEMENTARIA | V19: 8696.04 | W19: 34345824 | X19: -2000694.7 | Y19: =+O19 -> 32354 | AD19: =+CONCATENATE(A19,B19,D19) -> 1041ACTINVER 8344681 COMPLEMENTARIA | AE19: =+VLOOKUP(AD19,Catálogo!E:F,2,0) -> Efectivo y equivalentes de efectivo | AF19: =+VLOOKUP(AD19,Catálogo!E:G,3,0) -> Inversiones en valores realizables
A20: 104 | B20: 1 | C20: 3 | D20: ACTINVER 5371322 CUENTA GENERAL | E20: 0 | F20: 6.2686253e+08 | G20: -6.268607e+08 | H20: 1825.57 | J20: =+ROUND(H20/1000,0) -> 2 | K20: =+IFERROR(LEFT(AE20,3),0) -> Efe | L20: =+IFERROR(ABS(K20),"ok") -> ok | M20: =+IF(L20="ok",J20,0) -> 2 | O20: =+M20+N20 -> 2 | R20: 104 | S20: 1 | T20: 3 | U20: ACTINVER 5371322 CUENTA GENERAL | V20: 0 | W20: 6.2686253e+08 | X20: -6.268607e+08 | Y20: =+O20 -> 2 | AD20: =+CONCATENATE(A20,B20,D20) -> 1041ACTINVER 5371322 CUENTA GENERAL | AE20: =+VLOOKUP(AD20,Catálogo!E:F,2,0) -> Efectivo y equivalentes de efectivo | AF20: =+VLOOKUP(AD20,Catálogo!E:G,3,0) -> Inversiones en valores realizables
A21: 104 | B21: 1 | C21: 4 | D21: ACTINVER CTA 5371322 COMPLEMENTARIA | E21: 0 | F21: 11511438 | G21: -11511438 | H21: 0 | J21: =+ROUND(H21/1000,0) -> 0 | K21: =+IFERROR(LEFT(AE21,3),0) -> Efe | L21: =+IFERROR(ABS(K21),"ok") -> ok | M21: =+IF(L21="ok",J21,0) -> 0 | O21: =+M21+N21 -> 0 | R21: 104 | S21: 1 | T21: 4 | U21: ACTINVER CTA 5371322 COMPLEMENTARIA | V21: 0 | W21: 11511438 | X21: -11511438 | Y21: =+O21 -> 0 | AD21: =+CONCATENATE(A21,B21,D21) -> 1041ACTINVER CTA 5371322 COMPLEMENTARIA | AE21: =+VLOOKUP(AD21,Catálogo!E:F,2,0) -> Efectivo y equivalentes de efectivo | AF21: =+VLOOKUP(AD21,Catálogo!E:G,3,0) -> Inversiones en valores realizables
A22: 104 | B22: 1 | C22: 5 | D22: INVEX CTA 0705 COBRA INVER | E22: 0 | F22: 88535259 | G22: -88535259 | H22: 0 | J22: =+ROUND(H22/1000,0) -> 0 | K22: =+IFERROR(LEFT(AE22,3),0) -> Efe | L22: =+IFERROR(ABS(K22),"ok") -> ok | M22: =+IF(L22="ok",J22,0) -> 0 | O22: =+M22+N22 -> 0 | R22: 104 | S22: 1 | T22: 5 | U22: INVEX CTA 0705 COBRA INVER | V22: 0 | W22: 88535259 | X22: -88535259 | Y22: =+O22 -> 0 | AD22: =+CONCATENATE(A22,B22,D22) -> 1041INVEX CTA 0705 COBRA INVER | AE22: =+VLOOKUP(AD22,Catálogo!E:F,2,0) -> Efectivo y equivalentes de efectivo | AF22: =+VLOOKUP(AD22,Catálogo!E:G,3,0) -> Inversiones en valores realizables
A23: 104 | B23: 1 | C23: 6 | D23: INVEX CTA 0705 COBRA INVER COMPLEMENTARI | E23: 0 | F23: 9657687.7 | G23: -9657687.7 | H23: 0 | J23: =+ROUND(H23/1000,0) -> 0 | K23: =+IFERROR(LEFT(AE23,3),0) -> Efe | L23: =+IFERROR(ABS(K23),"ok") -> ok | M23: =+IF(L23="ok",J23,0) -> 0 | O23: =+M23+N23 -> 0 | R23: 104 | S23: 1 | T23: 6 | U23: INVEX CTA 0705 COBRA INVER COMPLEMENTARI | V23: 0 | W23: 9657687.7 | X23: -9657687.7 | Y23: =+O23 -> 0 | AD23: =+CONCATENATE(A23,B23,D23) -> 1041INVEX CTA 0705 COBRA INVER COMPLEMENTARI | AE23: =+VLOOKUP(AD23,Catálogo!E:F,2,0) -> Efectivo y equivalentes de efectivo | AF23: =+VLOOKUP(AD23,Catálogo!E:G,3,0) -> Inversiones en valores realizables
A24: 104 | B24: 1 | C24: 7 | D24: INVEX CTA 0732 RESERVA INVER | E24: 0 | F24: 2.7035193e+08 | G24: -2.7035193e+08 | H24: 0.32 | J24: =+ROUND(H24/1000,0) -> 0 | K24: =+IFERROR(LEFT(AE24,3),0) -> Efe | L24: =+IFERROR(ABS(K24),"ok") -> ok | M24: =+IF(L24="ok",J24,0) -> 0 | O24: =+M24+N24 -> 0 | R24: 104 | S24: 1 | T24: 7 | U24: INVEX CTA 0732 RESERVA INVER | V24: 0 | W24: 2.7035193e+08 | X24: -2.7035193e+08 | Y24: =+O24 -> 0 | AD24: =+CONCATENATE(A24,B24,D24) -> 1041INVEX CTA 0732 RESERVA INVER | AE24: =+VLOOKUP(AD24,Catálogo!E:F,2,0) -> Efectivo y equivalentes de efectivo | AF24: ISR Retenido
A25: 104 | B25: 1 | C25: 8 | D25: INVEX CTA 0732 RESERVA INVER COMPLEMENTA | E25: 0 | F25: 23677356 | G25: -11095558 | H25: 12581798 | J25: =+ROUND(H25/1000,0) -> 12582 | K25: =+IFERROR(LEFT(AE25,3),0) -> Efe | L25: =+IFERROR(ABS(K25),"ok") -> ok | M25: =+IF(L25="ok",J25,0) -> 12582 | O25: =+M25+N25 -> 12582 | R25: 104 | S25: 1 | T25: 8 | U25: INVEX CTA 0732 RESERVA INVER COMPLEMENTA | V25: 0 | W25: 23677356 | X25: -11095558 | Y25: =+O25 -> 12582 | AD25: =+CONCATENATE(A25,B25,D25) -> 1041INVEX CTA 0732 RESERVA INVER COMPLEMENTA | AE25: =+VLOOKUP(AD25,Catálogo!E:F,2,0) -> Efectivo y equivalentes de efectivo | AF25: =+VLOOKUP(AD25,Catálogo!E:G,3,0) -> Inversiones en valores realizables
A26: 108 | B26: 0 | C26: 0 | D26: CLIENTES | E26: 0 | F26: 2848819.5 | G26: -2848819.5 | H26: 0 | J26: =+ROUND(H26/1000,0) -> 0 | K26: =+IFERROR(LEFT(AE26,3),0) -> 0 | L26: =+IFERROR(ABS(K26),"ok") -> 0 | M26: =+IF(L26="ok",J26,0) -> 0 | O26: =+M26+N26 -> 0 | R26: 108 | S26: 0 | T26: 0 | U26: CLIENTES | V26: 0 | W26: 2848819.5 | X26: -2848819.5 | Y26: =+O26 -> 0 | AD26: =+CONCATENATE(A26,B26,D26) -> 1080CLIENTES | AE26: =+VLOOKUP(AD26,Catálogo!E:F,2,0) -> #N/A | AF26: =+VLOOKUP(AD26,Catálogo!E:G,3,0) -> 0
A27: 108 | B27: 1 | C27: 0 | D27: CLIENTES M.N. | E27: 0 | F27: 2848819.5 | G27: -2848819.5 | H27: 0 | J27: =+ROUND(H27/1000,0) -> 0 | K27: =+IFERROR(LEFT(AE27,3),0) -> 0 | L27: =+IFERROR(ABS(K27),"ok") -> 0 | M27: =+IF(L27="ok",J27,0) -> 0 | O27: =+M27+N27 -> 0 | R27: 108 | S27: 1 | T27: 0 | U27: CLIENTES M.N. | V27: 0 | W27: 2848819.5 | X27: -2848819.5 | Y27: =+O27 -> 0 | AD27: =+CONCATENATE(A27,B27,D27) -> 1081CLIENTES M.N. | AE27: =+VLOOKUP(AD27,Catálogo!E:F,2,0) -> #N/A | AF27: Impuesto al Valor Agregado
A28: 109 | B28: 0 | C28: 0 | D28: DEUDORES DIVERSOS | E28: 15536081 | F28: 1.2598267e+08 | G28: -1.3156741e+08 | H28: 9951343.1 | J28: =+ROUND(H28/1000,0) -> 9951 | K28: =+IFERROR(LEFT(AE28,3),0) -> 0 | L28: =+IFERROR(ABS(K28),"ok") -> 0 | M28: =+IF(L28="ok",J28,0) -> 0 | O28: =+M28+N28 -> 0 | R28: 109 | S28: 0 | T28: 0 | U28: DEUDORES DIVERSOS | V28: 15536081 | W28: 1.2598267e+08 | X28: -1.3156741e+08 | Y28: =+O28 -> 0 | AD28: =+CONCATENATE(A28,B28,D28) -> 1090DEUDORES DIVERSOS | AE28: =+VLOOKUP(AD28,Catálogo!E:F,2,0) -> #N/A | AF28: =+VLOOKUP(AD28,Catálogo!E:G,3,0) -> 0
A29: 109 | B29: 1 | C29: 0 | D29: DEUDORES DIVERSOS M.N. | E29: 15536081 | F29: 1.2598267e+08 | G29: -1.3156741e+08 | H29: 9951343.1 | J29: =+ROUND(H29/1000,0) -> 9951 | K29: =+IFERROR(LEFT(AE29,3),0) -> Deu | L29: =+IFERROR(ABS(K29),"ok") -> ok | M29: =+IF(L29="ok",J29,0) -> 9951 | N29: =-SUM(M11:M251) -> 1 | O29: =+M29+N29 -> 9952 | R29: 109 | S29: 1 | T29: 0 | U29: DEUDORES DIVERSOS M.N. | V29: 15536081 | W29: 1.2598267e+08 | X29: -1.3156741e+08 | Y29: =+O29 -> 9952 | AD29: =+CONCATENATE(A29,B29,D29) -> 1091DEUDORES DIVERSOS M.N. | AE29: =+VLOOKUP(AD29,Catálogo!E:F,2,0) -> Deudores diversos y otras cuentas por cobrar | AF29: =+VLOOKUP(AD29,Catálogo!E:G,3,0) -> 0
A30: 113 | B30: 0 | C30: 0 | D30: ANTICIPO DE IMPUESTOS | E30: 7040.35 | F30: 8828.47 | G30: 0 | H30: 15868.82 | J30: =+ROUND(H30/1000,0) -> 16 | K30: =+IFERROR(LEFT(AE30,3),0) -> 0 | L30: =+IFERROR(ABS(K30),"ok") -> 0 | M30: =+IF(L30="ok",J30,0) -> 0 | O30: =+M30+N30 -> 0 | R30: 113 | S30: 0 | T30: 0 | U30: ANTICIPO DE IMPUESTOS | V30: 7040.35 | W30: 8828.47 | X30: 0 | Y30: =+O30 -> 0 | AD30: =+CONCATENATE(A30,B30,D30) -> 1130ANTICIPO DE IMPUESTOS | AE30: =+VLOOKUP(AD30,Catálogo!E:F,2,0) -> #N/A | AF30: =+VLOOKUP(AD30,Catálogo!E:G,3,0) -> 0
A31: 113 | B31: 1 | C31: 0 | D31: ISR | E31: 7040.35 | F31: 8828.47 | G31: 0 | H31: 15868.82 | J31: =+ROUND(H31/1000,0) -> 16 | K31: =+IFERROR(LEFT(AE31,3),0) -> 0 | L31: =+IFERROR(ABS(K31),"ok") -> 0 | M31: =+IF(L31="ok",J31,0) -> 0 | O31: =+M31+N31 -> 0 | R31: 113 | S31: 1 | T31: 0 | U31: ISR | V31: 7040.35 | W31: 8828.47 | X31: 0 | Y31: =+O31 -> 0 | AD31: =+CONCATENATE(A31,B31,D31) -> 1131ISR | AE31: =+VLOOKUP(AD31,Catálogo!E:F,2,0) -> #N/A | AF31: =+VLOOKUP(AD31,Catálogo!E:G,3,0) -> 0
A32: 113 | B32: 1 | C32: 1 | D32: ISR PAGO PROVISIONALES | E32: 0 | F32: 12.15 | G32: 0 | H32: 12.15 | J32: =+ROUND(H32/1000,0) -> 0 | K32: =+IFERROR(LEFT(AE32,3),0) -> Imp | L32: =+IFERROR(ABS(K32),"ok") -> ok | M32: =+IF(L32="ok",J32,0) -> 0 | O32: =+M32+N32 -> 0 | R32: 113 | S32: 1 | T32: 1 | U32: ISR PAGO PROVISIONALES | V32: 0 | W32: 12.15 | X32: 0 | Y32: =+O32 -> 0 | AD32: =+CONCATENATE(A32,B32,D32) -> 1131ISR PAGO PROVISIONALES | AE32: =+VLOOKUP(AD32,Catálogo!E:F,2,0) -> Impuestos por recuperar | AF32: =+VLOOKUP(AD32,Catálogo!E:G,3,0) -> ISR Retenido
A33: 113 | B33: 1 | C33: 2 | D33: ISR RETENCIONES BANCOS | E33: 7040.35 | F33: 8816.32 | G33: 0 | H33: 15856.67 | J33: =+ROUND(H33/1000,0) -> 16 | K33: =+IFERROR(LEFT(AE33,3),0) -> Imp | L33: =+IFERROR(ABS(K33),"ok") -> ok | M33: =+IF(L33="ok",J33,0) -> 16 | O33: =+M33+N33 -> 16 | R33: 113 | S33: 1 | T33: 2 | U33: ISR RETENCIONES BANCOS | V33: 7040.35 | W33: 8816.32 | X33: 0 | Y33: =+O33 -> 16 | AD33: =+CONCATENATE(A33,B33,D33) -> 1131ISR RETENCIONES BANCOS | AE33: =+VLOOKUP(AD33,Catálogo!E:F,2,0) -> Impuestos por recuperar | AF33: =+VLOOKUP(AD33,Catálogo!E:G,3,0) -> ISR Retenido
A34: 114 | B34: 0 | C34: 0 | D34: IMPUESTOS A FAVOR | E34: 21849234 | F34: 19850154 | G34: -392940.62 | H34: 41306447 | J34: =+ROUND(H34/1000,0) -> 41306 | K34: =+IFERROR(LEFT(AE34,3),0) -> 0 | L34: =+IFERROR(ABS(K34),"ok") -> 0 | M34: =+IF(L34="ok",J34,0) -> 0 | O34: =+M34+N34 -> 0 | R34: 114 | S34: 0 | T34: 0 | U34: IMPUESTOS A FAVOR | V34: 21849234 | W34: 19850154 | X34: -392940.62 | Y34: =+O34 -> 0 | AD34: =+CONCATENATE(A34,B34,D34) -> 1140IMPUESTOS A FAVOR | AE34: =+VLOOKUP(AD34,Catálogo!E:F,2,0) -> #N/A | AF34: =+VLOOKUP(AD34,Catálogo!E:G,3,0) -> 0
A35: 114 | B35: 1 | C35: 0 | D35: IVA SALDO A FAVOR | E35: 21849234 | F35: 19850154 | G35: -392940.62 | H35: 41306447 | J35: =+ROUND(H35/1000,0) -> 41306 | K35: =+IFERROR(LEFT(AE35,3),0) -> 0 | L35: =+IFERROR(ABS(K35),"ok") -> 0 | M35: =+IF(L35="ok",J35,0) -> 0 | O35: =+M35+N35 -> 0 | R35: 114 | S35: 1 | T35: 0 | U35: IVA SALDO A FAVOR | V35: 21849234 | W35: 19850154 | X35: -392940.62 | Y35: =+O35 -> 0 | AD35: =+CONCATENATE(A35,B35,D35) -> 1141IVA SALDO A FAVOR | AE35: =+VLOOKUP(AD35,Catálogo!E:F,2,0) -> #N/A | AF35: =+VLOOKUP(AD35,Catálogo!E:G,3,0) -> 0
A36: 114 | B36: 1 | C36: 1 | D36: IVA SALDO A FAVOR AL 16% | E36: 21849234 | F36: 19850154 | G36: -392940.62 | H36: 41306447 | J36: =+ROUND(H36/1000,0) -> 41306 | K36: =+IFERROR(LEFT(AE36,3),0) -> Inv | L36: =+IFERROR(ABS(K36),"ok") -> ok | M36: =+IF(L36="ok",J36,0) -> 41306 | O36: =+M36+N36 -> 41306 | R36: 114 | S36: 1 | T36: 1 | U36: IVA SALDO A FAVOR AL 16% | V36: 21849234 | W36: 19850154 | X36: -392940.62 | Y36: =+O36 -> 41306 | AD36: =+CONCATENATE(A36,B36,D36) -> 1141IVA SALDO A FAVOR AL 16% | AE36: =+VLOOKUP(AD36,Catálogo!E:F,2,0) -> Inventarios inmobiliarios y costos pagados por anticipado | AF36: =+VLOOKUP(AD36,Catálogo!E:G,3,0) -> Impuesto al Valor Agregado
A37: 115 | B37: 0 | C37: 0 | D37: IMPUESTOS A FAVOR NO CAUSADO | E37: 3744074.6 | F37: 18144824 | G37: -19851507 | H37: 2037391.4 | J37: =+ROUND(H37/1000,0) -> 2037 | K37: =+IFERROR(LEFT(AE37,3),0) -> 0 | L37: =+IFERROR(ABS(K37),"ok") -> 0 | M37: =+IF(L37="ok",J37,0) -> 0 | O37: =+M37+N37 -> 0 | R37: 115 | S37: 0 | T37: 0 | U37: IMPUESTOS A FAVOR NO CAUSADO | V37: 3744074.6 | W37: 18144824 | X37: -19851507 | Y37: =+O37 -> 0 | AD37: =+CONCATENATE(A37,B37,D37) -> 1150IMPUESTOS A FAVOR NO CAUSADO | AE37: =+VLOOKUP(AD37,Catálogo!E:F,2,0) -> #N/A | AF37: =+VLOOKUP(AD37,Catálogo!E:G,3,0) -> 0
A38: 115 | B38: 1 | C38: 0 | D38: IVA ACREDITABLE NO PAGADO | E38: 3744074.6 | F38: 18144824 | G38: -19851507 | H38: 2037391.4 | J38: =+ROUND(H38/1000,0) -> 2037 | K38: =+IFERROR(LEFT(AE38,3),0) -> 0 | L38: =+IFERROR(ABS(K38),"ok") -> 0 | M38: =+IF(L38="ok",J38,0) -> 0 | O38: =+M38+N38 -> 0 | R38: 115 | S38: 1 | T38: 0 | U38: IVA ACREDITABLE NO PAGADO | V38: 3744074.6 | W38: 18144824 | X38: -19851507 | Y38: =+O38 -> 0 | AD38: =+CONCATENATE(A38,B38,D38) -> 1151IVA ACREDITABLE NO PAGADO | AE38: =+VLOOKUP(AD38,Catálogo!E:F,2,0) -> #N/A | AF38: =+VLOOKUP(AD38,Catálogo!E:G,3,0) -> 0
A39: 115 | B39: 1 | C39: 1 | D39: IVA ACREDITABLE NO PAGADO AL 16% | E39: 3744074.6 | F39: 18144824 | G39: -19851507 | H39: 2037391.4 | J39: =+ROUND(H39/1000,0) -> 2037 | K39: =+IFERROR(LEFT(AE39,3),0) -> Deu | L39: =+IFERROR(ABS(K39),"ok") -> ok | M39: =+IF(L39="ok",J39,0) -> 2037 | O39: =+M39+N39 -> 2037 | R39: 115 | S39: 1 | T39: 1 | U39: IVA ACREDITABLE NO PAGADO AL 16% | V39: 3744074.6 | W39: 18144824 | X39: -19851507 | Y39: =+O39 -> 2037 | AD39: =+CONCATENATE(A39,B39,D39) -> 1151IVA ACREDITABLE NO PAGADO AL 16% | AE39: =+VLOOKUP(AD39,Catálogo!E:F,2,0) -> Deudores diversos y otras cuentas por cobrar | AF39: =+VLOOKUP(AD39,Catálogo!E:G,3,0) -> 0
A40: 120 | B40: 0 | C40: 0 | D40: ANTICIPOS CONSTRUCCION | E40: 10998418 | F40: 0 | G40: 0 | H40: 10998418 | J40: =+ROUND(H40/1000,0) -> 10998 | K40: =+IFERROR(LEFT(AE40,3),0) -> 0 | L40: =+IFERROR(ABS(K40),"ok") -> 0 | M40: =+IF(L40="ok",J40,0) -> 0 | O40: =+M40+N40 -> 0 | R40: 120 | S40: 0 | T40: 0 | U40: ANTICIPOS CONSTRUCCION | V40: 10998418 | W40: 0 | X40: 0 | Y40: =+O40 -> 0 | AD40: =+CONCATENATE(A40,B40,D40) -> 1200ANTICIPOS CONSTRUCCION | AE40: =+VLOOKUP(AD40,Catálogo!E:F,2,0) -> #N/A | AF40: =+VLOOKUP(AD40,Catálogo!E:G,3,0) -> 0
A41: 120 | B41: 1 | C41: 0 | D41: ANTICIPOS CONSTRUCCION M.N. | E41: 10998418 | F41: 0 | G41: 0 | H41: 10998418 | J41: =+ROUND(H41/1000,0) -> 10998 | K41: =+IFERROR(LEFT(AE41,3),0) -> Inv | L41: =+IFERROR(ABS(K41),"ok") -> ok | M41: =+IF(L41="ok",J41,0) -> 10998 | O41: =+M41+N41 -> 10998 | R41: 120 | S41: 1 | T41: 0 | U41: ANTICIPOS CONSTRUCCION M.N. | V41: 10998418 | W41: 0 | X41: 0 | Y41: =+O41 -> 10998 | AD41: =+CONCATENATE(A41,B41,D41) -> 1201ANTICIPOS CONSTRUCCION M.N. | AE41: =+VLOOKUP(AD41,Catálogo!E:F,2,0) -> Inventarios inmobiliarios y costos pagados por anticipado | AF41: =+VLOOKUP(AD41,Catálogo!E:G,3,0) -> Otros pagos anticipados (v)
... A77: 125 | B77: 1 | C77: 2 | D77: DEPRECIACIÓN EQP COMPUTO | E77: -81980 | F77: 0 | G77: -53430 | H77: -135410 | J77: =+ROUND(H77/1000,0) -> -135 | K77: =+IFERROR(LEFT(AE77,3),0) -> Mob | L77: =+IFERROR(ABS(K77),"ok") -> ok | M77: =+IF(L77="ok",J77,0) -> -135 | O77: =+M77+N77 -> -135 | R77: 125 | S77: 1 | T77: 2 | U77: DEPRECIACIÓN EQP COMPUTO | V77: -81980 | W77: 0 | X77: -53430 | Y77: =+O77 -> -135 | AD77: =+CONCATENATE(A77,B77,D77) -> 1251DEPRECIACIÓN EQP COMPUTO | AE77: =+VLOOKUP(AD77,Catálogo!E:F,2,0) -> Mobiliario y equipo, neto | AF77: =+VLOOKUP(AD77,Catálogo!E:G,3,0) -> 0
A78: 173 | B78: 0 | C78: 0 | D78: DEPOSITOS EN GARANTIA | E78: 0 | F78: 3074005 | G78: -2957500 | H78: 116505 | J78: =+ROUND(H78/1000,0) -> 117 | K78: =+IFERROR(LEFT(AE78,3),0) -> 0 | L78: =+IFERROR(ABS(K78),"ok") -> 0 | M78: =+IF(L78="ok",J78,0) -> 0 | O78: =+M78+N78 -> 0 | R78: 173 | S78: 0 | T78: 0 | U78: DEPOSITOS EN GARANTIA | V78: 0 | W78: 3074005 | X78: -2957500 | Y78: =+O78 -> 0 | AD78: =+CONCATENATE(A78,B78,D78) -> 1730DEPOSITOS EN GARANTIA | AE78: =+VLOOKUP(AD78,Catálogo!E:F,2,0) -> #N/A | AF78: 0
A79: 173 | B79: 1 | C79: 0 | D79: DEPOSITOS EN GARANTIA M.N. | E79: 0 | F79: 3074005 | G79: -2957500 | H79: 116505 | J79: =+ROUND(H79/1000,0) -> 117 | K79: =+IFERROR(LEFT(AE79,3),0) -> Inv | L79: =+IFERROR(ABS(K79),"ok") -> ok | M79: =+IF(L79="ok",J79,0) -> 117 | O79: =+M79+N79 -> 117 | R79: 173 | S79: 1 | T79: 0 | U79: DEPOSITOS EN GARANTIA M.N. | V79: 0 | W79: 3074005 | X79: -2957500 | Y79: =+O79 -> 117 | AD79: =+CONCATENATE(A79,B79,D79) -> 1731DEPOSITOS EN GARANTIA M.N. | AE79: =+VLOOKUP(AD79,Catálogo!E:F,2,0) -> Inventarios inmobiliarios y costos pagados por anticipado | AF79: =+VLOOKUP(AD79,Catálogo!E:G,3,0) -> Otros pagos anticipados (v)
A80: 201 | B80: 0 | C80: 0 | D80: PROVEEDORES | E80: -18621429 | F80: 3.1238242e+08 | G80: -3.0111823e+08 | H80: -7357238.8 | J80: =+ROUND(H80/1000,0) -> -7357 | K80: =+IFERROR(LEFT(AE80,3),0) -> 0 | L80: =+IFERROR(ABS(K80),"ok") -> 0 | M80: =+IF(L80="ok",J80,0) -> 0 | O80: =+M80+N80 -> 0 | R80: 201 | S80: 0 | T80: 0 | U80: PROVEEDORES | V80: -18621429 | W80: 3.1238242e+08 | X80: -3.0111823e+08 | Y80: =+O80 -> 0 | AD80: =+CONCATENATE(A80,B80,D80) -> 2010PROVEEDORES | AE80: =+VLOOKUP(AD80,Catálogo!E:F,2,0) -> #N/A | AF80: =+VLOOKUP(AD80,Catálogo!E:G,3,0) -> 0
A81: 201 | B81: 1 | C81: 0 | D81: PROVEEDORES M.N. | E81: -18438327 | F81: 3.1029025e+08 | G81: -2.9921328e+08 | H81: -7361354.8 | J81: =+ROUND(H81/1000,0) -> -7361 | K81: =+IFERROR(LEFT(AE81,3),0) -> Pro | L81: =+IFERROR(ABS(K81),"ok") -> ok | M81: =+IF(L81="ok",J81,0) -> -7361 | O81: =+M81+N81 -> -7361 | R81: 201 | S81: 1 | T81: 0 | U81: PROVEEDORES M.N. | V81: -18438327 | W81: 3.1029025e+08 | X81: -2.9921328e+08 | Y81: =+O81 -> -7361 | AD81: =+CONCATENATE(A81,B81,D81) -> 2011PROVEEDORES M.N. | AE81: =+VLOOKUP(AD81,Catálogo!E:F,2,0) -> Proveedores y acreedores diversos | AF81: =+VLOOKUP(AD81,Catálogo!E:G,3,0) -> 0
A82: 201 | B82: 2 | C82: 0 | D82: PROVEEDORES M.E. | E82: -9457.03 | F82: 122319.1 | G82: -112862.07 | H82: 0 | J82: =+ROUND(H82/1000,0) -> 0 | K82: =+IFERROR(LEFT(AE82,3),0) -> Pro | L82: =+IFERROR(ABS(K82),"ok") -> ok | M82: =+IF(L82="ok",J82,0) -> 0 | O82: =+M82+N82 -> 0 | R82: 201 | S82: 2 | T82: 0 | U82: PROVEEDORES M.E. | V82: -9457.03 | W82: 122319.1 | X82: -112862.07 | Y82: =+O82 -> 0 | AD82: =+CONCATENATE(A82,B82,D82) -> 2012PROVEEDORES M.E. | AE82: =+VLOOKUP(AD82,Catálogo!E:F,2,0) -> Proveedores y acreedores diversos | AF82: =+VLOOKUP(AD82,Catálogo!E:G,3,0) -> 0
A83: 201 | B83: 200 | C83: 0 | D83: PROVEEDORES COMPLEMENTARIA | E83: -173644.96 | F83: 1969851.2 | G83: -1792090.3 | H83: 4116 | J83: =+ROUND(H83/1000,0) -> 4 | K83: =+IFERROR(LEFT(AE83,3),0) -> Pro | L83: =+IFERROR(ABS(K83),"ok") -> ok | M83: =+IF(L83="ok",J83,0) -> 4 | O83: =+M83+N83 -> 4 | R83: 201 | S83: 200 | T83: 0 | U83: PROVEEDORES COMPLEMENTARIA | V83: -173644.96 | W83: 1969851.2 | X83: -1792090.3 | Y83: =+O83 -> 4 | AD83: =+CONCATENATE(A83,B83,D83) -> 201200PROVEEDORES COMPLEMENTARIA | AE83: =+VLOOKUP(AD83,Catálogo!E:F,2,0) -> Proveedores y acreedores diversos | AF83: =+VLOOKUP(AD83,Catálogo!E:G,3,0) -> 0
A84: 202 | B84: 0 | C84: 0 | D84: ACREEDORES DIVERSOS | E84: -2500000 | F84: 27316000 | G84: -30539533 | H84: -5723533 | J84: =+ROUND(H84/1000,0) -> -5724 | K84: =+IFERROR(LEFT(AE84,3),0) -> 0 | L84: =+IFERROR(ABS(K84),"ok") -> 0 | M84: =+IF(L84="ok",J84,0) -> 0 | O84: =+M84+N84 -> 0 | R84: 202 | S84: 0 | T84: 0 | U84: ACREEDORES DIVERSOS | V84: -2500000 | W84: 27316000 | X84: -30539533 | Y84: =+O84 -> 0 | AD84: =+CONCATENATE(A84,B84,D84) -> 2020ACREEDORES DIVERSOS | AE84: =+VLOOKUP(AD84,Catálogo!E:F,2,0) -> #N/A | AF84: =+VLOOKUP(AD84,Catálogo!E:G,3,0) -> 0
A85: 202 | B85: 1 | C85: 0 | D85: ACREEDORES M.N. | E85: -2500000 | F85: 27316000 | G85: -30539533 | H85: -5723533 | J85: =+ROUND(H85/1000,0) -> -5724 | K85: =+IFERROR(LEFT(AE85,3),0) -> Pro | L85: =+IFERROR(ABS(K85),"ok") -> ok | M85: =+IF(L85="ok",J85,0) -> -5724 | O85: =+M85+N85 -> -5724 | R85: 202 | S85: 1 | T85: 0 | U85: ACREEDORES M.N. | V85: -2500000 | W85: 27316000 | X85: -30539533 | Y85: =+O85 -> -5724 | AD85: =+CONCATENATE(A85,B85,D85) -> 2021ACREEDORES M.N. | AE85: =+VLOOKUP(AD85,Catálogo!E:F,2,0) -> Proveedores y acreedores diversos | AF85: =+VLOOKUP(AD85,Catálogo!E:G,3,0) -> 0
A86: 218 | B86: 0 | C86: 0 | D86: IMPUESTOS POR PAGAR | E86: -42707.23 | F86: 2129273.6 | G86: -2476669 | H86: -390102.63 | J86: =+ROUND(H86/1000,0) -> -390 | K86: =+IFERROR(LEFT(AE86,3),0) -> 0 | L86: =+IFERROR(ABS(K86),"ok") -> 0 | M86: =+IF(L86="ok",J86,0) -> 0 | O86: =+M86+N86 -> 0 | R86: 218 | S86: 0 | T86: 0 | U86: IMPUESTOS POR PAGAR | V86: -42707.23 | W86: 2129273.6 | X86: -2476669 | Y86: =+O86 -> 0 | AD86: =+CONCATENATE(A86,B86,D86) -> 2180IMPUESTOS POR PAGAR | AE86: =+VLOOKUP(AD86,Catálogo!E:F,2,0) -> #N/A | AF86: =+VLOOKUP(AD86,Catálogo!E:G,3,0) -> 0
A87: 218 | B87: 1 | C87: 0 | D87: ISR | E87: -21438.63 | F87: 642011.18 | G87: -756372.16 | H87: -135799.61 | J87: =+ROUND(H87/1000,0) -> -136 | K87: =+IFERROR(LEFT(AE87,3),0) -> 0 | L87: =+IFERROR(ABS(K87),"ok") -> 0 | M87: =+IF(L87="ok",J87,0) -> 0 | O87: =+M87+N87 -> 0 | R87: 218 | S87: 1 | T87: 0 | U87: ISR | V87: -21438.63 | W87: 642011.18 | X87: -756372.16 | Y87: =+O87 -> 0 | AD87: =+CONCATENATE(A87,B87,D87) -> 2181ISR | AE87: =+VLOOKUP(AD87,Catálogo!E:F,2,0) -> #N/A | AF87: =+VLOOKUP(AD87,Catálogo!E:G,3,0) -> 0
A88: 218 | B88: 1 | C88: 3 | D88: ISR RETENCIONES SERVICIOS PROFESIONALES | E88: -21438.63 | F88: 346584.18 | G88: -411287.98 | H88: -86142.43 | J88: =+ROUND(H88/1000,0) -> -86 | K88: =+IFERROR(LEFT(AE88,3),0) -> Imp | L88: =+IFERROR(ABS(K88),"ok") -> ok | M88: =+IF(L88="ok",J88,0) -> -86 | O88: =+M88+N88 -> -86 | R88: 218 | S88: 1 | T88: 3 | U88: ISR RETENCIONES SERVICIOS PROFESIONALES | V88: -21438.63 | W88: 346584.18 | X88: -411287.98 | Y88: =+O88 -> -86 | AD88: =+CONCATENATE(A88,B88,D88) -> 2181ISR RETENCIONES SERVICIOS PROFESIONALES | AE88: =+VLOOKUP(AD88,Catálogo!E:F,2,0) -> Impuestos por pagar | AF88: =+VLOOKUP(AD88,Catálogo!E:G,3,0) -> 0
A89: 218 | B89: 1 | C89: 8 | D89: ISR RETENCIONES EFECTIVAMENTE PAGADO | E89: 0 | F89: 295427 | G89: -345084.18 | H89: -49657.18 | J89: =+ROUND(H89/1000,0) -> -50 | K89: =+IFERROR(LEFT(AE89,3),0) -> Imp | L89: =+IFERROR(ABS(K89),"ok") -> ok | M89: =+IF(L89="ok",J89,0) -> -50 | O89: =+M89+N89 -> -50 | R89: 218 | S89: 1 | T89: 8 | U89: ISR RETENCIONES EFECTIVAMENTE PAGADO | V89: 0 | W89: 295427 | X89: -345084.18 | Y89: =+O89 -> -50 | AD89: =+CONCATENATE(A89,B89,D89) -> 2181ISR RETENCIONES EFECTIVAMENTE PAGADO | AE89: =+VLOOKUP(AD89,Catálogo!E:F,2,0) -> Impuestos por pagar | AF89: =+VLOOKUP(AD89,Catálogo!E:G,3,0) -> 0
A90: 218 | B90: 2 | C90: 0 | D90: IVA | E90: -21268.6 | F90: 1487262.4 | G90: -1720296.8 | H90: -254303.02 | J90: =+ROUND(H90/1000,0) -> -254 | K90: =+IFERROR(LEFT(AE90,3),0) -> 0 | L90: =+IFERROR(ABS(K90),"ok") -> 0 | M90: =+IF(L90="ok",J90,0) -> 0 | O90: =+M90+N90 -> 0 | R90: 218 | S90: 2 | T90: 0 | U90: IVA | V90: -21268.6 | W90: 1487262.4 | X90: -1720296.8 | Y90: =+O90 -> 0 | AD90: =+CONCATENATE(A90,B90,D90) -> 2182IVA | AE90: =+VLOOKUP(AD90,Catálogo!E:F,2,0) -> #N/A | AF90: =+VLOOKUP(AD90,Catálogo!E:G,3,0) -> 0
... A116: 601 | B116: 0 | C116: 0 | D116: GASTOS DE ADMINISTRACIÓN | E116: 0 | F116: 58804.54 | G116: 0 | H116: 58804.54 | J116: =+ROUND(H116/1000,0) -> 59 | K116: =+IFERROR(LEFT(AE116,3),0) -> 0 | L116: =+IFERROR(ABS(K116),"ok") -> 0 | M116: =+IF(L116="ok",J116,0) -> 0 | O116: =+M116+N116 -> 0 | R116: 601 | S116: 0 | T116: 0 | U116: GASTOS DE ADMINISTRACIÓN | V116: 0 | W116: 58804.54 | X116: 0 | Y116: =+O116 -> 0 | AD116: =+CONCATENATE(A116,B116,D116) -> 6010GASTOS DE ADMINISTRACIÓN | AE116: =+VLOOKUP(AD116,Catálogo!E:F,2,0) -> #N/A | AF116: =+VLOOKUP(AD116,Catálogo!E:G,3,0) -> 0
A117: 601 | B117: 22 | C117: 0 | D117: GASTOS NO DEDUCIBLES | E117: 0 | F117: 5374.54 | G117: 0 | H117: 5374.54 | J117: =+ROUND(H117/1000,0) -> 5 | K117: =+IFERROR(LEFT(AE117,3),0) -> Gas | L117: =+IFERROR(ABS(K117),"ok") -> ok | M117: =+IF(L117="ok",J117,0) -> 5 | N117: 1 | O117: =+M117+N117 -> 6 | R117: 601 | S117: 22 | T117: 0 | U117: GASTOS NO DEDUCIBLES | V117: 0 | W117: 5374.54 | X117: 0 | Y117: =+O117 -> 6 | AD117: =+CONCATENATE(A117,B117,D117) -> 60122GASTOS NO DEDUCIBLES | AE117: =+VLOOKUP(AD117,Catálogo!E:F,2,0) -> Gastos operativos | AF117: =+VLOOKUP(AD117,Catálogo!E:G,3,0) -> 0
A118: 601 | B118: 101 | C118: 0 | D118: DEPRECIACION DEL EJERCICIO | E118: 0 | F118: 53430 | G118: 0 | H118: 53430 | J118: =+ROUND(H118/1000,0) -> 53 | K118: =+IFERROR(LEFT(AE118,3),0) -> 0 | L118: =+IFERROR(ABS(K118),"ok") -> 0 | M118: =+IF(L118="ok",J118,0) -> 0 | O118: =+M118+N118 -> 0 | R118: 601 | S118: 101 | T118: 0 | U118: DEPRECIACION DEL EJERCICIO | V118: 0 | W118: 53430 | X118: 0 | Y118: =+O118 -> 0 | AD118: =+CONCATENATE(A118,B118,D118) -> 601101DEPRECIACION DEL EJERCICIO | AE118: =+VLOOKUP(AD118,Catálogo!E:F,2,0) -> #N/A | AF118: =+VLOOKUP(AD118,Catálogo!E:G,3,0) -> 0
A119: 601 | B119: 101 | C119: 2 | D119: DEPRECIACION EQUIPO DE COMPUTO | E119: 0 | F119: 53430 | G119: 0 | H119: 53430 | J119: =+ROUND(H119/1000,0) -> 53 | K119: =+IFERROR(LEFT(AE119,3),0) -> Gas | L119: =+IFERROR(ABS(K119),"ok") -> ok | M119: =+IF(L119="ok",J119,0) -> 53 | O119: =+M119+N119 -> 53 | R119: 601 | S119: 101 | T119: 2 | U119: DEPRECIACION EQUIPO DE COMPUTO | V119: 0 | W119: 53430 | X119: 0 | Y119: =+O119 -> 53 | AD119: =+CONCATENATE(A119,B119,D119) -> 601101DEPRECIACION EQUIPO DE COMPUTO | AE119: =+VLOOKUP(AD119,Catálogo!E:F,2,0) -> Gastos operativos | AF119: =+VLOOKUP(AD119,Catálogo!E:G,3,0) -> 0
A120: 701 | B120: 0 | C120: 0 | D120: PRODUCTOS FINANCIEROS | E120: 0 | F120: 0 | G120: -856163.29 | H120: -856163.29 | J120: =+ROUND(H120/1000,0) -> -856 | K120: =+IFERROR(LEFT(AE120,3),0) -> 0 | L120: =+IFERROR(ABS(K120),"ok") -> 0 | M120: =+IF(L120="ok",J120,0) -> 0 | O120: =+M120+N120 -> 0 | R120: 701 | S120: 0 | T120: 0 | U120: PRODUCTOS FINANCIEROS | V120: 0 | W120: 0 | X120: -856163.29 | Y120: =+O120 -> 0 | AD120: =+CONCATENATE(A120,B120,D120) -> 7010PRODUCTOS FINANCIEROS | AE120: =+VLOOKUP(AD120,Catálogo!E:F,2,0) -> #N/A | AF120: =+VLOOKUP(AD120,Catálogo!E:G,3,0) -> 0
A121: 701 | B121: 1 | C121: 0 | D121: INTERESES GANADOS | E121: 0 | F121: 0 | G121: -846353.3 | H121: -846353.3 | J121: =+ROUND(H121/1000,0) -> -846 | K121: =+IFERROR(LEFT(AE121,3),0) -> Otr | L121: =+IFERROR(ABS(K121),"ok") -> ok | M121: =+IF(L121="ok",J121,0) -> -846 | O121: =+M121+N121 -> -846 | R121: 701 | S121: 1 | T121: 0 | U121: INTERESES GANADOS | V121: 0 | W121: 0 | X121: -846353.3 | Y121: =+O121 -> -846 | AD121: =+CONCATENATE(A121,B121,D121) -> 7011INTERESES GANADOS | AE121: Otros ingresos | AF121: =+VLOOKUP(AD121,Catálogo!E:G,3,0) -> 0
A122: 701 | B122: 2 | C122: 0 | D122: UTILIDAD CAMBIARIA | E122: 0 | F122: 0 | G122: -9809.99 | H122: -9809.99 | J122: =+ROUND(H122/1000,0) -> -10 | K122: =+IFERROR(LEFT(AE122,3),0) -> Otr | L122: =+IFERROR(ABS(K122),"ok") -> ok | M122: =+IF(L122="ok",J122,0) -> -10 | O122: =+M122+N122 -> -10 | R122: 701 | S122: 2 | T122: 0 | U122: UTILIDAD CAMBIARIA | V122: 0 | W122: 0 | X122: -9809.99 | Y122: =+O122 -> -10 | AD122: =+CONCATENATE(A122,B122,D122) -> 7012UTILIDAD CAMBIARIA | AE122: Otros ingresos | AF122: =+VLOOKUP(AD122,Catálogo!E:G,3,0) -> 0
A123: 702 | B123: 0 | C123: 0 | D123: GASTOS FINANCIEROS | E123: 0 | F123: 12774.05 | G123: 0 | H123: 12774.05 | J123: =+ROUND(H123/1000,0) -> 13 | K123: =+IFERROR(LEFT(AE123,3),0) -> 0 | L123: =+IFERROR(ABS(K123),"ok") -> 0 | M123: =+IF(L123="ok",J123,0) -> 0 | O123: =+M123+N123 -> 0 | R123: 702 | S123: 0 | T123: 0 | U123: GASTOS FINANCIEROS | V123: 0 | W123: 12774.05 | X123: 0 | Y123: =+O123 -> 0 | AD123: =+CONCATENATE(A123,B123,D123) -> 7020GASTOS FINANCIEROS | AE123: =+VLOOKUP(AD123,Catálogo!E:F,2,0) -> #N/A | AF123: =+VLOOKUP(AD123,Catálogo!E:G,3,0) -> 0
A124: 702 | B124: 2 | C124: 0 | D124: COMISIONES BANCARIAS | E124: 0 | F124: 11420.95 | G124: 0 | H124: 11420.95 | J124: =+ROUND(H124/1000,0) -> 11 | K124: =+IFERROR(LEFT(AE124,3),0) -> Int | L124: =+IFERROR(ABS(K124),"ok") -> ok | M124: =+IF(L124="ok",J124,0) -> 11 | O124: =+M124+N124 -> 11 | R124: 702 | S124: 2 | T124: 0 | U124: COMISIONES BANCARIAS | V124: 0 | W124: 11420.95 | X124: 0 | Y124: =+O124 -> 11 | AD124: =+CONCATENATE(A124,B124,D124) -> 7022COMISIONES BANCARIAS | AE124: =+VLOOKUP(AD124,Catálogo!E:F,2,0) -> Intereses a cargo | AF124: =+VLOOKUP(AD124,Catálogo!E:G,3,0) -> 0
A125: 702 | B125: 3 | C125: 0 | D125: PERDIDA CAMBIARIA | E125: 0 | F125: 1353.1 | G125: 0 | H125: 1353.1 | J125: =+ROUND(H125/1000,0) -> 1 | K125: =+IFERROR(LEFT(AE125,3),0) -> Otr | L125: =+IFERROR(ABS(K125),"ok") -> ok | M125: =+IF(L125="ok",J125,0) -> 1 | O125: =+M125+N125 -> 1 | R125: 702 | S125: 3 | T125: 0 | U125: PERDIDA CAMBIARIA | V125: 0 | W125: 1353.1 | X125: 0 | Y125: =+O125 -> 1 | AD125: =+CONCATENATE(A125,B125,D125) -> 7023PERDIDA CAMBIARIA | AE125: Otros ingresos | AF125: =+VLOOKUP(AD125,Catálogo!E:G,3,0) -> 0
A126: 751 | B126: 0 | C126: 0 | D126: OTROS PRODUCTOS | E126: 0 | F126: 0.1 | G126: -4608209.8 | H126: -4608209.7 | J126: =+ROUND(H126/1000,0) -> -4608 | K126: =+IFERROR(LEFT(AE126,3),0) -> 0 | L126: =+IFERROR(ABS(K126),"ok") -> 0 | M126: =+IF(L126="ok",J126,0) -> 0 | O126: =+M126+N126 -> 0 | R126: 751 | S126: 0 | T126: 0 | U126: OTROS PRODUCTOS | V126: 0 | W126: 0.1 | X126: -4608209.8 | Y126: =+O126 -> 0 | AD126: =+CONCATENATE(A126,B126,D126) -> 7510OTROS PRODUCTOS | AE126: =+VLOOKUP(AD126,Catálogo!E:F,2,0) -> #N/A | AF126: =+VLOOKUP(AD126,Catálogo!E:G,3,0) -> 0
A127: 751 | B127: 2 | C127: 0 | D127: OTROS INGRESOS | E127: 0 | F127: 0.1 | G127: -4608209.8 | H127: -4608209.7 | J127: =+ROUND(H127/1000,0) -> -4608 | K127: =+IFERROR(LEFT(AE127,3),0) -> Otr | L127: =+IFERROR(ABS(K127),"ok") -> ok | M127: =+IF(L127="ok",J127,0) -> -4608 | O127: =+M127+N127 -> -4608 | R127: 751 | S127: 2 | T127: 0 | U127: OTROS INGRESOS | V127: 0 | W127: 0.1 | X127: -4608209.8 | Y127: =+O127 -> -4608 | AD127: =+CONCATENATE(A127,B127,D127) -> 7512OTROS INGRESOS | AE127: =+VLOOKUP(AD127,Catálogo!E:F,2,0) -> Otros ingresos | AF127: =+VLOOKUP(AD127,Catálogo!E:G,3,0) -> 0
A128: 752 | B128: 0 | C128: 0 | D128: OTROS GASTOS | E128: 0 | F128: 44 | G128: 0 | H128: 44 | J128: =+ROUND(H128/1000,0) -> 0 | K128: =+IFERROR(LEFT(AE128,3),0) -> 0 | L128: =+IFERROR(ABS(K128),"ok") -> 0 | M128: =+IF(L128="ok",J128,0) -> 0 | O128: =+M128+N128 -> 0 | R128: 752 | S128: 0 | T128: 0 | U128: OTROS GASTOS | V128: 0 | W128: 44 | X128: 0 | Y128: =+O128 -> 0 | AD128: =+CONCATENATE(A128,B128,D128) -> 7520OTROS GASTOS | AE128: =+VLOOKUP(AD128,Catálogo!E:F,2,0) -> 0 | AF128: =+VLOOKUP(AD128,Catálogo!E:G,3,0) -> 0
A129: 752 | B129: 2 | C129: 0 | D129: RECARGOS | E129: 0 | F129: 44 | G129: 0 | H129: 44 | J129: =+ROUND(H129/1000,0) -> 0 | K129: =+IFERROR(LEFT(AE129,3),0) -> Gas | L129: =+IFERROR(ABS(K129),"ok") -> ok | M129: =+IF(L129="ok",J129,0) -> 0 | O129: =+M129+N129 -> 0 | R129: 752 | S129: 2 | T129: 0 | U129: RECARGOS | V129: 0 | W129: 44 | X129: 0 | Y129: =+O129 -> 0 | AD129: =+CONCATENATE(A129,B129,D129) -> 7522RECARGOS | AE129: =+VLOOKUP(AD129,Catálogo!E:F,2,0) -> Gastos operativos | AF129: =+VLOOKUP(AD129,Catálogo!E:G,3,0) -> 0
J130: =+ROUND(H130/1000,0) -> 0 | K130: =+IFERROR(LEFT(AE130,3),0) -> 0 | L130: =+IFERROR(ABS(K130),"ok") -> 0 | M130: =+IF(L130="ok",J130,0) -> 0 | O130: =+M130+N130 -> 0 | AD130: =+CONCATENATE(A130,B130,D130) | AE130: =+VLOOKUP(AD130,Catálogo!E:F,2,0) -> #N/A | AF130: =+VLOOKUP(AD130,Catálogo!E:G,3,0) -> #N/A
J131: =+ROUND(H131/1000,0) -> 0 | K131: =+IFERROR(LEFT(AE131,3),0) -> 0 | L131: =+IFERROR(ABS(K131),"ok") -> 0 | M131: =+IF(L131="ok",J131,0) -> 0 | O131: =+M131+N131 -> 0 | AD131: =+CONCATENATE(A131,B131,D131) | AE131: =+VLOOKUP(AD131,Catálogo!E:F,2,0) -> #N/A | AF131: =+VLOOKUP(AD131,Catálogo!E:G,3,0) -> #N/A
J132: =+ROUND(H132/1000,0) -> 0 | K132: =+IFERROR(LEFT(AE132,3),0) -> 0 | L132: =+IFERROR(ABS(K132),"ok") -> 0 | M132: =+IF(L132="ok",J132,0) -> 0 | O132: =+M132+N132 -> 0 | AD132: =+CONCATENATE(A132,B132,D132) | AE132: =+VLOOKUP(AD132,Catálogo!E:F,2,0) -> #N/A | AF132: =+VLOOKUP(AD132,Catálogo!E:G,3,0) -> #N/A
J133: =+ROUND(H133/1000,0) -> 0 | K133: =+IFERROR(LEFT(AE133,3),0) -> 0 | L133: =+IFERROR(ABS(K133),"ok") -> 0 | M133: =+IF(L133="ok",J133,0) -> 0 | O133: =+M133+N133 -> 0 | AD133: =+CONCATENATE(A133,B133,D133) | AE133: =+VLOOKUP(AD133,Catálogo!E:F,2,0) -> #N/A | AF133: =+VLOOKUP(AD133,Catálogo!E:G,3,0) -> #N/A
J134: =+ROUND(H134/1000,0) -> 0 | K134: =+IFERROR(LEFT(AE134,3),0) -> 0 | L134: =+IFERROR(ABS(K134),"ok") -> 0 | M134: =+IF(L134="ok",J134,0) -> 0 | O134: =+M134+N134 -> 0 | AD134: =+CONCATENATE(A134,B134,D134) | AE134: =+VLOOKUP(AD134,Catálogo!E:F,2,0) -> #N/A | AF134: =+VLOOKUP(AD134,Catálogo!E:G,3,0) -> #N/A
J135: =+ROUND(H135/1000,0) -> 0 | K135: =+IFERROR(LEFT(AE135,3),0) -> 0 | L135: =+IFERROR(ABS(K135),"ok") -> 0 | M135: =+IF(L135="ok",J135,0) -> 0 | O135: =+M135+N135 -> 0 | AD135: =+CONCATENATE(A135,B135,D135) | AE135: =+VLOOKUP(AD135,Catálogo!E:F,2,0) -> #N/A | AF135: =+VLOOKUP(AD135,Catálogo!E:G,3,0) -> #N/A
J136: =+ROUND(H136/1000,0) -> 0 | K136: =+IFERROR(LEFT(AE136,3),0) -> 0 | L136: =+IFERROR(ABS(K136),"ok") -> 0 | M136: =+IF(L136="ok",J136,0) -> 0 | O136: =+M136+N136 -> 0 | AD136: =+CONCATENATE(A136,B136,D136) | AE136: =+VLOOKUP(AD136,Catálogo!E:F,2,0) -> #N/A | AF136: =+VLOOKUP(AD136,Catálogo!E:G,3,0) -> #N/A
J137: =+ROUND(H137/1000,0) -> 0 | K137: =+IFERROR(LEFT(AE137,3),0) -> 0 | L137: =+IFERROR(ABS(K137),"ok") -> 0 | M137: =+IF(L137="ok",J137,0) -> 0 | O137: =+M137+N137 -> 0 | AD137: =+CONCATENATE(A137,B137,D137) | AE137: =+VLOOKUP(AD137,Catálogo!E:F,2,0) -> #N/A | AF137: =+VLOOKUP(AD137,Catálogo!E:G,3,0) -> #N/A
J138: =+ROUND(H138/1000,0) -> 0 | K138: =+IFERROR(LEFT(AE138,3),0) -> 0 | L138: =+IFERROR(ABS(K138),"ok") -> 0 | M138: =+IF(L138="ok",J138,0) -> 0 | O138: =+M138+N138 -> 0 | AD138: =+CONCATENATE(A138,B138,D138) | AE138: =+VLOOKUP(AD138,Catálogo!E:F,2,0) -> #N/A | AF138: =+VLOOKUP(AD138,Catálogo!E:G,3,0) -> #N/A
J139: =+ROUND(H139/1000,0) -> 0 | K139: =+IFERROR(LEFT(AE139,3),0) -> 0 | L139: =+IFERROR(ABS(K139),"ok") -> 0 | M139: =+IF(L139="ok",J139,0) -> 0 | O139: =+M139+N139 -> 0 | AD139: =+CONCATENATE(A139,B139,D139) | AE139: =+VLOOKUP(AD139,Catálogo!E:F,2,0) -> #N/A | AF139: =+VLOOKUP(AD139,Catálogo!E:G,3,0) -> #N/A
J140: =+ROUND(H140/1000,0) -> 0 | K140: =+IFERROR(LEFT(AE140,3),0) -> 0 | L140: =+IFERROR(ABS(K140),"ok") -> 0 | M140: =+IF(L140="ok",J140,0) -> 0 | O140: =+M140+N140 -> 0 | AD140: =+CONCATENATE(A140,B140,D140) | AE140: =+VLOOKUP(AD140,Catálogo!E:F,2,0) -> #N/A | AF140: =+VLOOKUP(AD140,Catálogo!E:G,3,0) -> #N/A
J141: =+ROUND(H141/1000,0) -> 0 | K141: =+IFERROR(LEFT(AE141,3),0) -> 0 | L141: =+IFERROR(ABS(K141),"ok") -> 0 | M141: =+IF(L141="ok",J141,0) -> 0 | O141: =+M141+N141 -> 0 | AD141: =+CONCATENATE(A141,B141,D141) | AE141: =+VLOOKUP(AD141,Catálogo!E:F,2,0) -> #N/A | AF141: =+VLOOKUP(AD141,Catálogo!E:G,3,0) -> #N/A
... J251: =+ROUND(H251/1000,0) -> 0 | K251: =+IFERROR(LEFT(AE251,3),0) -> 0 | L251: =+IFERROR(ABS(K251),"ok") -> 0 | M251: =+IF(L251="ok",J251,0) -> 0 | O251: =+M251+N251 -> 0 | AD251: =+CONCATENATE(A251,B251,D251) | AE251: =+VLOOKUP(AD251,Catálogo!E:F,2,0) -> #N/A | AF251: =+VLOOKUP(AD251,Catálogo!E:G,3,0) -> #N/A
AD252: =+CONCATENATE(A252,B252,D252) | AE252: =+VLOOKUP(AD252,Catálogo!E:F,2,0) -> #N/A | AF252: =+VLOOKUP(AD252,Catálogo!E:G,3,0) -> #N/A
AD253: =+CONCATENATE(A253,B253,D253) | AE253: =+VLOOKUP(AD253,Catálogo!E:F,2,0) -> #N/A | AF253: =+VLOOKUP(AD253,Catálogo!E:G,3,0) -> #N/A
AD254: =+CONCATENATE(A254,B254,D254) | AE254: =+VLOOKUP(AD254,Catálogo!E:F,2,0) -> #N/A | AF254: =+VLOOKUP(AD254,Catálogo!E:G,3,0) -> #N/A
AD255: =+CONCATENATE(A255,B255,D255) | AE255: =+VLOOKUP(AD255,Catálogo!E:F,2,0) -> #N/A | AF255: =+VLOOKUP(AD255,Catálogo!E:G,3,0) -> #N/A
AD256: =+CONCATENATE(A256,B256,D256) | AE256: =+VLOOKUP(AD256,Catálogo!E:F,2,0) -> #N/A | AF256: =+VLOOKUP(AD256,Catálogo!E:G,3,0) -> #N/A
AD257: =+CONCATENATE(A257,B257,D257) | AE257: =+VLOOKUP(AD257,Catálogo!E:F,2,0) -> #N/A | AF257: =+VLOOKUP(AD257,Catálogo!E:G,3,0) -> #N/A
AD258: =+CONCATENATE(A258,B258,D258) | AE258: =+VLOOKUP(AD258,Catálogo!E:F,2,0) -> #N/A | AF258: =+VLOOKUP(AD258,Catálogo!E:G,3,0) -> #N/A
AD259: =+CONCATENATE(A259,B259,D259) | AE259: =+VLOOKUP(AD259,Catálogo!E:F,2,0) -> #N/A | AF259: =+VLOOKUP(AD259,Catálogo!E:G,3,0) -> #N/A
AD260: =+CONCATENATE(A260,B260,D260) | AE260: =+VLOOKUP(AD260,Catálogo!E:F,2,0) -> #N/A | AF260: =+VLOOKUP(AD260,Catálogo!E:G,3,0) -> #N/A
AD261: =+CONCATENATE(A261,B261,D261) | AE261: =+VLOOKUP(AD261,Catálogo!E:F,2,0) -> #N/A | AF261: =+VLOOKUP(AD261,Catálogo!E:G,3,0) -> #N/A
AD262: =+CONCATENATE(A262,B262,D262) | AE262: =+VLOOKUP(AD262,Catálogo!E:F,2,0) -> #N/A | AF262: =+VLOOKUP(AD262,Catálogo!E:G,3,0) -> #N/A
AD263: =+CONCATENATE(A263,B263,D263) | AE263: =+VLOOKUP(AD263,Catálogo!E:F,2,0) -> #N/A | AF263: =+VLOOKUP(AD263,Catálogo!E:G,3,0) -> #N/A
... AD308: =+CONCATENATE(A308,B308,D308) | AE308: =+VLOOKUP(AD308,Catálogo!E:F,2,0) -> #N/A | AF308: =+VLOOKUP(AD308,Catálogo!E:G,3,0) -> #N/A
AD309: =+CONCATENATE(A309,B309,D309) | AE309: =+VLOOKUP(AD309,Catálogo!E:F,2,0) -> #N/A
AD310: =+CONCATENATE(A310,B310,D310) | AE310: =+VLOOKUP(AD310,Catálogo!E:F,2,0) -> #N/A
AD311: =+CONCATENATE(A311,B311,D311) | AE311: =+VLOOKUP(AD311,Catálogo!E:F,2,0) -> #N/A
AD312: =+CONCATENATE(A312,B312,D312) | AE312: =+VLOOKUP(AD312,Catálogo!E:F,2,0) -> #N/A
AD313: =+CONCATENATE(A313,B313,D313) | AE313: =+VLOOKUP(AD313,Catálogo!E:F,2,0) -> #N/A
AD314: =+CONCATENATE(A314,B314,D314) | AE314: =+VLOOKUP(AD314,Catálogo!E:F,2,0) -> #N/A
AD315: =+CONCATENATE(A315,B315,D315) | AE315: =+VLOOKUP(AD315,Catálogo!E:F,2,0) -> #N/A
AD316: =+CONCATENATE(A316,B316,D316) | AE316: =+VLOOKUP(AD316,Catálogo!E:F,2,0) -> #N/A
AD317: =+CONCATENATE(A317,B317,D317) | AE317: =+VLOOKUP(AD317,Catálogo!E:F,2,0) -> #N/A
AD318: =+CONCATENATE(A318,B318,D318) | AE318: =+VLOOKUP(AD318,Catálogo!E:F,2,0) -> #N/A
AD319: =+CONCATENATE(A319,B319,D319) | AE319: =+VLOOKUP(AD319,Catálogo!E:F,2,0) -> #N/A
AD320: =+CONCATENATE(A320,B320,D320) | AE320: =+VLOOKUP(AD320,Catálogo!E:F,2,0) -> #N/A
... AD565: =+CONCATENATE(A565,B565,D565) | AE565: =+VLOOKUP(AD565,Catálogo!E:F,2,0) -> #N/A

Sheet Validación
D8: =SUM(D12:D35) -> 0 | E8: =SUM(E12:E35) -> 0 | F8: =SUM(F12:F31) -> 1 | G8: =SUM(G12:G31) -> 1 | H8: Check
A11: Balance | B11: Clasificación | C11: Plazo | D11: 2024M | E11: 2024 | F11: 2023M | G11: 2023
A12: Efectivo y equivalentes de efectivo | B12: Activo | C12: Corto plazo | D12: =+ROUND(E12,0) -> 42719 | E12: =+SUMIF(BalanzaActual!$AH:$AH,Validación!$A12,BalanzaActual!$Z:$Z) -> 42719 | F12: =+ROUND(G12,0) -> 46651 | G12: =+SUMIF(BalanzaAnterior!$AE:$AE,Validación!$A12,BalanzaAnterior!$Y:$Y) -> 46651
A13: Deudores diversos y otras cuentas por cobrar | B13: Activo | C13: Corto plazo | D13: =+ROUND(E13,0) -> 25042 | E13: =+SUMIF(BalanzaActual!$AH:$AH,Validación!$A13,BalanzaActual!$Z:$Z) -> 25042 | F13: =+ROUND(G13,0) -> 11989 | G13: =+SUMIF(BalanzaAnterior!$AE:$AE,Validación!$A13,BalanzaAnterior!$Y:$Y) -> 11989
A14: Inventarios inmobiliarios y costos pagados por anticipado | B14: Activo | C14: Largo Plazo | D14: =+ROUND(E14,0) -> 1085783 | E14: =+SUMIF(BalanzaActual!$AH:$AH,Validación!$A14,BalanzaActual!$Z:$Z) -> 1085783 | F14: =+ROUND(G14,0) -> 773964 | G14: =+SUMIF(BalanzaAnterior!$AE:$AE,Validación!$A14,BalanzaAnterior!$Y:$Y) -> 773964
A15: Mobiliario y equipo, neto | B15: Activo | C15: Largo Plazo | D15: =+ROUND(E15,0) -> 364 | E15: =+SUMIF(BalanzaActual!$AH:$AH,Validación!$A15,BalanzaActual!$Z:$Z) -> 364 | F15: =+ROUND(G15,0) -> 43 | G15: =+SUMIF(BalanzaAnterior!$AE:$AE,Validación!$A15,BalanzaAnterior!$Y:$Y) -> 43
A16: Impuestos por recuperar | B16: Activo | C16: Largo Plazo | D16: =+ROUND(E16,0) -> 291 | E16: =+SUMIF(BalanzaActual!$AH:$AH,Validación!$A16,BalanzaActual!$Z:$Z) -> 291 | F16: =+ROUND(G16,0) -> 16 | G16: =+SUMIF(BalanzaAnterior!$AE:$AE,Validación!$A16,BalanzaAnterior!$Y:$Y) -> 16
A17: Proveedores y acreedores diversos | B17: Pasivo | C17: Corto plazo | D17: =+ROUND(E17,0) -> -37961 | E17: =+SUMIF(BalanzaActual!$AH:$AH,Validación!$A17,BalanzaActual!$Z:$Z) -> -37961 | F17: =+ROUND(G17,0) -> -13081 | G17: =+SUMIF(BalanzaAnterior!$AE:$AE,Validación!$A17,BalanzaAnterior!$Y:$Y) -> -13081
A18: Acreedores diversos | B18: Pasivo | C18: Corto plazo | D18: =+ROUND(E18,0) -> 0 | E18: =+SUMIF(BalanzaActual!$AH:$AH,Validación!$A18,BalanzaActual!$Z:$Z) -> 0 | F18: =+ROUND(G18,0) -> 0 | G18: =+SUMIF(BalanzaAnterior!$AE:$AE,Validación!$A18,BalanzaAnterior!$Y:$Y) -> 0
A19: Impuestos por pagar | B19: Pasivo | C19: Corto plazo | D19: =+ROUND(E19,0) -> -460 | E19: =+SUMIF(BalanzaActual!$AH:$AH,Validación!$A19,BalanzaActual!$Z:$Z) -> -460 | F19: =+ROUND(G19,0) -> -390 | G19: =+SUMIF(BalanzaAnterior!$AE:$AE,Validación!$A19,BalanzaAnterior!$Y:$Y) -> -390
A20: Depósitos en garantía recibidos | B20: Pasivo | C20: Largo Plazo | D20: =+ROUND(E20,0) -> -407950 | E20: =+SUMIF(BalanzaActual!$AH:$AH,Validación!$A20,BalanzaActual!$Z:$Z) -> -407950 | F20: =+ROUND(G20,0) -> -71045 | G20: =+SUMIF(BalanzaAnterior!$AE:$AE,Validación!$A20,BalanzaAnterior!$Y:$Y) -> -71045
A21: Préstamos a largo plazo | B21: Pasivo | C21: Largo Plazo | D21: =+ROUND(E21,0) -> -330000 | E21: =+SUMIF(BalanzaActual!$AH:$AH,Validación!$A21,BalanzaActual!$Z:$Z) -> -330000 | F21: =+ROUND(G21,0) -> -271000 | G21: =+SUMIF(BalanzaAnterior!$AE:$AE,Validación!$A21,BalanzaAnterior!$Y:$Y) -> -271000
A22: Otras aportaciones del fideicomitente | B22: Pasivo | C22: Largo Plazo | D22: =+ROUND(E22,0) -> -125867 | E22: =+SUMIF(BalanzaActual!$AH:$AH,Validación!$A22,BalanzaActual!$Z:$Z) -> -125867 | F22: =+ROUND(G22,0) -> -196719 | G22: =+SUMIF(BalanzaAnterior!$AE:$AE,Validación!$A22,BalanzaAnterior!$Y:$Y) -> -196719
A23: Aportaciones | B23: Capital | D23: =+ROUND(E23,0) -> -272972 | E23: =+SUMIF(BalanzaActual!$AH:$AH,Validación!$A23,BalanzaActual!$Z:$Z) -> -272972 | F23: =+ROUND(G23,0) -> -272972 | G23: =+SUMIF(BalanzaAnterior!$AE:$AE,Validación!$A23,BalanzaAnterior!$Y:$Y) -> -272972
A24: Resultado del ejercicio | B24: Capital | D24: =+ROUND(E24,0) -> 0 | E24: =+SUMIF(BalanzaActual!$AH:$AH,Validación!$A24,BalanzaActual!$Z:$Z) -> 0 | F24: =+ROUND(G24,0) -> 0 | G24: =+SUMIF(BalanzaAnterior!$AE:$AE,Validación!$A24,BalanzaAnterior!$Y:$Y) -> 0
A25: Resultados acumulados | B25: Capital | D25: =+ROUND(E25,0) -> -7456 | E25: =+SUMIF(BalanzaActual!$AH:$AH,Validación!$A25,BalanzaActual!$Z:$Z) -> -7456 | F25: =+ROUND(G25,0) -> 394 | G25: =+SUMIF(BalanzaAnterior!$AE:$AE,Validación!$A25,BalanzaAnterior!$Y:$Y) -> 394
A26: Ingresos | B26: Resultados | D26: =+ROUND(E26,0) -> 0 | E26: =+SUMIF(BalanzaActual!$AH:$AH,Validación!$A26,BalanzaActual!$Z:$Z) -> 0 | F26: =+ROUND(G26,0) -> 0 | G26: =+SUMIF(BalanzaAnterior!$AE:$AE,Validación!$A26,BalanzaAnterior!$Y:$Y) -> 0
A27: Gastos operativos | B27: Resultados | D27: =+ROUND(E27,0) -> 36492 | E27: =+SUMIF(BalanzaActual!$AH:$AH,Validación!$A27,BalanzaActual!$Z:$Z) -> 36492 | F27: =+ROUND(G27,0) -> 59 | G27: =+SUMIF(BalanzaAnterior!$AE:$AE,Validación!$A27,BalanzaAnterior!$Y:$Y) -> 59
A28: Intereses a cargo | B28: Resultados | D28: =+ROUND(E28,0) -> 21 | E28: =+SUMIF(BalanzaActual!$AH:$AH,Validación!$A28,BalanzaActual!$Z:$Z) -> 21 | F28: =+ROUND(G28,0) -> 11 | G28: =+SUMIF(BalanzaAnterior!$AE:$AE,Validación!$A28,BalanzaAnterior!$Y:$Y) -> 11
A29: Intereses a favor | B29: Resultados | D29: =+ROUND(E29,0) -> -8050 | E29: =+SUMIF(BalanzaActual!$AH:$AH,Validación!$A29,BalanzaActual!$Z:$Z) -> -8050 | F29: =+ROUND(G29,0) -> -2456 | G29: =+SUMIF(BalanzaAnterior!$AE:$AE,Validación!$A29,BalanzaAnterior!$Y:$Y) -> -2456
A30: Otros ingresos | B30: Resultados | D30: =+ROUND(E30,0) -> 0 | E30: =+SUMIF(BalanzaActual!$AH:$AH,Validación!$A30,BalanzaActual!$Z:$Z) -> 0 | F30: =+ROUND(G30,0) -> -5463 | G30: =+SUMIF(BalanzaAnterior!$AE:$AE,Validación!$A30,BalanzaAnterior!$Y:$Y) -> -5463
A31: Fluctuación cambiaria | B31: Resultados | D31: =+ROUND(E31,0) -> 4 | E31: =+SUMIF(BalanzaActual!$AH:$AH,Validación!$A31,BalanzaActual!$Z:$Z) -> 4 | F31: =+ROUND(G31,0) -> 0 | G31: =+SUMIF(BalanzaAnterior!$AE:$AE,Validación!$A31,BalanzaAnterior!$Y:$Y) -> 0
A32: Traspaso a resultados acumulados

Sheet Portada
B3: =+Datos!C4 -> Fideicomiso Irrevocable 4341
B4: =+Datos!C5 -> Fideicomiso FORTMCK 19-12 Lomas Verdes
B6: =+"Estados financieros "&LOWER(Datos!C7)&", e Informe de los auditores independientes del "&Datos!C10 -> Estados financieros por los ejercicios terminados al 31 de diciembre de 2024 y 2023, e Informe de los auditores independientes del 30 de abril de 2025

Sheet Contenido
B6: =+Datos!C4 -> Fideicomiso Irrevocable 4341
B7: =+Datos!C5 -> Fideicomiso FORTMCK 19-12 Lomas Verdes
B9: =+"Informe de los auditores independientes y estados financieros "&LOWER(Datos!C7) -> Informe de los auditores independientes y estados financieros por los ejercicios terminados al 31 de diciembre de 2024 y 2023
B12: Contenido | C12: Página
B16: Informe de los auditores independientes | C16: 1
B17: Estados de posición financiera | C17: 3
B18: Estados de resultados | C18: 4
B19: Estados de cambios en el patrimonio | C19: 5
B20: Estados de flujos de efectivo | C20: 6
B21: Notas a los estados financieros | C21: 7

Sheet Dictamen 1
B5: Al Comité Técnico y Administrador de
B6: =+Datos!C4 -> Fideicomiso Irrevocable 4341
B7: =+Datos!C5 -> Fideicomiso FORTMCK 19-12 Lomas Verdes
B10: =+UPPER("Informe de los Auditores Independientes") -> INFORME DE LOS AUDITORES INDEPENDIENTES
B14: Opinión
B16: =+CONCATENATE(G16,Datos!C4,", ",Datos!C5,,'Dictamen 1'!G18,LOWER(Datos!C14),'Dictamen 1'!G20) -> Hemos auditado los estados financieros adjuntos de Fideicomiso Irrevocable 4341, Fideicomiso FORTMCK 19-12 Lomas Verdes, (el “Fideicomiso”), que comprenden los estados de posición financiera al 31 de diciembre de 2024 y 2023, los estados de resultados, de cambios en el patrimonio y de flujos de efectivo, por los ejercicios terminados en dichas fechas, así como las notas explicativas de los estados financieros, las cuales incluyen un resumen de las principales políticas contables. | G16: Hemos auditado los estados financieros adjuntos de
B18: =+CONCATENATE("En nuestra opinión, los estados financieros adjuntos presentan razonablemente, en todos los aspectos importantes la situación financiera del Fideicomiso ",LOWER(Datos!C14),", así como su desempeño financiero y sus flujos de efectivo correspondientes a los ejercicios terminados en dicha fecha, de conformidad con las Normas de Información Financiera Mexicanas (NIF).") -> En nuestra opinión, los estados financieros adjuntos presentan razonablemente, en todos los aspectos importantes la situación financiera del Fideicomiso al 31 de diciembre de 2024 y 2023, así como su desempeño financiero y sus flujos de efectivo correspondientes a los ejercicios terminados en dicha fecha, de conformidad con las Normas de Información Financiera Mexicanas (NIF). | G18: , (el “Fideicomiso”), que comprenden los estados de posición financiera
B20: Fundamento de la opinión | G20: , los estados de resultados, de cambios en el patrimonio y de flujos de efectivo, por los ejercicios terminados en dichas fechas, así como las notas explicativas de los estados financieros, las cuales incluyen un resumen de las principales políticas contables.
B22: Realizamos nuestra auditoría de conformidad con las Normas Internacionales de Auditoría (NIAs). Nuestras responsabilidades de acuerdo con dichas normas se describen más adelante en la sección "Responsabilidades del auditor en relación con la auditoría de los estados financieros" de este informe. Somos independientes del Fideicomiso de conformidad con el Código de Ética Profesional del Instituto Mexicano de Contadores Públicos, A.C. y cumplimos con las demás responsabilidades de ética de conformidad con dicho código. Consideramos que la evidencia de auditoría que hemos obtenido proporciona una base suficiente y adecuada para nuestra opinión. | G22: Los estados financieros del
G23: fueron auditados por otros auditores quienes expresaron una opinión limpia sobre dichos.
B24: Responsabilidades de la administración y de los responsables del gobierno del Fideicomiso en relación con los estados financieros
B26: La Administración es responsable de la preparación y presentación fiel de los estados financieros adjuntos de conformidad con las NIF, y del control interno que la administración considere necesario para permitir la preparación de estados financieros libres de incorrección material, debida a fraude o error.
B28: En la preparación de los estados financieros, la administración es responsable de la valoración de la capacidad del Fideicomiso de continuar como empresa en funcionamiento, revelando, según corresponda, las cuestiones relacionadas con la Empresa en funcionamiento y utilizando el principio contable de empresa en funcionamiento excepto si la administración tiene intención de liquidar el Fideicomiso o de cesar sus operaciones, o bien no existe otra alternativa realista.
B30: Los responsables del gobierno del Fideicomiso son responsables de la supervisión del proceso de información financiera del Fideicomiso.

Sheet Dictamen 2
B4: Responsabilidades del auditor en relación con la auditoría de los estados financieros
B6: Nuestros objetivos son obtener una seguridad razonable de que los estados financieros en su conjunto están libres de incorrección material, debida a fraude o error, y emitir un informe de auditoría que contiene nuestra opinión. Seguridad razonable es un alto grado de seguridad, pero no garantiza que una auditoría realizada de conformidad con las NIA siempre detecte una incorrección material cuando existe. Las incorrecciones pueden deberse a fraude o error y se consideran materiales si, individualmente o de forma agregada, puede preverse razonablemente que influyan en las decisiones económicas que los usuarios toman basándose en los estados financieros.
B8: Como parte de una auditoría de conformidad con las NIA, aplicamos nuestro juicio profesional y mantenemos una actitud de escepticismo profesional durante toda la auditoría. También:
B10: · Identificamos y valoramos los riesgos de incorrección material en los estados financieros, debida a fraude o error, diseñamos y aplicamos procedimientos de auditoría para responder a dichos riesgos y obtenemos evidencia de auditoría suficiente y adecuada para proporcionar una base para nuestra opinión. El riesgo de no detectar una incorrección material debida a fraude es más elevado que en el caso de una incorrección material debida a error, ya que el fraude puede implicar colusión, falsificación, omisiones deliberadas, manifestaciones intencionadamente erróneas o la elusión del control interno.
B12: · Obtenemos conocimiento del control interno relevante para la auditoría con el fin de diseñar procedimientos de auditoría que sean adecuados en función de las circunstancias y no con la finalidad de expresar una opinión sobre la eficacia del control interno de la entidad.
B14: · Evaluamos la adecuación de las políticas contables aplicadas y la razonabilidad de las estimaciones contables y la correspondiente información revelada por la administración.
B16: · Concluimos sobre lo adecuado de la utilización, por la administración, del principio contable de empresa en funcionamiento y basándonos en la evidencia de auditoría obtenida, concluimos sobre si existe o no una incertidumbre material relacionada con hechos o con condiciones que pueden generar dudas significativas sobre la capacidad del Fideicomiso para continuar como empresa en funcionamiento. Si concluimos que existe una incertidumbre material, se requiere que llamemos la atención en nuestro informe de auditoría sobre la correspondiente información revelada en los estados financieros o, si dichas revelaciones no son adecuadas, que expresemos una opinión modificada. Nuestras conclusiones se basan en la evidencia de auditoría obtenida hasta la fecha de nuestro informe de auditoría. Sin embargo, hechos o condiciones futuros pueden ser causa de que la Sociedad deje de ser uno empresa en funcionamiento.
B18: · Evaluamos la presentación global, la estructura y el contenido de los estados financieros, incluida la información revelada, y si los estados financieros representan las transacciones y hechos subyacentes de un modo que logran la presentación fiel.
B20: · Entre otras cuestiones, comunicamos a los responsables del gobierno de la entidad en relación con el alcance y el momento de realización de la auditoría planificados y los hallazgos significativos de la auditoría, así como cualquier deficiencia significativa del control interno que identificamos en el transcurso de la auditoría.
B22: L. C. C. Belén Arias Martínez
B23: Cédula Profesional 4514685
B24: No. REG.AGAFF.18344
B26: =+Datos!C10 -> 30 de abril de 2025

Sheet BG
B5: =+Datos!C4 -> Fideicomiso Irrevocable 4341
B6: =+Datos!C5 -> Fideicomiso FORTMCK 19-12 Lomas Verdes
B8: Estados de posición financiera
B9: =+Datos!C6 -> Al 31 de diciembre de 2024 y 2023
B10: (En miles de pesos)
R11: 1. (CI )Áreas de Riesgo y Rubros Susceptibles a Error | S11: 2. Análisis de Variaciones y Materialidad | V11: 3. Revisión del Dictamen 2023 | X11: Conclusiòn General
B12: Activos | C12: Nota | E12: =+Datos!C8 -> 2024 | G12: =+Datos!C9 -> 2023 | R12: Analisis CI | S12: Variación | T12: Materialidad | U12: Conclusión | V12: 2023 NOTAS | W12: Complicaciones y Ajustes Pendientes
B13: Activo circulante: | T13: =+E25*7% -> 80793.93
B14: Efectivo y equivalentes de efectivo | C14: 3a y 4 | D14: $ | E14: =+VLOOKUP($B14,Validación!$A$12:$D$39,4,0) -> 42719 | F14: $ | G14: =+VLOOKUP($B14,Validación!$A$12:$G$39,6,0) -> 46651 | R14: PC | S14: =+E14-G14 -> -3932 | T14: =IF(E14>$T$13,"Supera","No supera") -> No supera | V14: SI | X14: Si Revisar prueba de doble proposito
B15: Deudores diversos y otras cuentas por cobrar | C15: 3b | E15: =+VLOOKUP($B15,Validación!$A$12:$D$39,4,0)-'N13 Partes relacionadas'!G17 -> 24099 | G15: =+VLOOKUP($B15,Validación!$A$12:$G$39,6,0)-'N13 Partes relacionadas'!I17 -> 11046
B16: Cuentas por cobrar a partes relacionadas | C16: 13 | E16: =+'N13 Partes relacionadas'!G17 -> 943 | G16: =+'N13 Partes relacionadas'!I17 -> 943 | R16: PC | S16: =+E16-G16 -> 0 | T16: =IF(E16>$T$13,"Supera","No supera") -> No supera | X16: Si Revisar prueba de doble proposito
B17: Total activo circulante | E17: =SUM(E14:E16) -> 67761 | G17: =SUM(G14:G16) -> 58640
B19: Activo no circulante: | X19: Si Revisar prueba de doble proposito
B20: Inventarios inmobiliarios y costos pagados por anticipado | C20: 3c y 5 | E20: =+VLOOKUP(B20,Validación!$A$12:$D$39,4,0) -> 1085783 | G20: =+VLOOKUP($B20,Validación!$A$12:$G$39,6,0) -> 773964 | R20: PC | S20: =+E20-G20 -> 311819 | T20: =IF(E20>$T$13,"Supera","No supera") -> Supera | U20: PS | V20: SI | W20: Inventarios inmobiliarios pagados por anticipado: Se revisó la existencia y propiedad mediante escrituras y registros legales. También se verificaron los avances de obra, contrastando certificados y documentos de soporte que mantenga una conciliación actualizada. | X20: Si Revisar prueba de doble proposito
B21: Mobiliario y equipo, neto | C21: 3d | E21: =+VLOOKUP(B21,Validación!$A$12:$D$39,4,0) -> 364 | G21: =+VLOOKUP($B21,Validación!$A$12:$G$39,6,0) -> 43 | R21: PC | S21: =+E21-G21 -> 321 | T21: =IF(E21>$T$13,"Supera","No supera") -> No supera | X21: Si Revisar prueba de doble proposito
B22: Impuestos por recuperar | E22: =+VLOOKUP(B22,Validación!$A$12:$D$39,4,0) -> 291 | G22: =+VLOOKUP($B22,Validación!$A$12:$G$39,6,0) -> 16 | R22: PC | S22: =+E22-G22 -> 275 | T22: =IF(E22>$T$13,"Supera","No supera") -> No supera | V22: SI | Y22: IVA generado por el aumento en las adquisiciones y aumentos de Construcción
B23: Total activo no circulante | E23: =SUM(E20:E22) -> 1086438 | G23: =SUM(G20:G22) -> 774023
B25: Total activo | D25: $ | E25: =+E17+E23 -> 1154199 | F25: $ | G25: =+G17+G23 -> 832663
B27: Pasivos
B28: Pasivo circulante:
B29: Proveedores y acreedores diversos | C29: 3e y6 | D29: $ | E29: =-VLOOKUP(B29,Validación!$A$12:$D$39,4,0)-'N13 Partes relacionadas'!G26 -> 35778 | F29: $ | G29: =-VLOOKUP(B29,Validación!$A$12:$G$39,6,0)-'N13 Partes relacionadas'!I26 -> 7357 | R29: PC | S29: =+E29-G29 -> 28421 | T29: =IF(E29>$T$13,"Supera","No supera") -> No supera | X29: Si Revisar prueba de doble proposito | Y29: Debemos realizar selección de pasivo para revisar, la mayoria de los proveedores se refieren a Gastos relacionados con la Contrucción.
B30: Cuentas por pagar a partes relacionadas | C30: 13 | E30: =+'N13 Partes relacionadas'!G26 -> 2183 | G30: =+'N13 Partes relacionadas'!I26 -> 5724
B31: Impuestos por pagar | E31: =-VLOOKUP(B31,Validación!$A$12:$D$39,4,0) -> 460 | G31: =-VLOOKUP(B31,Validación!$A$12:$G$39,6,0) -> 390 | R31: PC | S31: =+E31-G31 -> 70 | T31: =IF(E31>$T$13,"Supera","No supera") -> No supera | X31: Si Revisar prueba de doble proposito
B32: Total pasivo circulante | E32: =SUM(E29:E31) -> 38421 | G32: =SUM(G29:G31) -> 13471
B34: Pasivo no circulante:
B35: Depósitos en garantía recibidos | C35: 3f y 7 | E35: =-VLOOKUP(B35,Validación!$A$12:$D$39,4,0) -> 407950 | G35: =-VLOOKUP(B35,Validación!$A$12:$G$39,6,0) -> 71045 | S35: =+E35-G35 -> 336905 | T35: =IF(E35>$T$13,"Supera","No supera") -> Supera | U35: PS | W35: Depositos en garantia: se reviso que esten adecuadamente respaldados por contratos y correctamente registrados como pasivos conforme a los acuerdos establecidos y las políticas de la empresa. | X35: Si Revisar prueba de doble proposito
B36: Préstamos a largo plazo | C36: 3h y 8 | E36: =-VLOOKUP(B36,Validación!$A$12:$D$39,4,0) -> 330000 | G36: =-VLOOKUP(B36,Validación!$A$12:$G$39,6,0) -> 271000 | R36: PC | S36: =+E36-G36 -> 59000 | T36: =IF(E36>$T$13,"Supera","No supera") -> Supera | U36: PS | V36: SI | W36: Préstamos bancarios Se revisaron los saldos y movimientos verificando el cumplimiento de los términos del contrato, la correcta amortización, y la adecuada clasificación entre corto y largo plazo. | X36: Si Revisar prueba de doble proposito
B37: Otras aportaciones del Fideicomitente | C37: 9 y13 | E37: =-VLOOKUP(B37,Validación!$A$12:$D$39,4,0) -> 125867 | G37: =-VLOOKUP(B37,Validación!$A$12:$G$39,6,0) -> 196719 | R37: PC | S37: =+E37-G37 -> -70852 | T37: =IF(E37>$T$13,"Supera","No supera") -> Supera | U37: PS | V37: SI | X37: Si Revisar prueba de doble proposito
B38: Total pasivo No circulante | E38: =SUM(E35:E37) -> 863817 | G38: =SUM(G35:G37) -> 538764
B40: Total pasivo | D40: $ | E40: =+E38+E32 -> 902238 | F40: $ | G40: =+G38+G32 -> 552235
B42: Patrimonio del Fideicomiso
B43: Aportaciones | C43: 3i y 11 | D43: $ | E43: =-VLOOKUP(B43,Validación!$A$12:$D$39,4,0) -> 272972 | F43: $ | G43: =-VLOOKUP(B43,Validación!$A$12:$G$39,6,0) -> 272972 | R43: PC | S43: =+E43-G43 -> 0 | T43: =IF(E43>$T$13,"Supera","No supera") -> Supera | V43: SI | W43: Patrimonio: Se revisaron los movimientos en el patrimonio, confirmando que tanto los movimientos como cualquier cambio en el patrimonio fueron debidamente documentados y registrados conforme a los contratos y políticas establecidos. | X43: Si Revisar prueba de doble proposito
B44: Resultado del ejercicio | E44: =+ER!E25 -> -28467 | G44: =+ER!G25 -> 7849 | R44: PC | S44: =+E44-G44 -> -36316 | T44: =IF(E44>$T$13,"Supera","No supera") -> No supera
B45: Resultados acumulados | E45: =-VLOOKUP(B45,Validación!$A$12:$D$39,4,0) -> 7456 | G45: =-VLOOKUP(B45,Validación!$A$12:$G$39,6,0)+1 -> -393 | R45: PC | S45: =+E45-G45 -> 7849 | T45: =IF(E45>$T$13,"Supera","No supera") -> No supera
B46: Total del Patrimonio | E46: =SUM(E43:E45) -> 251961 | G46: =SUM(G43:G45) -> 280428
B48: Total de pasivo y Patrimonio | D48: $ | E48: =+E46+E40 -> 1154199 | F48: $ | G48: =+G46+G40 -> 832663
B51: Las notas adjuntas son parte de los estados financieros.
E52: =+E48-E25 -> 0 | G52: =+G48-G25 -> 0 | R52: <<Check

Sheet ER
B5: =+Datos!C4 -> Fideicomiso Irrevocable 4341
B6: =+Datos!C5 -> Fideicomiso FORTMCK 19-12 Lomas Verdes
B8: Estados de resultados
B9: =+Datos!C7 -> Por los ejercicios terminados al 31 de diciembre de 2024 y 2023
B10: (En miles de pesos)
R11: 1. (CI )Áreas de Riesgo y Rubros Susceptibles a Error | S11: 2. Análisis de Variaciones y Materialidad
C12: Nota | E12: =+Datos!C8 -> 2024 | G12: =+Datos!C9 -> 2023 | R12: Analisis CI | S12: Variación | T12: Materialidad | U12: Conclusión
T13: =+BG!E25*7% -> 80793.93
B14: Otros ingresos | D14: $ | E14: =-VLOOKUP(B14,Validación!$A$12:$D$39,4,0) -> 0 | F14: $ | G14: =-VLOOKUP(B14,Validación!$A$12:$G$39,6,0) -> 5463 | S14: =+E14-G14 -> -5463 | T14: =IF(E14>$T$13,"Supera","No supera") -> No supera
B16: Gastos operativos | C16: j | E16: =VLOOKUP(B16,Validación!$A$12:$D$39,4,0) -> 36492 | G16: =VLOOKUP(B16,Validación!$A$12:$G$39,6,0) -> 59 | S16: =+E16-G16 -> 36433 | T16: =IF(E16>$T$13,"Supera","No supera") -> No supera
B17: Resultado de operación | E17: =+E14-E16 -> -36492 | G17: =+G14-G16 -> 5404
B19: Resultado Integral de Financiamiento
B20: Intereses a cargo | E20: =-VLOOKUP(B20,Validación!$A$12:$D$39,4,0) -> -21 | G20: =-VLOOKUP(B20,Validación!$A$12:$G$39,6,0) -> -11 | S20: =+E20-G20 -> -10 | T20: =IF(E20>$T$13,"Supera","No supera") -> No supera
B21: Intereses a favor | E21: =-VLOOKUP(B21,Validación!$A$12:$D$39,4,0) -> 8050 | G21: =-VLOOKUP(B21,Validación!$A$12:$G$39,6,0) -> 2456 | S21: =+E21-G21 -> 5594 | T21: =IF(E21>$T$13,"Supera","No supera") -> No supera
B22: Fluctuación cambiaria | E22: =-VLOOKUP(B22,Validación!$A$12:$D$39,4,0) -> -4 | G22: =-VLOOKUP(B22,Validación!$A$12:$G$39,6,0) -> 0 | S22: =+E22-G22 -> -4 | T22: =IF(E22>$T$13,"Supera","No supera") -> No supera
E23: =SUM(E20:E22) -> 8025 | G23: =SUM(G20:G22) -> 2445
B25: Resultado del ejercicio | D25: $ | E25: =+E17+E23 -> -28467 | F25: $ | G25: =+G17+G23 -> 7849
B30: Las notas adjuntas son parte de los estados financieros.

Sheet ECC
B7: =ER!B5 -> Fideicomiso Irrevocable 4341
B8: =ER!B6 -> Fideicomiso FORTMCK 19-12 Lomas Verdes
B10: Estado de variaciones en el patrimonio
B11: =ER!B9 -> Por los ejercicios terminados al 31 de diciembre de 2024 y 2023
B12: =ER!B10 -> (En miles de pesos)
D15: Patrimonio | F15: Resultados acumulados | H15: Resultado del ejercicio | J15: Total de
J16: patrimonio
B18: =+CONCATENATE("Saldo al 31 de diciembre ",Datos!C9-1) -> Saldo al 31 de diciembre 2022 | C18: $ | D18: =+D26-D21 -> 272972 | E18: $ | F18: -101 | G18: $ | H18: =-H21 -> -292 | I18: $ | J18: =SUM(D18:H18) -> 272579
B20: Movimientos inherentes a las decisiones de los accionistas-
B21: Traspaso a resultados acumulados | D21: 0 | F21: =-H21 -> -292 | H21: =-Datos!C11 -> 292 | J21: =SUM(D21:H21) -> 0
B23: Movimientos inherentes al reconocimiento del resultado del ejercicio-
B24: Resultado del ejercicio | D24: 0 | F24: 0 | H24: =+BG!G44 -> 7849 | J24: =+H24 -> 7849
B26: =+CONCATENATE("Saldo al 31 de diciembre ",Datos!C9) -> Saldo al 31 de diciembre 2023 | C26: $ | D26: =+BG!G43 -> 272972 | E26: $ | F26: =+F21+F18 -> -393 | G26: $ | H26: =+H24+H21+H18 -> 7849 | I26: $ | J26: =SUM(D26:H26) -> 280428
B28: Movimientos inherentes a las decisiones de los accionistas-
B29: Traspaso a resultados acumulados | D29: 0 | F29: =-H29 -> 7849 | H29: =-H26 -> -7849 | J29: =SUM(D29:H29) -> 0
B31: Movimientos inherentes al reconocimiento del resultado del ejercicio-
B32: Resultado del ejercicio | D32: 0 | F32: 0 | H32: =+BG!E44 -> -28467 | J32: =+H32 -> -28467
B34: =+CONCATENATE("Saldo al 31 de diciembre ",Datos!C8) -> Saldo al 31 de diciembre 2024 | C34: $ | D34: =+BG!E43 -> 272972 | E34: $ | F34: =+F32+F26+F29 -> 7456 | G34: $ | H34: =+H32+H26+H29 -> -28467 | I34: $ | J34: =+J32+J26 -> 251961
B37: Las notas adjuntas son parte de los estados financieros.
D38: =+D34-BG!E43 -> 0 | F38: =+F34-BG!E45 -> 0 | H38: =+H34-BG!E44 -> 0 | J38: =+J34-BG!E46 -> 0 | K38: <<Check 2024
D39: =+D26-BG!G43 -> 0 | F39: =+F26-BG!G45 -> 0 | H39: =+H26-BG!G44 -> 0 | J39: =+J26-BG!G46 -> 0 | K39: <<Check 2023

Sheet CF
B7: =+Datos!C4 -> Fideicomiso Irrevocable 4341
B8: =+Datos!C5 -> Fideicomiso FORTMCK 19-12 Lomas Verdes
B10: Estados de flujos de efectivo
B11: =+Datos!C7 -> Por los ejercicios terminados al 31 de diciembre de 2024 y 2023
B12: (En miles de pesos)
D14: =+Datos!C8 -> 2024 | E14: =+Datos!D8 -> 0 | F14: =+Datos!C9 -> 2023
B16: Actividades de operación:
B17: Resultado del ejercicio | C17: $ | D17: =+BG!E44 -> -28467 | E17: $ | F17: =+BG!G44 -> 7849
B19: Partidas relacionadas con actividades de financiamiento:
B20: Intereses a favor | D20: =-ER!E20 -> 21 | F20: =-ER!G20 -> 11
B21: Intereses a cargo | D21: =-ER!E21 -> -8050 | F21: =-ER!G21 -> -2456
D22: =+D17+D21+D20 -> -36496 | F22: =+F17+F21+F20 -> 5404
B24: Cambios en el capital de trabajo:
B25: (Incremento) disminución en:
B26: =+BG!B15 -> Deudores diversos y otras cuentas por cobrar | D26: =-BG!E15+BG!G15 -> -13053 | F26: 7291
B27: =+BG!B16 -> Cuentas por cobrar a partes relacionadas | D27: =-BG!E16+BG!G16 -> 0
B28: Impuestos por recuperar | D28: =-BG!E22+BG!G22 -> -275 | F28: -19466
B29: Incremento (disminución) en:
B30: =+BG!B29 -> Proveedores y acreedores diversos | D30: =+BG!E29-BG!G29 -> 28421 | F30: -11265
B31: =+BG!B30 -> Cuentas por pagar a partes relacionadas | D31: =+BG!E30-BG!G30 -> -3541 | F31: 3224
B32: Impuestos por pagar | D32: =+BG!E31-BG!G31 -> 70 | F32: 347
B33: Depósitos en garantía recibidos | D33: =+BG!E35-BG!G35 -> 336905 | F33: 71045
B34: Flujos netos de efectivo utilizados en actividades de operación | D34: =SUM(D22:D33) -> 312031 | F34: =SUM(F22:F33) -> 56580
B36: Actividades de inversión:
B37: Inventarios inmobiliarios pagados por anticipado | D37: =-BG!E20+BG!G20 -> -311819 | F37: -159432
B38: Mobiliario y equipo, neto | D38: =-BG!E21+BG!G21 -> -321 | F38: 0
B39: Intereses a cargo | D39: =+ER!E20 -> -21 | F39: =-F20 -> -11
B40: Intereses a favor | D40: =+ER!E21 -> 8050 | F40: =-F21 -> 2456
B41: Flujos netos de efectivo utilizados en actividades de inversión | D41: =SUM(D37:D40) -> -304111 | F41: =SUM(F37:F40) -> -156987
B43: Actividades de financiamiento:
B44: Préstamos bancarios | D44: =+BG!E36-BG!G36 -> 59000 | F44: 271000
B45: Otras aportaciones del Fideicomitente | D45: =+BG!E37-BG!G37 -> -70852 | F45: -123974
B46: Flujos netos de efectivo de actividades de Financiamiento | D46: =SUM(D44:D45) -> -11852 | F46: =SUM(F44:F45) -> 147026
B48: Aumento neto de efectivo y equivalentes de efectivo | D48: =+D34+D41+D46 -> -3932 | F48: =+F34+F41+F46 -> 46619
B50: Efectivo y equivalentes de efectivo al inicio del periodo | D50: =+F52 -> 46651 | F50: 32
B52: Efectivo y equivalentes de efectivo al final del periodo | C52: $ | D52: =+D48+D50 -> 42719 | E52: $ | F52: =+F48+F50 -> 46651
B56: Las notas adjuntas son parte de los estados financieros.
D58: =+D52-BG!E14 -> 0 | F58: =+F52-BG!G14 -> 0 | G58: <<Chek

Sheet Nota 1 y 2
B2: Fideicomiso Irrevocable 4341
B3: Fideicomiso FORTMCK 19-12 Lomas Verdes
B5: Notas a los Estados Financieros
B6: =+Datos!C7 -> Por los ejercicios terminados al 31 de diciembre de 2024 y 2023
B7: (En miles de pesos)
B9: 1. Naturaleza del Fideicomiso y características más importantes
B11: El Fideicomiso Irrevocable 4341 FORTMCK 19-12 Lomas Verdes (Banco Actinver, S. A., Institución de Banca Múltiple, Grupo Financiero Actinver, Fiduciario) (el “Fideicomiso”), se constituyó el 3 de octubre de 2018 mediante un contrato de fideicomiso irrevocable y de administración, entre Fortem Capital I, S.C. (Administrador), Fideicomiso Irrevocable No. 3518 (Banco Actinver, S.A., Institución de Banca Múltiple, Grupo Financiero Actinver, División Fiduciaria) (el “Fideicomiso Fortem CKD 18”) como Fideicomitente y Fideicomisario; y Banco Actinver, S.A., Institución de Banca Múltiple, Grupo financiero Actinver, División Fiduciaria, como fiduciario.
B13: El Fideicomitente y fideicomisario acordaron que la denominación del Fideicomiso sea Fideicomiso FORTMCK 19-12 Lomas Verdes y que el mismo no realizará actividades empresariales.
B15: El domicilio del Fideicomiso es Av. Santa Fe, No. 505, Interior 802, Santa Fe Cuajimalpa, C.P 05348, Ciudad de México.
B17: a. Proyecto
B19: El proyecto de Lomas Verdes fue presentado y autorizado por el Comité Técnico del Fideicomiso Fortem CKD 18, con las siguientes características:
B21: · Se trata de un proyecto mayormente residencial denominado “Terralago” ubicado en la zona de Lomas Verdes, en el municipio de Naucalpan de Juárez.
B23: · Consiste en la urbanización de la propiedad para la construcción de lotes y macro lotes habitacionales para desarrollo de vivienda, y macro lotes para espacios comerciales.
B25: · El Proyecto considera: (a) un área vendible total de 202,819m2 con la siguiente distribución: (i) 317 lotes unifamiliares con superficies desde 200m2 y 500m2, (ii) 29 macro lotes para desarrollo de vivienda vertical con superficies desde 800m2 hasta 5,600m2 concentrando un total de 87,999m2, (iii) 5 lotes comerciales, y (iv) 8.2 hectáreas de áreas verdes, y (b) un parque central.
B27: · Hasta septiembre de 2023 el Comité autorizó un presupuesto total de inversión de $1,892,601 de los cuales se han ejercido cerca del 42% y se realizará en 3 etapas.
B29: · La Administración del Fideicomiso estima que, con base en la información y proyecciones presupuestales disponibles a la fecha, la conclusión del proyecto ocurrirá en el ejercicio 2026; no obstante, dicha estimación se encuentra sujeta a que no se presenten eventos posteriores relevantes, cambios en las condiciones del mercado o circunstancias ajenas a la Administración que pudieran afectar los plazos originalmente previstos.
... B39: Decreto para regular la subcontratación laboral.
B41: =+CONCATENATE(Datos!C16,H41,Datos!C20,H43) -> El 27 de diciembre de 2022, se publicó en el Diario Oficial de la Federación un decreto por medio del cual se reformaron los artículos 76 y 78 de la Ley Federal del Trabajo (“LFT”), el cual entró en vigor el pasado 1o de enero de 2023. Su objetivo fue el de incrementar el período anual mínimo de vacaciones a los trabajadores que tengan más de un año de servicio. | H41: , se publicó en el Diario Oficial de la Federación un decreto por medio del cual se reformaron los artículos 76 y 78 de la Ley Federal del Trabajo (“LFT”), el cual entró en vigor el pasado
B43: Sin embargo, como se menciona anteriormente, los fines del Fideicomiso, son las inversiones en proyectos inmobiliarios, las cuales se gestionan a través de terceros especializados, por lo cual la Administración del Fideicomiso ha concluido que los servicios recibidos por parte de sus prestadores de servicios no constituyen subcontratación de personal laboral en los términos de la Reforma, por lo que no ha identificado impactos que revelar en los estados financieros adjuntos. | H43: . Su objetivo fue el de incrementar el período anual mínimo de vacaciones a los trabajadores que tengan más de un año de servicio.
B45: 2. Bases de presentación
B47: a. Aplicación de las Normas de Información Financiera (NIF) mexicanas y supletoriedad
B49: Los estados financieros al 31 de diciembre de 2024 y 2023, que se acompañan, cumplen cabalmente con lo establecido en las NIF, para mostrar una presentación razonable de la situación financiera del Fideicomiso. Las NIF establecen que las Normas Internacionales de Información Financiera (NIIF), Normas Internacionales de Contabilidad (NIC), Interpretaciones a las NIIF (INIIF) y el Comité́ de Interpretaciones (SIC) son supletoriamente parte de las NIF, cuando la ausencia de estas así́ lo requiera.
B51: Durante 2024 y 2023 el Fideicomiso, no aplicó en particular ninguna NIIF, INIIF y SIC supletorias, emitidas por el International Accounting Standards Board.
B53: A partir del 1 de enero de 2024 el Fideicomiso adoptó de manera prospectiva las siguientes NIF, y Mejoras a las NIF, emitidas por el Consejo Mexicano de Normas de Información Financiera (CINIF), y que entraron en vigor a partir de la fecha mencionada. La Administración considera que las NIF y las Mejoras a las NIF no tuvieron una afectación importante en la información financiera que presenta el Fideicomiso.
B55: Nuevas NIF 2024
B57: NIF C-10 – Instrumentos financieros derivados y relaciones de cobertura. Se incorpora el tratamiento contable para coberturas de instrumentos de capital cuyo valor razonable se reconoce en otros resultados integrales (ORI).
B59: NIF C-2 – Inversión en instrumentos financieros. Se actualiza la terminología y definición para los instrumentos financieros “para cobrar y vender”, permitiendo su reconocimiento en ORI incluso si no se venden por condiciones de mercado.
B61: NIF D-4 – Impuestos a la utilidad. Se precisa que, en caso de beneficios fiscales por capitalización de utilidades, los impuestos causados y diferidos se deben determinar con la tasa aplicable a utilidades no distribuidas.
B63: Mejoras generales 2024
B65: El Fideicomiso incorporó las siguientes precisiones normativas sin efectos materiales:
B67:  Revisión anual del valor residual, periodo y método de depreciación (NIF C-6, C-8).
... B105: El ejercicio terminado el 31 de diciembre de 2024 es considerado como entorno económico no inflacionario (inflación acumulada de los tres ejercicios anuales anteriores menor que el 26%), conforme a lo establecido en la NIF B-10 "Efectos de la inflación"; consecuentemente no se reconocen los efectos de la inflación en la información financiera del Fideicomiso; en caso de estar en un entorno inflacionario, se deberán registrar de manera retrospectiva los efectos acumulados de la inflación no reconocidos en los períodos en los que el entorno fue calificado como no inflacionario. El porcentaje de inflación anual, la acumulada en los tres últimos ejercicios y los índices utilizados para determinar la inflación son los siguientes:

Sheet Nota 1 tablas
D4: Al cierre de | E4: Inflación anual (%) | F4: Acumulada (%)
D6: 2024 | E6: 0.0421 | F6: 0.1763
D7: 2023 | E7: 0.0466 | F7: 0.1984
D8: 2022 | E8: 0.0782 | F8: 0.1833
B10: Negocio en Marcha –
B12: Los estados financieros han sido preparados por la Administración asumiendo que el Fideicomiso continuará operando como negocio en marcha.

Sheet Nota 3
B4: 3. Principales políticas contables
B6: A continuación, se resumen las políticas de contabilidad más significativas, las cuales han sido aplicadas consistentemente en los años que se presentan, a menos que se especifique lo contrario.
B8: Las NIF requieren el uso de ciertas estimaciones contables en la preparación de estados financieros. Asimismo, requieren que la Administración ejerza su juicio para definir las políticas de contabilidad que aplicará el Fideicomiso. Los rubros que involucran un mayor grado de juicio o complejidad y los que los supuestos y estimaciones son significativos para los estados financieros se describen en la Nota anterior.
B10: a. Efectivo y equivalentes de efectivo
B12: El efectivo y equivalentes de efectivo incluye saldos de caja, depósitos bancarios y otros instrumentos financieros de alta liquidez, con riesgos de poca importancia por cambios en su valor. El efectivo y los equivalentes de efectivo se reconocen inicialmente a su valor razonable.
B14: Los instrumentos financieros de alta liquidez se valúan con base en el modelo negocios que corresponda para cada tipo de instrumento, esto es, con fines de negociación, para cobrar principal e intereses o para cobrar y vender. Los cambios en el valor razonable se reconocen en el estado de resultado integral conforme se devengan.
B16: El efectivo y equivalentes de efectivo denominados en moneda extranjera u otra medida de intercambio, como es el caso de las Unidades de Inversión (UDI), deben convertirse a la medida de intercambio correspondiente a la fecha de cierre de los estados financieros. Los efectos por conversión deben reconocerse en el estado de resultados integral conforme se devenguen.
B18: b. Deudores diversos y otras cuentas por cobrar
B20: Los deudores diversos y otras cuentas por cobrar se reconocen cuando la transacción se realiza, o el bien o servicio es devengado, esto es, cuando de acuerdo con el contrato celebrado se ha transferido el control de los recursos, bienes o servicios. Los deudores diversos y otras cuentas por cobrar se valúan inicialmente al precio de la transacción y posteriormente al precio de la transacción pendiente de cobro, menos las bonificaciones, descuentos o devoluciones y la estimación para perdidas crediticias, en caso de corresponder.
B22: Cuando se espera que las cuentas por cobrar se recuperen en un periodo de un año o menos desde la fecha de cierre (o en el ciclo normal de operaciones del negocio en el caso que este ciclo exceda este periodo) se presentan como activo circulante. En caso de no cumplir lo mencionado se presentan como activos no circulantes.
B24: Las pérdidas crediticias esperadas existentes, así́ como las diferencias que surgen de cancelar dichas pérdidas crediticias se presentan formando parte del rubro de gastos. Dichas pérdidas son determinadas (individualmente) (de forma colectiva) atendiendo a las siguientes características:
B26: La estimación de pérdidas crediticias esperadas se determina considerando la probabilidad de incumplimiento y la severidad de la pérdida de las cuentas por cobrar con base en la experiencia histórica, condiciones actuales y pronósticos razonables que se observan en el comportamiento de las mismas.
... B100: Las obligaciones o pérdidas relacionadas con contingencias se reconocen cuando es probable que sus efectos se materialicen y existan elementos razonables para su cuantificación. Si no existen estos elementos razonables, se incluye revelación en forma cualitativa en las notas a los estados financieros. Los ingresos, utilidades o activos contingentes se reconocen hasta el momento en que existe certeza de su realización.

Sheet N4 Efectivo
B3: 4. Efectivo y equivalentes de efectivo
B5: =+CONCATENATE(Datos!C14,E5) -> Al 31 de diciembre de 2024 y 2023, el saldo se integra principalmente por depósitos en cuentas de cheques, todos de gran liquidez: | E5: , el saldo se integra principalmente por depósitos en cuentas de cheques, todos de gran liquidez:
G8: =+Datos!C8 -> 2024 | I8: =+Datos!C9 -> 2023
E10: Depósitos en cuenta de cheques | F10: $ | G10: =+ROUND((SUMIF(BalanzaActual!$AI:$AI,E10,BalanzaActual!$Z:$Z)),0) -> 464 | H10: $ | I10: =+ROUND((SUMIF(BalanzaAnterior!$AF:$AF,E10,BalanzaAnterior!$Y:$Y)),0) -> 1174
E11: Inversiones en valores realizables | G11: =+ROUND((SUMIF(BalanzaActual!$AI:$AI,E11,BalanzaActual!$Z:$Z)),0) -> 42255 | I11: =+ROUND((SUMIF(BalanzaAnterior!$AF:$AF,E11,BalanzaAnterior!$Y:$Y)),0) -> 45477
E12: Total | F12: $ | G12: =SUM(G10:G11) -> 42719 | H12: $ | I12: =SUM(I10:I11) -> 46651
G14: =+'N4 Efectivo'!G12-BG!E14 -> 0 | I14: =+'N4 Efectivo'!I12-BG!G14 -> 0 | J14: Check

Sheet Nota 5 Txt
B5: 5. Inventarios inmobiliarios y costos pagados por anticipado
B7: Los inventarios inmobiliarios y costos pagados por anticipado incluyen desarrollos inmobiliarios residenciales los cuales se encuentran en proceso de urbanización y construcción de casa habitación principalmente. El Fideicomiso desarrolla los proyectos a través de la contratación de Constructoras y empresas especializadas en el mercado particular del proyecto lo que simplifica su ejecución y mejora su eficiencia.
B9: El Fideicomiso registra en el rubro de “Inventarios inmobiliarios” los conceptos de lotes y terrenos en los que ya han sido traspasados los riesgos y beneficios. Por su parte, los pagos que realiza a sus proveedores se registran como costos pagados por anticipado en tanto no le han sido traspasados los riesgos y beneficios del activo final; dichos costos pagados por anticipado deben presentarse de forma separada e incluyen las construcciones en proceso, los gastos legales, financieros y por trámites ante autoridades gubernamentales, así como los gastos de administración y comercialización. Ambos conceptos forman la cuenta de "Inventarios inmobiliarios y costos pagados por anticipado".
B11: Al 31 de diciembre de 2024 y 2023, el saldo de inventarios inmobiliarios pagados por anticipado corresponde a: | E11: , el saldo de este rubro, corresponde a:
B13: Al cierre del ejercicio 2024, el Fideicomiso registró un incremento significativo en el desarrollo "Terralago", derivado principalmente de inversiones orientadas al desarrollo y comercialización del proyecto. Las erogaciones se centraron en trámites estatales por impacto de obra, rehabilitación de vialidades, capitalización de intereses, comisiones de comercialización, gestiones ante la CFE y honorarios de administración. Adicionalmente, se realizaron inversiones en infraestructura básica como sistemas de agua potable y tratada, pavimentación de vialidades y obra eléctrica. Este incremento refleja el progreso relevante alcanzado en la etapa de urbanización del proyecto.
B15: (i) Los terrenos corresponden a bienes inmuebles adquiridos por el fideicomiso para su desarrollo o enajenación futura. Se clasifican como inventario inmobiliario y se reconocen al costo de adquisición, incluyendo gastos directamente atribuibles a su compra
B17: (ii) Las construcciones en proceso representan la inversión realizada en obras que se encuentran en ejecución y que aún no han sido concluidas ni destinadas a su uso final. Este rubro incluye los costos directos e indirectos atribuibles a la construcción, tales como materiales, mano de obra, servicios contratados y gastos relacionados con el desarrollo del proyecto.
B19: (iii) Los gastos legales, financieros y por trámites corresponden a los costos necesarios para la adecuada estructuración, financiamiento y regularización del proyecto. Este rubro incluye honorarios por asesoría legal y financiera, costos asociados a la obtención de permisos y licencias, derechos de registro, gastos notariales, así como comisiones bancarias o de financiamiento directamente relacionados.
B21: (iv) Los gastos administrativos y de comercialización comprenden los costos incurridos en la gestión, coordinación y promoción dirigidos a la comercialización del proyecto.
B23: (v) Los otros pagos anticipados corresponden a anticipos otorgados a proveedores y contratistas para la adquisición de bienes o servicios necesarios para la ejecución de dichas obras.
B25: Al 31 de diciembre de 2024 y 2023, los movimientos en la cuenta de inventarios inmobiliarios pagados por anticipado fueron como sigue:
B27: Estos desarrollos inmobiliarios garantizan los préstamos que se mencionan en la Nota 8, e incluyen la capitalización al cierre de 2024 y 2023 de $ 79,785 y $ 22,958 por costos financieros.
B213: 1. Contingencias
B215: Al 31 de diciembre de 2023, como consecuencia de las operaciones propias de su actividad, el Fideicomiso identifica, monitorea y evalúa diversos criterios o asuntos que pudieran representar una contingencia económica, fiscal o reputacional, los cuales están comunicados a los responsables del gobierno de la entidad ya que por su naturaleza pueden tener impacto en el futuro en caso de que cambien las circunstancias actuales, sin embargo, en opinión de la Administración y de sus asesores legales, fiscales y laborales internos y externos considera que los mismos no representan pasivos contingentes a esa fecha ya que no ha recibido reclamos y no ha sido emplazada a juicios materiales que sean cuantificables de manera confiable.
B217: De acuerdo con la legislación fiscal vigente, las autoridades tienen la facultad de revisar los cinco ejercicios fiscales anteriores a la última declaración del Impuesto Sobre la Renta (ISR) presentada.
B222: 2. Compromisos contraídos
... B236: Los estados financieros y las notas a los mismos fueron autorizados para su emisión y publicación el 20 de marzo de 2024, por Ignacio García de Quevedo Gómez Gallardo - Director de Administración y Finanzas, y están sujetas a la aprobación del Comité Técnico y Administrador del Fideicomiso.

Sheet N5 Inventarios Inm(Tablas)
D3: =+Datos!C8 -> 2024 | F3: =+Datos!C9 -> 2023 | G3: Variación vs 2023
B4: Inventarios inmobiliarios
B5: Terrenos (i) | C5: $ | D5: =+ROUND((SUMIF(BalanzaActual!$AI:$AI,B5,BalanzaActual!$Z:$Z)),0) -> 388000 | E5: $ | F5: =+ROUND((SUMIF(BalanzaAnterior!$AF:$AF,B5,BalanzaAnterior!$Y:$Y)),0) -> 388000 | G5: =+D5-F5 -> 0
B6: Total de Inventarios inmobiliarios | D6: =+D5 -> 388000 | F6: =+F5 -> 388000
B8: Costos pagados por anticipado
B9: Construcción en proceso (ii) | D9: =+ROUND((SUMIF(BalanzaActual!$AI:$AI,B9,BalanzaActual!$Z:$Z)),0) -> 95033 | F9: =+ROUND((SUMIF(BalanzaAnterior!$AF:$AF,B9,BalanzaAnterior!$Y:$Y)),0) -> 13933 | G9: =+D9-F9 -> 81100
B10: Gastos legales, financieros y por trámites (iii) | D10: =+ROUND((SUMIF(BalanzaActual!$AI:$AI,B10,BalanzaActual!$Z:$Z)),0) -> 478485 | F10: =+ROUND((SUMIF(BalanzaAnterior!$AF:$AF,B10,BalanzaAnterior!$Y:$Y)),0) -> 293576 | G10: =+D10-F10 -> 184909
B11: Gastos administrativos y de comercialización (iv) | D11: =+ROUND((SUMIF(BalanzaActual!$AI:$AI,B11,BalanzaActual!$Z:$Z)),0) -> 25669 | F11: =+ROUND((SUMIF(BalanzaAnterior!$AF:$AF,B11,BalanzaAnterior!$Y:$Y)),0) -> 26034 | G11: =+D11-F11 -> -365
B12: Total Costos pagados por anticipado | D12: =+D11+D10+D9 -> 599187 | F12: =+F11+F10+F9 -> 333543
B14: Impuesto al Valor Agregado | D14: =+ROUND((SUMIF(BalanzaActual!$AI:$AI,B14,BalanzaActual!$Z:$Z)),0) -> 72465 | F14: =+ROUND((SUMIF(BalanzaAnterior!$AF:$AF,B14,BalanzaAnterior!$H:$H)/1000),0) -> 41306 | G14: =+D14-F14 -> 31159
B16: Otros pagos anticipados (v) | D16: =+ROUND((SUMIF(BalanzaActual!$AI:$AI,B16,BalanzaActual!$Z:$Z)),0) -> 26131 | F16: =+ROUND((SUMIF(BalanzaAnterior!$AF:$AF,B16,BalanzaAnterior!$Y:$Y)),0) -> 11115 | G16: =+D16-F16 -> 15016
B17: Total Inventarios inmobiliarios y costos pagados por anticipado | C17: $ | D17: =+D16+D6+D12+D14 -> 1085783 | E17: $ | F17: =+F16+F6+F12+F14 -> 773964
D19: =+D17-BG!E20 -> 0 | F19: =+F17-BG!G20 -> 0 | G19: <<Check
D21: 2024 | F21: 2023
B23: Inversión al inicio del periodo | C23: $ | D23: =+F17 -> 773964 | E23: $ | F23: =573172+1 -> 573173 | G23: =+D23-F23 -> 200791
B25: Adiciones por costos capitalizados | D25: =+D12+D16-F12-F16+D14-F14 -> 311819 | F25: =159485+F14 -> 200791 | G25: =+D25-F25 -> 111028
B27: Inversión al final del periodo | C27: $ | D27: =+D23+D25 -> 1085783 | E27: $ | F27: =+F23+F25 -> 773964
D29: =+D27-D17 -> 0 | F29: =+F27-F17 -> 0 | G29: <<Check

Sheet N6 Proveedores
B3: 6. Proveedores y acreedores diversos
B5: Al 31 de diciembre de 2024 y 2023, el saldo se integra principalmente por saldos a favor de proveedores relacionados con el desarrollo y construcción del proyecto como sigue:
M7: Saldo en pesos | O7: Saldo en miles
G8: =+Datos!C8 -> 2024 | I8: =+Datos!C9 -> 2023 | M8: 2024 | N8: 2023 | O8: 2024 | P8: 2023 | Q8: Clasificación
L9: Proveedor: ( 101 ) FIDEICOMISO IRREVOCABLE NUMERO 3518 | M9: -1205516.7 | O9: =+ROUND(M9/1000,0) -> -1206 | P9: =+ROUND(N9/1000,0) -> 0
E10: Construcción y desarrollo | F10: $ | G10: =+-SUMIF(Q:Q,E10,O:O) -> 29645 | H10: $ | I10: =+-SUMIF(Q:Q,E10,P:P) -> 3523 | L10: Proveedor: ( 205 ) BANCO ACTINVER S.A., INSTITUCION DE BANCA MULTIPLE, GRUPO FINANCIERO ACTINVER | M10: -6960 | N10: -6960 | O10: =+ROUND(M10/1000,0) -> -7 | P10: =+ROUND(N10/1000,0) -> -7 | Q10: Administrativos de obra
E11: Relacionados a energía eléctrica | G11: =+-SUMIF(Q:Q,E11,O:O) -> 2887 | I11: =+-SUMIF(Q:Q,E11,P:P) -> 0 | L11: Proveedor: ( 1061 ) BLUEPATH, S.A. DE C.V. | M11: -7571.32 | N11: -9941.2 | O11: =+ROUND(M11/1000,0) -> -8 | P11: =+ROUND(N11/1000,0) -> -10 | Q11: Administrativos de obra
E12: Administrativos de obra | G12: =+-SUMIF(Q:Q,E12,O:O) -> 1801 | I12: =+-SUMIF(Q:Q,E12,P:P) -> 2817 | L12: Proveedor: ( 1108 ) CUERPO DE VIGILANCIA AUXILIAR Y URBANA DEL ESTADO DE MEXICO | M12: -153358.24 | N12: -290164.8 | O12: =+ROUND(M12/1000,0) -> -153 | P12: =+ROUND(N12/1000,0) -> -290 | Q12: Administrativos de obra
E13: Consultoría en desarrollo y construcción | G13: =+-SUMIF(Q:Q,E13,O:O) -> 1445 | I13: =+-SUMIF(Q:Q,E13,P:P) -> 1017 | L13: Proveedor: ( 1556 ) ROBERTO CUETO STRIMPOPULOS | M13: -43851.37 | N13: -8330.66 | O13: =+ROUND(M13/1000,0) -> -44 | P13: =+ROUND(N13/1000,0) -> -8 | Q13: Administrativos de obra
E14: Total | F14: $ | G14: =SUM(G10:G13) -> 35778 | H14: $ | I14: =SUM(I10:I13) -> 7357 | L14: Proveedor: ( 1660 ) CFE DISTRIBUCION | M14: -2886509.2 | O14: =+ROUND(M14/1000,0) -> -2887 | P14: =+ROUND(N14/1000,0) -> 0 | Q14: Relacionados a energía eléctrica
L15: Proveedor: ( 1995 ) AMIRA KARAM MORALES | M15: -171 | O15: =+ROUND(M15/1000,0) -> 0 | P15: =+ROUND(N15/1000,0) -> 0 | Q15: Administrativos de obra
G16: =+'N6 Proveedores'!G14-BG!E29 -> 0 | I16: =+'N6 Proveedores'!I14-BG!G29 -> 0 | J16: Check | L16: Proveedor: ( 3325 ) ANA LILIA JANETH PORRAS FIGUEROA | M16: -1579983 | N16: -2077337.8 | O16: =+ROUND(M16/1000,0) -> -1580 | P16: =+ROUND(N16/1000,0) -> -2077 | Q16: Administrativos de obra
L17: Proveedor: ( 3350 ) GRUPO CONSTRUCTOR ACTUM SA DE CV | M17: -850400 | O17: =+ROUND(M17/1000,0) -> -850 | P17: =+ROUND(N17/1000,0) -> 0 | Q17: Construcción y desarrollo
L18: Proveedor: ( 3360 ) THREE CONSULTORIA MEDIOAMBIENTAL SA DE CV | M18: -353089.72 | O18: =+ROUND(M18/1000,0) -> -353 | P18: =+ROUND(N18/1000,0) -> 0 | Q18: Consultoría en desarrollo y construcción
L19: Proveedor: ( 3361 ) INGENIERIA Y CONSTRUCCIONES GABE SA DE CV | M19: -935365.14 | O19: =+ROUND(M19/1000,0) -> -935 | P19: =+ROUND(N19/1000,0) -> 0 | Q19: Construcción y desarrollo
L20: Proveedor: ( 3367 ) GRUPO CULUMBIO MEXICO SA DE CV | M20: -12467641 | O20: =+ROUND(M20/1000,0) -> -12468 | P20: =+ROUND(N20/1000,0) -> 0 | Q20: Construcción y desarrollo
L21: Proveedor: ( 3422 ) INDUSTRIAL DE ASFALTOS Y PAVIMENTOS SA DE CV | M21: -2139981.6 | O21: =+ROUND(M21/1000,0) -> -2140 | P21: =+ROUND(N21/1000,0) -> 0 | Q21: Construcción y desarrollo
L22: Proveedor: ( 3428 ) CONTROL LOGISTICO Y ADMINISTRADORA DE VALVULAS Y EQUIPOS SA DE CV | M22: -12909332 | O22: =+ROUND(M22/1000,0) -> -12909 | P22: =+ROUND(N22/1000,0) -> 0 | Q22: Construcción y desarrollo
L23: Proveedor: ( 3440 ) TGC GEOTECNIA SA DE CV | M23: -206909.2 | O23: =+ROUND(M23/1000,0) -> -207 | P23: =+ROUND(N23/1000,0) -> 0 | Q23: Construcción y desarrollo
L24: Proveedor: ( 3548 ) CUARTAGO CONSULTORES SA DE CV | M24: -87000 | O24: =+ROUND(M24/1000,0) -> -87 | P24: =+ROUND(N24/1000,0) -> 0 | Q24: Consultoría en desarrollo y construcción
L25: Proveedor: ( 3561 ) ISIDRO MORENO CAMACHO | M25: -8700 | O25: =+ROUND(M25/1000,0) -> -9 | P25: =+ROUND(N25/1000,0) -> 0 | Q25: Administrativos de obra
L26: Proveedor: ( 3565 ) ESENCIA REPUTACIONAL SC | M26: -136300 | O26: =+ROUND(M26/1000,0) -> -136 | P26: =+ROUND(N26/1000,0) -> 0 | Q26: Construcción y desarrollo
L27: Proveedor: ( 25 ) VICTOR MANUEL LIRA ESTRELLA | N27: -2467.65 | O27: =+ROUND(M27/1000,0) -> 0 | P27: =+ROUND(N27/1000,0) -> -2 | Q27: Administrativos de obra
L28: Proveedor: ( 1081 ) Notaria 211 y 135 de la Ciudad de México | N28: -8068 | O28: =+ROUND(M28/1000,0) -> 0 | P28: =+ROUND(N28/1000,0) -> -8 | Q28: Administrativos de obra
L29: Proveedor: ( 1153 ) CORPORATIVO PYCESA S.A. DE C.V. | N29: -1722106.7 | O29: =+ROUND(M29/1000,0) -> 0 | P29: =+ROUND(N29/1000,0) -> -1722 | Q29: Construcción y desarrollo
L30: Proveedor: ( 1798 ) WRIGHT ADMON, S.A.DE C.V. | N30: -1160 | O30: =+ROUND(M30/1000,0) -> 0 | P30: =+ROUND(N30/1000,0) -> -1 | Q30: Administrativos de obra
L31: Proveedor: ( 2529 ) LUCIANO MEDINA ELENO | N31: -416333.2 | O31: =+ROUND(M31/1000,0) -> 0 | P31: =+ROUND(N31/1000,0)+2 -> -414 | Q31: Administrativos de obra
L32: Proveedor: ( 2607 ) ITEGRA-HEXABYTE, S.A. DE C.V. | N32: -59344.83 | O32: =+ROUND(M32/1000,0) -> 0 | P32: =+ROUND(N32/1000,0) -> -59 | Q32: Construcción y desarrollo
L33: Proveedor: ( 2692 ) FPMEXICO ABOGADOS, S.A. | N33: -870000 | O33: =+ROUND(M33/1000,0) -> 0 | P33: =+ROUND(N33/1000,0) -> -870 | Q33: Consultoría en desarrollo y construcción
L34: Proveedor: ( 3339 ) DEOLIVASE SA DE CV | N34: -15080 | O34: =+ROUND(M34/1000,0) -> 0 | P34: =+ROUND(N34/1000,0) -> -15 | Q34: Construcción y desarrollo
L35: Proveedor: ( 3342 ) IYG PROYECTO, CONSTRUCCION Y MANTENIMIENTO SA DE CV | N35: -101110.7 | O35: =+ROUND(M35/1000,0) -> 0 | P35: =+ROUND(N35/1000,0) -> -101 | Q35: Construcción y desarrollo
L36: Proveedor: ( 3343 ) CAPSTONE ADVISORS, SC | N36: -52200 | O36: =+ROUND(M36/1000,0) -> 0 | P36: =+ROUND(N36/1000,0) -> -52 | Q36: Construcción y desarrollo
L37: Proveedor: ( 3345 ) AMELO INFRAESTRUCTURA SA DE CV | N37: -1421000 | O37: =+ROUND(M37/1000,0) -> 0 | P37: =+ROUND(N37/1000,0) -> -1421 | Q37: Construcción y desarrollo
L38: Proveedor: ( 3353 ) CONSORCIO CONSTRUCTOR AA SA DE CV | N38: -153236 | O38: =+ROUND(M38/1000,0) -> 0 | P38: =+ROUND(N38/1000,0) -> -153 | Q38: Construcción y desarrollo
L39: Proveedor: ( 3354 ) BBSRED CORPORATIVO SA DE CV | N39: -4638.84 | O39: =+ROUND(M39/1000,0) -> 0 | P39: =+ROUND(N39/1000,0) -> -5 | Q39: Consultoría en desarrollo y construcción
L40: Proveedor: ( 3843 ) WILLIAMS SCOTSMAN MEXICO S DE RL DE CV | N40: -50234.38 | O40: =+ROUND(M40/1000,0) -> 0 | P40: =+ROUND(N40/1000,0) -> -50 | Q40: Consultoría en desarrollo y construcción
L41: Proveedor: ( 4000 ) FFM CONSUMO SA DE CV | N41: -91640 | O41: =+ROUND(M41/1000,0) -> 0 | P41: =+ROUND(N41/1000,0) -> -92 | Q41: Consultoría en desarrollo y construcción
L42: Proveedor: ( 3304 ) MAAT ABOGADOS SC | M42: 0 | O42: =+ROUND(M42/1000,0) -> 0 | Q42: Consultoría en desarrollo y construcción
L43: Proveedor: ( 3430 ) GRUPO DESARROLLADOR SEQUOYA SA DE CV / VELEMENT SA DE CV | M43: -500000 | O43: =+ROUND(M43/1000,0) -> -500 | Q43: Consultoría en desarrollo y construcción
L44: Proveedor: ( 3839 ) DEPOSITOS POR IDENTIFICAR | M44: -505000 | O44: =+ROUND(M44/1000,0) -> -505 | Q44: Consultoría en desarrollo y construcción

Sheet N7 Depósitos en garantía
B2: 7. Depósitos en garantía recibidos
B4: Al 31 de diciembre de 2024 y 2023, los depósitos en garantía corresponden a montos entregados por terceros con la intención de adquirir inmuebles, estos montos no implican una compraventa formal hasta que se cumplan los requisitos legales correspondientes, incluyendo la escrituración y transferencia de los riesgos y beneficios del inmueble. Por lo tanto, se reconocen como pasivo a valor histórico. Las garantías retenidas corresponden a montos descontados a diversos proveedores por obligaciones contractuales, y serán devueltas conforme a los plazos y condiciones establecidos, los depósitos en garantía se detallan como sigue:
B7: Al cierre del tercer trimestre de 2024 se han obtenido promesas de compraventa de 89 unidades habitacionales, 8 unidades multifamiliares, 3 unidades comerciales y el terreno de Naucalpan, con una superficie de 2.2 hectáreas, alcanzando un valor total comprometido de $926,005, este resultado representa un avance del 95% respecto al plan establecido y un progreso del 63%, lo que refleja un desempeño favorable a pesar de que durante algunos meses del año la obra se vio afectada por una suspensión temporal derivada de factores ajenos a la administración. Dicha suspensión fue levantada antes del cierre de diciembre, permitiendo retomar el ritmo normal de ejecución del proyecto, el cual mantiene bases sólidas que respaldan su continuidad y desarrollo.
F8: 2024 | H8: 2023
D10: Saldo inicial | E10: $ | F10: 71045 | G10: $ | H10: -
D11: Depósitos por promesas de compraventa | F11: =203263+141589+8500 -> 353352 | H11: =3877+66418+950 -> 71245
D12: Devoluciones y/o cancelaciones | F12: -19336 | H12: -200
D13: Total Depósitos en garantía | E13: $ | F13: =SUM(F10:F12) -> 405061 | G13: $ | H13: =SUM(H10:H12) -> 71045
D15: Garantías retenidas a proveedores | F15: =-ROUND((SUMIF(BalanzaActual!$AI:$AI,D15,BalanzaActual!$Z:$Z)),0) -> 2889 | H15: =-ROUND((SUMIF(BalanzaActual!$AI:$AI,F15,BalanzaActual!$Z:$Z)),0) -> 0
D16: Total Depósitos en garantía recibidos | E16: $ | F16: =+F15+F13 -> 407950 | G16: $ | H16: =+H15+H13 -> 71045
F18: =+F16-BG!E35 -> 0 | H18: =+H16-BG!G35 -> 0 | I18: <<Check

Sheet N8 Préstamos
B3: 8. Préstamos a largo plazo
B5: Al 31 de diciembre de 2024 y 2023, el Fideicomiso ha recibido un préstamo bancario hasta por $330,000, con NXX CAPITAL MEZZI, SAPI DE CV SOFOM ENR, del cual se han realizado diversas disposiciones durante los ejercicios, los saldos y detalle se presentan a continuación:
B8: Con fecha 6 de marzo de 2024, el Fideicomiso realizó la cuarta disposición por un monto de $59,000 en el marco del contrato de crédito simple celebrado con NXX Capital Mezz I, S.A.P.I. de C.V., SOFOM, E.N.R., el 24 de agosto de 2023. La disposición fue estructurada con una entrega neta al acreditado de $55,124 reteniéndose $2,849 para la cuenta de reserva y $1,027 por concepto de comisión por estructuración. Los recursos solicitados se destinaron a diversos conceptos del proyecto, entre ellos ingeniería y construcción, dotación de energía eléctrica, publicidad, estudios de impacto ambiental y seguridad en obra. Esta disposición devenga intereses ordinarios a una tasa anual del 18%, conforme a las condiciones establecidas en el contrato de crédito, cabe destacar que los intereses devengados se facturan y liquidan en el mismo mes, contribuyendo a una mayor solidez en los flujos de efectivo.
B10: Con fecha 24 de agosto de 2023, el Fideicomiso celebró un contrato de crédito con Nxx Capital Mezz I, S.A.P.I. de C.V., SOFOM, E.N.R. (“Nexxus Capital”), como acreditante, sujeto a los límites de apalancamiento establecidos contractualmente. Durante el ejercicio 2023 se realizaron diversas disposiciones del crédito, sumando un total de $271,000, registrándose los costos financieros e intereses devengados en el rubro de inventarios inmobiliarios pagados por anticipado.
H11: =+Datos!C8 -> 2024 | J11: =+Datos!C9 -> 2023
F13: Principal del crédito | G13: $ | H13: =+ROUND((-SUMIF(BalanzaActual!$AI:$AI,F13,BalanzaActual!$Z:$Z)),0) -> 330000 | I13: $ | J13: =+ROUND((-SUMIF(BalanzaAnterior!$AF:$AF,F13,BalanzaAnterior!$Y:$Y)),0) -> 271000
F14: Total | G14: $ | H14: =SUM(H13:H13) -> 330000 | I14: $ | J14: =SUM(J13:J13) -> 271000
H17: =+H14-BG!E36 -> 0 | J17: =+J14-BG!G36 -> 0 | K17: Check

Sheet N9 Otras Aportaciones Fid
B3: 9. Otras aportaciones del Fideicomitente
B5: Para el cumplimiento de su modelo de negocio, el Fideicomiso ha recibido diversas aportaciones del Fideicomiso Fortem CKD 18, las cuales se clasifican en el pasivo según la NIF C 11 y la NIF C 12, principalmente porque estas obligaciones a cargo del Fideicomiso, deben ser cubiertas en efectivo o en su caso, con otros activos diferentes a los Instrumentos financieros de capital/patrimonio del mismo Fideicomiso.
B7: =+CONCATENATE(Datos!C14,", el saldo de estas aportaciones es de $ ",H18," y $ ",J18," respectivamente.") -> Al 31 de diciembre de 2024 y 2023, el saldo de estas aportaciones es de $ 125867 y $ 196719 respectivamente.
H16: =+Datos!C8 -> 2024 | J16: =+Datos!C9 -> 2023
F18: Otras aportaciones del fideicomitente | G18: $ | H18: =+ROUND((-SUMIF(BalanzaActual!$AI:$AI,F18,BalanzaActual!$Z:$Z)),0) -> 125867 | I18: $ | J18: =+ROUND((-SUMIF(BalanzaAnterior!$AF:$AF,F18,BalanzaAnterior!$Y:$Y)),0) -> 196719
F19: Total | G19: $ | H19: =+H18 -> 125867 | I19: $ | J19: =+J18 -> 196719
H21: =+BG!E37-H19 -> 0 | J21: =+BG!G37-J19 -> 0 | K21: Check

Sheet Nota 10 Impuestos
B7: 10. Impuestos a la utilidad
B9: La Administración del Fideicomiso considera éste no realiza actividades empresariales con base en el artículo 16 del Código Fiscal de la Federación (CFF), por lo que no ésta obligado al cálculo y determinación de impuestos a la utilidad conforme a lo dispuesto en el artículo 13 de la Ley del ISR, como resultado de lo anterior, el Fideicomiso no ha reconocido en sus resultados los efectos del impuesto sobre la renta corriente y diferido que corresponden a sus operaciones, así como activos y pasivos y que en su momento serán responsabilidad de los Fideicomitentes informarlos y enterarlos a las autoridades fiscales.

Sheet N11 Patrimonio
B3: 11. Patrimonio
B5: =+CONCATENATE(Datos!C14,D5) -> Al 31 de diciembre de 2024 y 2023, las aportaciones de patrimonio al fideicomiso fueron de la siguiente forma: | D5: , las aportaciones de patrimonio al fideicomiso fueron de la siguiente forma:
B8: El patrimonio del Fideicomiso está integrado de los siguientes bienes y derechos:
B10: · Por la Aportación inicial.
B12: · Por las aportaciones que realice el Fideicomitente para que el Fiduciario el proyecto inmobiliario correspondiente y comercialice el mismo, en los términos adquiera los activos, desarrolle y construya de los fines del Fideicomiso.
B14: · Por los activos, así como todos los derechos y obligaciones relacionados con los mismos, o cualquier activo y derechos que sean cedidos al y/o adquiridos y/o asumidos por el Fiduciario para fines del Fideicomiso.
B16: · Por los frutos y productos que se obtengan como consecuencia de la comercialización y operación del proyecto inmobiliario, incluyendo, sin limitar, el pago de las rentas generadas por el proyecto inmobiliario, pagos de cuotas de mantenimiento, entre otros.
B18: Las partes del Fideicomiso reconocen que el patrimonio se le trasmite o se le trasmitirá al Fiduciario exclusivamente para cumplir los fines del Fideicomiso. El Fiduciario no asume y queda liberado de responsabilidad alguna respecto de la procedencia, autenticidad o legitimidad de los recursos recibidos con motivo de la aportación que se realice al patrimonio.
B20: Durante la vigencia del Fideicomiso, el Fideicomitente, de conformidad con las instrucciones que reciba del Administrador, el Comité Técnico o, en su caso, la Asamblea de Tenedores, realizará aportaciones al Fideicomiso cuyos fines podrán ser:
B22: i. La realización de inversiones.
B23: ii. El pago de gastos del Fideicomiso.
D31: Compañía | G31: Porcentaje de participación | I31: =+Datos!C8 -> 2024 | K31: =+Datos!C9 -> 2023
D33: Fideicomiso Fortem CKD 18 | G33: 1 | H33: $ | I33: =+ROUND((-SUMIF(BalanzaActual!$AI:$AI,D33,BalanzaActual!$Z:$Z)),0) -> 272972 | J33: $ | K33: =+ROUND((-SUMIF(BalanzaAnterior!$AF:$AF,D33,BalanzaAnterior!$Y:$Y)),0) -> 272972
D34: Total de aportaciones | G34: 1 | H34: $ | I34: =SUM(I33) -> 272972 | J34: $ | K34: =SUM(K33) -> 272972
I36: =+I34-BG!E43 -> 0 | K36: =+K34-BG!G43 -> 0 | L36: <<Check

Sheet N12 Vencimientos
B3: 12. Tabla de vencimientos de los principales activos y pasivos
B5: =+CONCATENATE(F5,LOWER(Datos!C18),":") -> A continuación, se muestran los plazos de vencimientos de los principales rubros de activo y pasivo al 31 de diciembre de 2024 y 2023: | F5: A continuación, se muestran los plazos de vencimientos de los principales rubros de activo y pasivo
F16: =BG!B12 -> Activos | H16: Hasta un año | I16: =BG!D12 -> 0 | J16: Mayor a un año | K16: =BG!F12 -> 0 | L16: Total | M16: Check
F18: =BG!B14 -> Efectivo y equivalentes de efectivo | G18: $ | H18: =+BG!E14 -> 42719 | I18: $ | J18: 0 | K18: $ | L18: =SUM(H18:J18) -> 42719 | M18: =+L18-BG!E14 -> 0
F19: =BG!B15 -> Deudores diversos y otras cuentas por cobrar | H19: =+BG!E15 -> 24099 | J19: 0 | L19: =SUM(H19:J19) -> 24099 | M19: =+L19-BG!E15 -> 0
F20: =BG!B16 -> Cuentas por cobrar a partes relacionadas | H20: =+BG!E16 -> 943 | J20: 0 | L20: =SUM(H20:J20) -> 943 | M20: =+L20-BG!E16 -> 0
F21: =+BG!B20 -> Inventarios inmobiliarios y costos pagados por anticipado | H21: 0 | J21: =+BG!E20 -> 1085783 | L21: =SUM(H21:J21) -> 1085783 | M21: =+L21-BG!E20 -> 0
F22: =+BG!B22 -> Impuestos por recuperar | H22: 0 | J22: =+BG!E22 -> 291 | L22: =SUM(H22:J22) -> 291 | M22: =+L22-BG!E22 -> 0
F23: Total de activos | G23: $ | H23: =SUM(H18:H22) -> 67761 | I23: $ | J23: =SUM(J18:J22) -> 1086074 | K23: $ | L23: =SUM(L18:L22) -> 1153835
F25: =BG!B27 -> Pasivos | H25: Hasta un año | I25: =BG!D19 -> 0 | J25: Mayor a un año | K25: =BG!F19 -> 0 | L25: Total
F27: =BG!B29 -> Proveedores y acreedores diversos | G27: $ | H27: =+BG!E29 -> 35778 | I27: $ | J27: 0 | K27: $ | L27: =SUM(H27:J27) -> 35778 | M27: =+L27-BG!E29 -> 0
F28: =BG!B30 -> Cuentas por pagar a partes relacionadas | H28: =+BG!E30 -> 2183 | J28: 0 | L28: =SUM(H28:J28) -> 2183 | M28: =+L28-BG!E30 -> 0
F29: =+BG!B35 -> Depósitos en garantía recibidos | H29: 0 | J29: =+BG!E35 -> 407950 | L29: =SUM(H29:J29) -> 407950 | M29: =+L29-BG!E35 -> 0
F30: =+BG!B36 -> Préstamos a largo plazo | H30: 0 | J30: =+BG!E36 -> 330000 | L30: =SUM(H30:J30) -> 330000 | M30: =+L30-BG!E36 -> 0
F31: =+BG!B37 -> Otras aportaciones del Fideicomitente | H31: 0 | J31: =+BG!E37 -> 125867 | L31: =SUM(H31:J31) -> 125867 | M31: =+L31-BG!E37 -> 0
F32: Total de pasivos | G32: $ | H32: =SUM(H27:H31) -> 37961 | I32: $ | J32: =SUM(J27:J31) -> 863817 | K32: $ | L32: =SUM(L27:L31) -> 901778

Sheet N13 Partes relacionadas
B3: 13. Transacciones con partes relacionadas
B5: =+CONCATENATE(Datos!C14,E5) -> Al 31 de diciembre de 2024 y 2023, los saldos con partes relacionadas se integran como sigue: | E5: , los saldos con partes relacionadas se integran como sigue:
G11: =+Datos!C8 -> 2024 | I11: =+Datos!C9 -> 2023
E12: Por cobrar:
E14: Fortem Capital I SC | F14: $ | G14: =ROUND(+O29/1000,0) -> 715 | H14: $ | I14: =+ROUND(Q29/1000,0) -> 715 | N14: Cuentas por cobrar | O14: Saldo 2024 | P14: Saldo 2024 en miles | Q14: Saldo contraparte | R14: Diferencia | S14: Comentarios
E15: Fideicomiso Fortmck 18-08 Cine Apolo | G15: =ROUND(+O30/1000,0) -> 85 | I15: =+ROUND(Q30/1000,0) -> 85 | N15: Proveedor: ( 102 ) FORTEM CAPITAL I SC | O15: 714904.52 | P15: =+O15/1000 -> 714.90452 | Q15: 0 | R15: =+P15-Q15 -> 714.90452 | S15: Diferencia
E16: FC1 Desarrollo SAPI | G16: =ROUND(+O31/1000,0) -> 143 | I16: =+ROUND(Q31/1000,0) -> 143 | N16: Proveedor: ( 109 ) FIDEICOMISO FORTMCK18-08 CINE APOLO | O16: 85231.32 | P16: =+O16/1000 -> 85.23132 | Q16: 85231.32 | R16: =+O16-Q16 -> 0 | S16: Ok
E17: Total | F17: $ | G17: =SUM(G14:G16) -> 943 | H17: $ | I17: =SUM(I14:I16) -> 943 | N17: Proveedor: ( 1975 ) FC1 DESARROLLO S.A.P.I. DE C.V. | O17: 142652.77 | P17: =+O17/1000 -> 142.65277 | Q17: 0 | R17: =+P17-Q17 -> 142.65277 | S17: No disponible
G19: =+Datos!C8 -> 2024 | I19: =+Datos!C9 -> 2023 | N19: Cuentas por pagar | O19: Saldo 2024 | P19: Saldo 2024 en miles | Q19: Saldo contraparte | R19: Diferencia
E20: Por pagar: | N20: Proveedor: ( 101 ) FIDEICOMISO IRREVOCABLE NUMERO 3518 | O20: -1205516.7 | P20: =+O20/1000 -> -1205.5167 | Q20: 0 | R20: =+P20-Q20 -> -1205.5167 | S20: No disponible
N21: Proveedor: ( 101 ) FIDEICOMISO IRREVOCABLE NUMERO 3518 | O21: 0 | P21: =+O21/1000 -> 0 | Q21: 0 | R21: =+P21-Q21 -> 0 | S21: No disponible
E22: Fideicomiso Irrevocable 3518 | F22: $ | G22: =+-ROUND(O45/1000,0) -> 1206 | H22: $ | I22: 0 | N22: Proveedor: ( 103 ) FIDEICOMISO FORTMCK 18-01 TIZAYUCA | O22: 0 | P22: =+O22/1000 -> 0 | Q22: 0 | R22: =+P22-Q22 -> 0 | S22: Ok
E23: Asociación de condominos Almar la Laz AC | G23: =-ROUND(O85/1000,0) -> 977 | I23: =-+ROUND(Q85/1000,0) -> 3872 | N23: Proveedor: ( 107 ) FIDEICOMISO FORTMCK 19-14 PLAZA AC LA PAZ SUR | O23: 0 | P23: =+O23/1000 -> 0 | Q23: 0 | R23: =+P23-Q23 -> 0 | S23: Ok
E24: Fideicomiso Fortmck 19-14 La Paz Sur | G24: 0 | I24: =-ROUND(Q84/1000,0) -> 1384 | N24: Proveedor: ( 113 ) ASOCIACION DE CONDOMINOS ALMAR LA PAZ, AC | O24: -977152.38 | P24: =+O24/1000 -> -977.15238 | Q24: 0 | R24: =+P24-Q24 -> -977.15238 | S24: No disponible
E25: Fideicomiso Fortmck 18-01 Tizayuca | G25: 0 | I25: =-ROUND(Q83/1000,0) -> 468 | N25: Proveedor: ( 1177 ) FIDEICOMISO FORTMC19-18 TROPICANA | O25: 0 | P25: =+O25/1000 -> 0 | Q25: 0 | R25: =+P25-Q25 -> 0 | S25: Ok
E26: Total | F26: $ | G26: =SUM(G22:G25) -> 2183 | H26: $ | I26: =SUM(I22:I25) -> 5724 | R26: =+P26-Q26 -> 0
G28: =+Datos!C8 -> 2024 | I28: =+Datos!C9 -> 2023 | N28: Deudores diversos | O28: Saldo 2024 | P28: Saldo 2024 en miles | Q28: Saldo 2023
E29: Por pagar: | N29: Proveedor: ( 102 ) FORTEM CAPITAL I SC | O29: 714904.52 | P29: =+O29/1000 -> 714.90452 | Q29: 714904.52
N30: Proveedor: ( 109 ) FIDEICOMISO FORTMCK18-08 CINE APOLO | O30: 85231.32 | P30: =+O30/1000 -> 85.23132 | Q30: 85231.32
E31: Fideicomiso Fortem CKD 18 | N31: Proveedor: ( 1975 ) FC1 DESARROLLO S.A.P.I. DE C.V. | O31: 142652.77 | P31: =+O31/1000 -> 142.65277 | Q31: 142652.77
E32: Otras aportaciones del Fideicomitente | F32: $ | G32: =+'N9 Otras Aportaciones Fid'!H18 -> 125867 | H32: $ | I32: 196719 | N32: Proveedor: ( 1111 ) PEQUEÑAS SUPERFICIES DE MEXICO SAPI DE CV | O32: 290000 | P32: =+O32/1000 -> 290
E33: Total | F33: $ | G33: =SUM(G31:G32) -> 125867 | H33: $ | I33: 196719 | N33: Proveedor: ( 1191 ) MUNICIPIO DE NAUCALPAN DE JUAREZ | O33: 2958071.5 | P33: =+O33/1000 -> 2958.0715 | Q33: 1427878.2
N34: Proveedor: ( 1556 ) ROBERTO CUETO STRIMPOPULOS | O34: 171461.97 | P34: =+O34/1000 -> 171.46197 | Q34: 179792.63
G35: =+G33-BG!E37 -> 0 | I35: =+I33-BG!G37 -> 0 | J35: <<Check | N35: Proveedor: ( 1660 ) CFE DISTRIBUCION | O35: 5252394.2 | P35: =+O35/1000 -> 5252.3942
N36: Proveedor: ( 3265 ) SECRETARIA DE MEDIO AMBIENTE Y RECURSOS NATURALES | O36: 44551 | P36: =+O36/1000 -> 44.551
N37: Proveedor: ( 3311 ) SECRETARIA DE FINANZAS ESTADO DE MEXICO | O37: 3939 | P37: =+O37/1000 -> 3.939 | Q37: 3939
N38: Proveedor: ( 3325 ) ANA LILIA JANETH PORRAS FIGUEROA | O38: 934029.01 | P38: =+O38/1000 -> 934.02901 | Q38: 1405829
N39: Proveedor: ( 3329 ) LASALLE PARTNERS S DE RL DE CV | O39: 85028 | P39: =+O39/1000 -> 85.028 | Q39: 85028
N40: Proveedor: ( 3334 ) GOBIERNO DEL ESTADO DE MEXICO | O40: 7713344 | P40: =+O40/1000 -> 7713.344 | Q40: 5903620
N41: Proveedor: ( 3423 ) TALLER GLOBAL, S.C. | O41: 435417.43 | P41: =+O41/1000 -> 435.41743 | Q41: 2467.65
N42: Proveedor: ( 25 ) VICTOR MANUEL LIRA ESTRELLA
O44: Saldo 2024 | P44: Saldo en miles | Q44: Saldo 2023 | R44: Clasificación
N45: Proveedor: ( 101 ) FIDEICOMISO IRREVOCABLE NUMERO 3518 | O45: -1205516.7 | P45: =+O45/1000 -> -1205.5167 | R45: Otros Proveedores
N46: Proveedor: ( 205 ) BANCO ACTINVER S.A., INSTITUCION DE BANCA MULTIPLE, GRUPO FINANCIERO ACTINVER | O46: -6960 | P46: =+O46/1000 -> -6.96 | Q46: -6960 | R46: Otros Proveedores
N47: Proveedor: ( 1061 ) BLUEPATH, S.A. DE C.V. | O47: -7571.32 | P47: =+O47/1000 -> -7.57132 | Q47: -9941.2 | R47: Otros Proveedores
N48: Proveedor: ( 1108 ) CUERPO DE VIGILANCIA AUXILIAR Y URBANA DEL ESTADO DE MEXICO | O48: -153358.24 | P48: =+O48/1000 -> -153.35824 | Q48: -290164.8 | R48: Administrativos de obra
N49: Proveedor: ( 1556 ) ROBERTO CUETO STRIMPOPULOS | O49: -43851.37 | P49: =+O49/1000 -> -43.85137 | Q49: -8330.66 | R49: Administrativos de obra
N50: Proveedor: ( 1660 ) CFE DISTRIBUCION | O50: -2886509.2 | P50: =+O50/1000 -> -2886.5092 | R50: Relacionados a energia electriac
N51: Proveedor: ( 1995 ) AMIRA KARAM MORALES | O51: -171 | P51: =+O51/1000 -> -0.171 | R51: Administrativos de obra
N52: Proveedor: ( 3325 ) ANA LILIA JANETH PORRAS FIGUEROA | O52: -1579983 | P52: =+O52/1000 -> -1579.983 | Q52: -2077337.8 | R52: Administrativos de obra
N53: Proveedor: ( 3350 ) GRUPO CONSTRUCTOR ACTUM SA DE CV | O53: -850400 | P53: =+O53/1000 -> -850.4 | R53: Construcción y desarrollo
N54: Proveedor: ( 3360 ) THREE CONSULTORIA MEDIOAMBIENTAL SA DE CV | O54: -353089.72 | P54: =+O54/1000 -> -353.08972 | R54: Consultoría en desarrollo y construccion
N55: Proveedor: ( 3361 ) INGENIERIA Y CONSTRUCCIONES GABE SA DE CV | O55: -935365.14 | P55: =+O55/1000 -> -935.36514 | R55: Construcción y desarrollo
N56: Proveedor: ( 3367 ) GRUPO CULUMBIO MEXICO SA DE CV | O56: -12467641 | P56: =+O56/1000 -> -12467.641 | R56: Construcción y desarrollo
N57: Proveedor: ( 3422 ) INDUSTRIAL DE ASFALTOS Y PAVIMENTOS SA DE CV | O57: -2139981.6 | P57: =+O57/1000 -> -2139.9816 | R57: Construcción y desarrollo
N58: Proveedor: ( 3428 ) CONTROL LOGISTICO Y ADMINISTRADORA DE VALVULAS Y EQUIPOS SA DE CV | O58: -12909332 | P58: =+O58/1000 -> -12909.332 | R58: Construcción y desarrollo
N59: Proveedor: ( 3440 ) TGC GEOTECNIA SA DE CV | O59: -206909.2 | P59: =+O59/1000 -> -206.9092 | R59: Construcción y desarrollo
N60: Proveedor: ( 3548 ) CUARTAGO CONSULTORES SA DE CV | O60: -87000 | P60: =+O60/1000 -> -87 | R60: Consultoría en desarrollo y construccion
N61: Proveedor: ( 3561 ) ISIDRO MORENO CAMACHO | O61: -8700 | P61: =+O61/1000 -> -8.7 | R61: Administrativos de obra
N62: Proveedor: ( 3565 ) ESENCIA REPUTACIONAL SC | O62: -136300 | P62: =+O62/1000 -> -136.3 | R62: Construcción y desarrollo
N63: Proveedor: ( 25 ) VICTOR MANUEL LIRA ESTRELLA | Q63: -2467.65 | R63: Administrativos de obra
N64: Proveedor: ( 1081 ) Notaria 211 y 135 de la Ciudad de México | Q64: -8068 | R64: Administrativos de obra
N65: Proveedor: ( 1153 ) CORPORATIVO PYCESA S.A. DE C.V. | Q65: -1722106.7 | R65: Construcción y desarrollo
N66: Proveedor: ( 1798 ) WRIGHT ADMON, S.A.DE C.V. | Q66: -1160 | R66: Administrativos de obra
N67: Proveedor: ( 2529 ) LUCIANO MEDINA ELENO | Q67: -416333.2 | R67: Administrativos de obra
N68: Proveedor: ( 2607 ) ITEGRA-HEXABYTE, S.A. DE C.V. | Q68: -59344.83 | R68: Construcción y desarrollo
N69: Proveedor: ( 2692 ) FPMEXICO ABOGADOS, S.A. | Q69: -870000 | R69: Consultoría en desarrollo y construccion
N70: Proveedor: ( 3339 ) DEOLIVASE SA DE CV | Q70: -15080 | R70: Construcción y desarrollo
N71: Proveedor: ( 3342 ) IYG PROYECTO, CONSTRUCCION Y MANTENIMIENTO SA DE CV | Q71: -101110.7 | R71: Construcción y desarrollo
N72: Proveedor: ( 3343 ) CAPSTONE ADVISORS, SC | Q72: -52200 | R72: Construcción y desarrollo
N73: Proveedor: ( 3345 ) AMELO INFRAESTRUCTURA SA DE CV | Q73: -1421000 | R73: Administrativos de obra
N74: Proveedor: ( 3353 ) CONSORCIO CONSTRUCTOR AA SA DE CV | Q74: -153236 | R74: Construcción y desarrollo
... N77: Proveedor: ( 4000 ) FFM CONSUMO SA DE CV | Q77: -91640 | R77: Consultoría en desarrollo y construccion
N81: Acreedores | O81: Saldo 2024 | P81: Saldo en miles | Q81: Saldo 2023
N82: Proveedor: ( 101 ) FIDEICOMISO IRREVOCABLE NUMERO 3518 | O82: 0 | P82: =+O82/1000 -> 0
N83: Proveedor: ( 103 ) FIDEICOMISO FORTMCK 18-01 TIZAYUCA | O83: 0 | P83: =+O83/1000 -> 0 | Q83: -467943
N84: Proveedor: ( 107 ) FIDEICOMISO FORTMCK 19-14 PLAZA AC LA PAZ SUR | O84: 0 | P84: =+O84/1000 -> 0 | Q84: -1384076
N85: Proveedor: ( 113 ) ASOCIACION DE CONDOMINOS ALMAR LA PAZ, AC | O85: -977152.38 | P85: =+O85/1000 -> -977.15238 | Q85: -3871514
N86: Proveedor: ( 1177 ) FIDEICOMISO FORTMC19-18 TROPICANA | O86: 0 | P86: =+O86/1000 -> 0
N87: Proveedor: ( 3304 ) MAAT ABOGADOS SC | O87: 0 | P87: =+O87/1000 -> 0
N88: Proveedor: ( 3430 ) GRUPO DESARROLLADOR SEQUOYA SA DE CV / VELEMENT SA DE CV | O88: -500000 | P88: =+O88/1000 -> -500
N89: Proveedor: ( 3839 ) DEPOSITOS POR IDENTIFICAR | O89: -505000 | P89: =+O89/1000 -> -505

Sheet Nota de la 14 en adelante
B4: 14. Contingencias
B6: Al 31 de diciembre de 2024 y 2023, como consecuencia de las operaciones propias de su actividad, el Fideicomiso identifica, monitorea y evalúa diversos criterios o asuntos que pudieran representar una contingencia económica, fiscal o reputacional, los cuales se comunican a los responsables del gobierno de la entidad ya que por su naturaleza pueden tener impacto en el futuro en caso de que cambien las circunstancias actuales. En este sentido, el Juicio Ordinario Civil 1047/2022 promovido por Fraccionamientos y Construcciones en contra del Fideicomiso ACTINVER F/4341 concluyó con sentencia definitiva del 13 de diciembre de 2023 que absolvió al fideicomiso de las reclamaciones presentadas. La sentencia fue confirmada en apelación y actualmente se encuentra en trámite un Juicio de Amparo Directo, sin que se prevea un impacto económico relevante. | E6: , como consecuencia de las operaciones propias de su actividad, el Fideicomiso identifica, monitorea y evalúa diversos criterios o asuntos que pudieran representar una contingencia económica, fiscal o reputacional, los cuales están comunicados a los responsables del gobierno de la entidad ya que por su naturaleza pueden tener impacto en el futuro en caso de que cambien las circunstancias actuales, sin embargo, en opinión de la Administración y de sus asesores legales, fiscales y laborales internos y externos considera que los mismos no representan pasivos contingentes a esa fecha ya que no ha recibido reclamos y no ha sido emplazada a juicios materiales que sean cuantificables de manera confiable.
B8: Durante el mes de agosto de 2024 se ordenó la suspensión provisional de la obra "Terralago" relacionada con el Juicio de Amparo Indirecto 1018/2024, derivada de la solicitud presentada por vecinos del Fraccionamiento Lomas Verdes. El equipo jurídico del Fideicomiso atendió el procedimiento hasta que, el 2 de diciembre de 2024, se dictó Sentencia Interlocutoria favorable al Fideicomiso, en la que se negó la suspensión definitiva solicitada y se levantó la suspensión provisional otorgada previamente, por lo que al cierre de 2024 el proyecto se encontraba operando con normalidad. Con base en la confirmación de los asesores legales externos, se considera que el procedimiento carece de fundamentos suficientes y existe alta probabilidad de que la resolución final sea favorable al Fideicomiso, por lo que la probabilidad de pérdida se considera remota.
B10: Derivado de la suspensión provisional de la obra durante el mes de agosto y hasta el 2 de diciembre de 2024, el Fideicomiso realizó los ajustes necesarios al presupuesto de avance físico-financiero de la obra, así como a su presupuesto económico general, considerando las diligencias y gestiones derivadas de dicho paro. Dichos ajustes fueron evaluados y autorizados por el Comité Interno y los responsables del proyecto, asegurando que los efectos identificados quedaran debidamente considerados en los presupuestos revisados. Derivado de lo anterior, el Fideicomiso reconoció en resultados los gastos incurridos por diversos trámites relacionados con este juicio. En consecuencia, el Fideicomiso considera que no existen pasivos contingentes adicionales que deban reconocerse contablemente, ya que no se han recibido reclamaciones firmes ni existen juicios que puedan ser cuantificables de manera confiable en su resultado adverso. Finalmente, al 31 de diciembre de 2024, no se tiene conocimiento de otros reclamos o gravámenes en curso.
B12: De acuerdo con la legislación fiscal vigente, las autoridades tienen la facultad de revisar los cinco ejercicios fiscales anteriores a la última declaración del Impuesto Sobre la Renta (ISR) presentada.
B15: 15. Compromisos contraídos
B17: =+CONCATENATE(Datos!C19,E17) -> El Fideicomiso al 31 de diciembre de 2024, cuenta con compromisos propios de la operación y los que se mencionan en la Nota 9 de “Otras aportaciones del Fideicomitente ". | E17: , cuenta con compromisos propios de la operación y los que se mencionan en la Nota 9 de “Otras aportaciones del Fideicomitente ".
B20: 16. Autorización de la emisión de los estados financieros
B22: =+CONCATENATE("Los estados financieros y las notas a los mismos fueron autorizados para su emisión y publicación el ",Datos!C10,", por Ignacio García de Quevedo Gómez Gallardo - Director de Administración y Finanzas, y están sujetas a la aprobación del Comité Técnico y Administrador del Fideicomiso.") -> Los estados financieros y las notas a los mismos fueron autorizados para su emisión y publicación el 30 de abril de 2025, por Ignacio García de Quevedo Gómez Gallardo - Director de Administración y Finanzas, y están sujetas a la aprobación del Comité Técnico y Administrador del Fideicomiso.
